Workbook

Sheet Bioenergy_Data
A1: Owner | B1: Fuel | C1: Fuel (no space after comma) | D1: Fuel 1 | E1: Fuel 2 | F1: Fuel 3 | G1: Capacity (MW) | H1: Status | I1: Start Year | J1: Retired Year | K1: Latitude | L1: Longitude | M1: Country/Area | N1: Generation (TWh) | O1: Emission Factor (kg CO2/ mmBtu) | P1: Fuel Consumption (mmBtu) | Q1: CO2 Emissions (g CO2) | R1: Carbon Intensity (g CO2/ kWh)
A2: bh energy gap llp | B2: bioenergy: refuse (municipal and industrial wastes) | C2: =SUBSTITUTE(Table1[[#This Row],[Fuel]],", ",",") -> bioenergy: refuse (municipal and industrial wastes) | D2: bioenergy: refuse (municipal and industrial wastes) | G2: 44 | H2: pre-construction | I2: 2027 | J2: N/A | K2: 52.6086 | L2: -2.0103 | M2: united kingdom | N2: =Table1[[#This Row],[Capacity (MW)]]*8760*0.72*10^-6 -> 0.2775168 | O2: {=AVERAGE(VLOOKUP(_xlfn.TEXTSPLIT(Table1[[#This Row],[Fuel (no space after comma)]], ","), FuelList_Final_EF!$A$2:$B$32, 2, FALSE))} -> 105.42963 | P2: =(16112*Table1[[#This Row],[Generation (TWh)]]*10^9)/10^6 -> 4471350.7 | Q2: =Table1[[#This Row],[Emission Factor (kg CO2/ mmBtu)]]*Table1[[#This Row],[Fuel Consumption (mmBtu)]]*10^3 -> 4.7141283e+11 | R2: =(Table1[[#This Row],[CO2 Emissions (g CO2)]])/(Table1[[#This Row],[Generation (TWh)]]*10^9) -> 1698.6821 | T2: =AVERAGE(Table1[Carbon Intensity (g CO2/ kWh)]) -> 1682.2644
A3: metsä fibre oy | B3: bioenergy: wood & other biomass (solids), bioenergy: wood & other biomass (syngas) | C3: =SUBSTITUTE(Table1[[#This Row],[Fuel]],", ",",") -> bioenergy: wood & other biomass (solids),bioenergy: wood & other biomass (syngas) | D3: bioenergy: wood & other biomass (solids) | E3: bioenergy: wood & other biomass (syngas) | G3: 260 | H3: operating | I3: 2017 | J3: N/A | K3: 62.5908 | L3: 25.7522 | M3: finland | N3: =Table1[[#This Row],[Capacity (MW)]]*8760*0.72*10^-6 -> 1.639872 | O3: {=AVERAGE(VLOOKUP(_xlfn.TEXTSPLIT(Table1[[#This Row],[Fuel (no space after comma)]], ","), FuelList_Final_EF!$A$2:$B$32, 2, FALSE))} -> 70.305377 | P3: =(16112*Table1[[#This Row],[Generation (TWh)]]*10^9)/10^6 -> 26421618 | Q3: =Table1[[#This Row],[Emission Factor (kg CO2/ mmBtu)]]*Table1[[#This Row],[Fuel Consumption (mmBtu)]]*10^3 -> 1.8575818e+12 | R3: =(Table1[[#This Row],[CO2 Emissions (g CO2)]])/(Table1[[#This Row],[Generation (TWh)]]*10^9) -> 1132.7602
A4: renergy group partners llc | B4: bioenergy: refuse (municipal and industrial wastes) | C4: =SUBSTITUTE(Table1[[#This Row],[Fuel]],", ",",") -> bioenergy: refuse (municipal and industrial wastes) | D4: bioenergy: refuse (municipal and industrial wastes) | G4: 30 | H4: pre-construction | I4: 2026 | J4: N/A | K4: 30.042122 | L4: 31.095022 | M4: egypt | N4: =Table1[[#This Row],[Capacity (MW)]]*8760*0.72*10^-6 -> 0.189216 | O4: {=AVERAGE(VLOOKUP(_xlfn.TEXTSPLIT(Table1[[#This Row],[Fuel (no space after comma)]], ","), FuelList_Final_EF!$A$2:$B$32, 2, FALSE))} -> 105.42963 | P4: =(16112*Table1[[#This Row],[Generation (TWh)]]*10^9)/10^6 -> 3048648.2 | Q4: =Table1[[#This Row],[Emission Factor (kg CO2/ mmBtu)]]*Table1[[#This Row],[Fuel Consumption (mmBtu)]]*10^3 -> 3.2141784e+11 | R4: =(Table1[[#This Row],[CO2 Emissions (g CO2)]])/(Table1[[#This Row],[Generation (TWh)]]*10^9) -> 1698.6821
A5: e.on värme sverige ab | B5: bioenergy: wood & other biomass (solids), fossil liquids: waste/other oil | C5: =SUBSTITUTE(Table1[[#This Row],[Fuel]],", ",",") -> bioenergy: wood & other biomass (solids),fossil liquids: waste/other oil | D5: bioenergy: wood & other biomass (solids) | E5: fossil liquids: waste/other oil | G5: 100 | H5: operating | I5: 1974 | J5: N/A | K5: 59.2649 | L5: 15.1772 | M5: sweden | N5: =Table1[[#This Row],[Capacity (MW)]]*8760*0.72*10^-6 -> 0.63072 | O5: {=AVERAGE(VLOOKUP(_xlfn.TEXTSPLIT(Table1[[#This Row],[Fuel (no space after comma)]], ","), FuelList_Final_EF!$A$2:$B$32, 2, FALSE))} -> 85.539958 | P5: =(16112*Table1[[#This Row],[Generation (TWh)]]*10^9)/10^6 -> 10162161 | Q5: =Table1[[#This Row],[Emission Factor (kg CO2/ mmBtu)]]*Table1[[#This Row],[Fuel Consumption (mmBtu)]]*10^3 -> 8.6927079e+11 | R5: =(Table1[[#This Row],[CO2 Emissions (g CO2)]])/(Table1[[#This Row],[Generation (TWh)]]*10^9) -> 1378.2198
A6: fri el green power spa | B6: bioenergy: biodiesel | C6: =SUBSTITUTE(Table1[[#This Row],[Fuel]],", ",",") -> bioenergy: biodiesel | D6: bioenergy: biodiesel | G6: 68 | H6: operating | I6: 2008 | J6: N/A | K6: 40.9744 | L6: 14.3766 | M6: italy | N6: =Table1[[#This Row],[Capacity (MW)]]*8760*0.72*10^-6 -> 0.4288896 | O6: {=AVERAGE(VLOOKUP(_xlfn.TEXTSPLIT(Table1[[#This Row],[Fuel (no space after comma)]], ","), FuelList_Final_EF!$A$2:$B$32, 2, FALSE))} -> 73.84 | P6: =(16112*Table1[[#This Row],[Generation (TWh)]]*10^9)/10^6 -> 6910269.2 | Q6: =Table1[[#This Row],[Emission Factor (kg CO2/ mmBtu)]]*Table1[[#This Row],[Fuel Consumption (mmBtu)]]*10^3 -> 5.1025428e+11 | R6: =(Table1[[#This Row],[CO2 Emissions (g CO2)]])/(Table1[[#This Row],[Generation (TWh)]]*10^9) -> 1189.7101
A7: a2a spa | B7: bioenergy: refuse (municipal and industrial wastes) | C7: =SUBSTITUTE(Table1[[#This Row],[Fuel]],", ",",") -> bioenergy: refuse (municipal and industrial wastes) | D7: bioenergy: refuse (municipal and industrial wastes) | G7: 36 | H7: operating | I7: 2009 | J7: N/A | K7: 40.9791 | L7: 14.3828 | M7: italy | N7: =Table1[[#This Row],[Capacity (MW)]]*8760*0.72*10^-6 -> 0.2270592 | O7: {=AVERAGE(VLOOKUP(_xlfn.TEXTSPLIT(Table1[[#This Row],[Fuel (no space after comma)]], ","), FuelList_Final_EF!$A$2:$B$32, 2, FALSE))} -> 105.42963 | P7: =(16112*Table1[[#This Row],[Generation (TWh)]]*10^9)/10^6 -> 3658377.8 | Q7: =Table1[[#This Row],[Emission Factor (kg CO2/ mmBtu)]]*Table1[[#This Row],[Fuel Consumption (mmBtu)]]*10^3 -> 3.8570141e+11 | R7: =(Table1[[#This Row],[CO2 Emissions (g CO2)]])/(Table1[[#This Row],[Generation (TWh)]]*10^9) -> 1698.6821
A8: a2a spa | B8: bioenergy: refuse (municipal and industrial wastes) | C8: =SUBSTITUTE(Table1[[#This Row],[Fuel]],", ",",") -> bioenergy: refuse (municipal and industrial wastes) | D8: bioenergy: refuse (municipal and industrial wastes) | G8: 36 | H8: operating | I8: 2009 | J8: N/A | K8: 40.9791 | L8: 14.3828 | M8: italy | N8: =Table1[[#This Row],[Capacity (MW)]]*8760*0.72*10^-6 -> 0.2270592 | O8: {=AVERAGE(VLOOKUP(_xlfn.TEXTSPLIT(Table1[[#This Row],[Fuel (no space after comma)]], ","), FuelList_Final_EF!$A$2:$B$32, 2, FALSE))} -> 105.42963 | P8: =(16112*Table1[[#This Row],[Generation (TWh)]]*10^9)/10^6 -> 3658377.8 | Q8: =Table1[[#This Row],[Emission Factor (kg CO2/ mmBtu)]]*Table1[[#This Row],[Fuel Consumption (mmBtu)]]*10^3 -> 3.8570141e+11 | R8: =(Table1[[#This Row],[CO2 Emissions (g CO2)]])/(Table1[[#This Row],[Generation (TWh)]]*10^9) -> 1698.6821
A9: a2a spa | B9: bioenergy: refuse (municipal and industrial wastes) | C9: =SUBSTITUTE(Table1[[#This Row],[Fuel]],", ",",") -> bioenergy: refuse (municipal and industrial wastes) | D9: bioenergy: refuse (municipal and industrial wastes) | G9: 36 | H9: operating | I9: 2009 | J9: N/A | K9: 40.9791 | L9: 14.3828 | M9: italy | N9: =Table1[[#This Row],[Capacity (MW)]]*8760*0.72*10^-6 -> 0.2270592 | O9: {=AVERAGE(VLOOKUP(_xlfn.TEXTSPLIT(Table1[[#This Row],[Fuel (no space after comma)]], ","), FuelList_Final_EF!$A$2:$B$32, 2, FALSE))} -> 105.42963 | P9: =(16112*Table1[[#This Row],[Generation (TWh)]]*10^9)/10^6 -> 3658377.8 | Q9: =Table1[[#This Row],[Emission Factor (kg CO2/ mmBtu)]]*Table1[[#This Row],[Fuel Consumption (mmBtu)]]*10^3 -> 3.8570141e+11 | R9: =(Table1[[#This Row],[CO2 Emissions (g CO2)]])/(Table1[[#This Row],[Generation (TWh)]]*10^9) -> 1698.6821
A10: N/A | B10: bioenergy: refuse (municipal and industrial wastes) | C10: =SUBSTITUTE(Table1[[#This Row],[Fuel]],", ",",") -> bioenergy: refuse (municipal and industrial wastes) | D10: bioenergy: refuse (municipal and industrial wastes) | G10: 125 | H10: operating | I10: 1997 | J10: N/A | K10: 51.683 | L10: 4.5805 | M10: netherlands | N10: =Table1[[#This Row],[Capacity (MW)]]*8760*0.72*10^-6 -> 0.7884 | O10: {=AVERAGE(VLOOKUP(_xlfn.TEXTSPLIT(Table1[[#This Row],[Fuel (no space after comma)]], ","), FuelList_Final_EF!$A$2:$B$32, 2, FALSE))} -> 105.42963 | P10: =(16112*Table1[[#This Row],[Generation (TWh)]]*10^9)/10^6 -> 12702701 | Q10: =Table1[[#This Row],[Emission Factor (kg CO2/ mmBtu)]]*Table1[[#This Row],[Fuel Consumption (mmBtu)]]*10^3 -> 1.339241e+12 | R10: =(Table1[[#This Row],[CO2 Emissions (g CO2)]])/(Table1[[#This Row],[Generation (TWh)]]*10^9) -> 1698.6821
A11: aeb exploitatie bv | B11: bioenergy: refuse (municipal and industrial wastes), bioenergy: wastewater and sewage sludge (solids or biogas) | C11: =SUBSTITUTE(Table1[[#This Row],[Fuel]],", ",",") -> bioenergy: refuse (municipal and industrial wastes),bioenergy: wastewater and sewage sludge (solids or biogas) | D11: bioenergy: refuse (municipal and industrial wastes) | E11: bioenergy: wastewater and sewage sludge (solids or biogas) | G11: 39 | H11: operating | I11: 1993 | J11: N/A | K11: 52.4011 | L11: 4.7935 | M11: netherlands | N11: =Table1[[#This Row],[Capacity (MW)]]*8760*0.72*10^-6 -> 0.2459808 | O11: {=AVERAGE(VLOOKUP(_xlfn.TEXTSPLIT(Table1[[#This Row],[Fuel (no space after comma)]], ","), FuelList_Final_EF!$A$2:$B$32, 2, FALSE))} -> 81.497101 | P11: =(16112*Table1[[#This Row],[Generation (TWh)]]*10^9)/10^6 -> 3963242.6 | Q11: =Table1[[#This Row],[Emission Factor (kg CO2/ mmBtu)]]*Table1[[#This Row],[Fuel Consumption (mmBtu)]]*10^3 -> 3.2299279e+11 | R11: =(Table1[[#This Row],[CO2 Emissions (g CO2)]])/(Table1[[#This Row],[Generation (TWh)]]*10^9) -> 1313.0813
A12: aeb exploitatie bv | B12: bioenergy: refuse (municipal and industrial wastes), bioenergy: wastewater and sewage sludge (solids or biogas) | C12: =SUBSTITUTE(Table1[[#This Row],[Fuel]],", ",",") -> bioenergy: refuse (municipal and industrial wastes),bioenergy: wastewater and sewage sludge (solids or biogas) | D12: bioenergy: refuse (municipal and industrial wastes) | E12: bioenergy: wastewater and sewage sludge (solids or biogas) | G12: 72 | H12: operating | I12: 2007 | J12: N/A | K12: 52.4011 | L12: 4.7935 | M12: netherlands | N12: =Table1[[#This Row],[Capacity (MW)]]*8760*0.72*10^-6 -> 0.4541184 | O12: {=AVERAGE(VLOOKUP(_xlfn.TEXTSPLIT(Table1[[#This Row],[Fuel (no space after comma)]], ","), FuelList_Final_EF!$A$2:$B$32, 2, FALSE))} -> 81.497101 | P12: =(16112*Table1[[#This Row],[Generation (TWh)]]*10^9)/10^6 -> 7316755.7 | Q12: =Table1[[#This Row],[Emission Factor (kg CO2/ mmBtu)]]*Table1[[#This Row],[Fuel Consumption (mmBtu)]]*10^3 -> 5.9629437e+11 | R12: =(Table1[[#This Row],[CO2 Emissions (g CO2)]])/(Table1[[#This Row],[Generation (TWh)]]*10^9) -> 1313.0813
A13: N/A | B13: bioenergy: agricultural waste (biogas) | C13: =SUBSTITUTE(Table1[[#This Row],[Fuel]],", ",",") -> bioenergy: agricultural waste (biogas) | D13: bioenergy: agricultural waste (biogas) | G13: 1058 | H13: operating | I13: 2017 | J13: N/A | K13: -2.7165 | L13: 101.3702 | M13: indonesia | N13: =Table1[[#This Row],[Capacity (MW)]]*8760*0.72*10^-6 -> 6.6730176 | O13: {=AVERAGE(VLOOKUP(_xlfn.TEXTSPLIT(Table1[[#This Row],[Fuel (no space after comma)]], ","), FuelList_Final_EF!$A$2:$B$32, 2, FALSE))} -> 52.07 | P13: =(16112*Table1[[#This Row],[Generation (TWh)]]*10^9)/10^6 -> 1.0751566e+08 | Q13: =Table1[[#This Row],[Emission Factor (kg CO2/ mmBtu)]]*Table1[[#This Row],[Fuel Consumption (mmBtu)]]*10^3 -> 5.5983404e+12 | R13: =(Table1[[#This Row],[CO2 Emissions (g CO2)]])/(Table1[[#This Row],[Generation (TWh)]]*10^9) -> 838.95184
A14: agroaurora sac | B14: bioenergy: agricultural waste (solids) | C14: =SUBSTITUTE(Table1[[#This Row],[Fuel]],", ",",") -> bioenergy: agricultural waste (solids) | D14: bioenergy: agricultural waste (solids) | G14: 38 | H14: operating | I14: 2012 | J14: N/A | K14: -4.9279 | L14: -80.8491 | M14: peru | N14: =Table1[[#This Row],[Capacity (MW)]]*8760*0.72*10^-6 -> 0.2396736 | O14: {=AVERAGE(VLOOKUP(_xlfn.TEXTSPLIT(Table1[[#This Row],[Fuel (no space after comma)]], ","), FuelList_Final_EF!$A$2:$B$32, 2, FALSE))} -> 118.17 | P14: =(16112*Table1[[#This Row],[Generation (TWh)]]*10^9)/10^6 -> 3861621 | Q14: =Table1[[#This Row],[Emission Factor (kg CO2/ mmBtu)]]*Table1[[#This Row],[Fuel Consumption (mmBtu)]]*10^3 -> 4.5632776e+11 | R14: =(Table1[[#This Row],[CO2 Emissions (g CO2)]])/(Table1[[#This Row],[Generation (TWh)]]*10^9) -> 1903.955
A15: agropéu agro industrial de pompéu sa | B15: bioenergy: agricultural waste (solids) | C15: =SUBSTITUTE(Table1[[#This Row],[Fuel]],", ",",") -> bioenergy: agricultural waste (solids) | D15: bioenergy: agricultural waste (solids) | G15: 52 | H15: operating | I15: 2016 | J15: N/A | K15: -19.2517 | L15: -44.985 | M15: brazil | N15: =Table1[[#This Row],[Capacity (MW)]]*8760*0.72*10^-6 -> 0.3279744 | O15: {=AVERAGE(VLOOKUP(_xlfn.TEXTSPLIT(Table1[[#This Row],[Fuel (no space after comma)]], ","), FuelList_Final_EF!$A$2:$B$32, 2, FALSE))} -> 118.17 | P15: =(16112*Table1[[#This Row],[Generation (TWh)]]*10^9)/10^6 -> 5284323.5 | Q15: =Table1[[#This Row],[Emission Factor (kg CO2/ mmBtu)]]*Table1[[#This Row],[Fuel Consumption (mmBtu)]]*10^3 -> 6.2444851e+11 | R15: =(Table1[[#This Row],[CO2 Emissions (g CO2)]])/(Table1[[#This Row],[Generation (TWh)]]*10^9) -> 1903.955
A16: the aichi gamagori biomass power generation llc | B16: bioenergy: wood & other biomass (solids) | C16: =SUBSTITUTE(Table1[[#This Row],[Fuel]],", ",",") -> bioenergy: wood & other biomass (solids) | D16: bioenergy: wood & other biomass (solids) | G16: 50 | H16: operating | I16: 2023 | J16: N/A | K16: 34.8052 | L16: 137.208 | M16: japan | N16: =Table1[[#This Row],[Capacity (MW)]]*8760*0.72*10^-6 -> 0.31536 | O16: {=AVERAGE(VLOOKUP(_xlfn.TEXTSPLIT(Table1[[#This Row],[Fuel (no space after comma)]], ","), FuelList_Final_EF!$A$2:$B$32, 2, FALSE))} -> 93.8 | P16: =(16112*Table1[[#This Row],[Generation (TWh)]]*10^9)/10^6 -> 5081080.3 | Q16: =Table1[[#This Row],[Emission Factor (kg CO2/ mmBtu)]]*Table1[[#This Row],[Fuel Consumption (mmBtu)]]*10^3 -> 4.7660533e+11 | R16: =(Table1[[#This Row],[CO2 Emissions (g CO2)]])/(Table1[[#This Row],[Generation (TWh)]]*10^9) -> 1511.3056
A17: osaka gas co ltd | B17: bioenergy: wood & other biomass (solids) | C17: =SUBSTITUTE(Table1[[#This Row],[Fuel]],", ",",") -> bioenergy: wood & other biomass (solids) | D17: bioenergy: wood & other biomass (solids) | G17: 18.75 | H17: construction | I17: 2024 | J17: N/A | K17: 34.7004 | L17: 137.249 | M17: japan | N17: =Table1[[#This Row],[Capacity (MW)]]*8760*0.72*10^-6 -> 0.11826 | O17: {=AVERAGE(VLOOKUP(_xlfn.TEXTSPLIT(Table1[[#This Row],[Fuel (no space after comma)]], ","), FuelList_Final_EF!$A$2:$B$32, 2, FALSE))} -> 93.8 | P17: =(16112*Table1[[#This Row],[Generation (TWh)]]*10^9)/10^6 -> 1905405.1 | Q17: =Table1[[#This Row],[Emission Factor (kg CO2/ mmBtu)]]*Table1[[#This Row],[Fuel Consumption (mmBtu)]]*10^3 -> 178727000256 | R17: =(Table1[[#This Row],[CO2 Emissions (g CO2)]])/(Table1[[#This Row],[Generation (TWh)]]*10^9) -> 1511.3056
A18: other | B18: bioenergy: wood & other biomass (solids) | C18: =SUBSTITUTE(Table1[[#This Row],[Fuel]],", ",",") -> bioenergy: wood & other biomass (solids) | D18: bioenergy: wood & other biomass (solids) | G18: 56.25 | H18: construction | I18: 2024 | J18: N/A | K18: 34.7004 | L18: 137.249 | M18: japan | N18: =Table1[[#This Row],[Capacity (MW)]]*8760*0.72*10^-6 -> 0.35478 | O18: {=AVERAGE(VLOOKUP(_xlfn.TEXTSPLIT(Table1[[#This Row],[Fuel (no space after comma)]], ","), FuelList_Final_EF!$A$2:$B$32, 2, FALSE))} -> 93.8 | P18: =(16112*Table1[[#This Row],[Generation (TWh)]]*10^9)/10^6 -> 5716215.4 | Q18: =Table1[[#This Row],[Emission Factor (kg CO2/ mmBtu)]]*Table1[[#This Row],[Fuel Consumption (mmBtu)]]*10^3 -> 536181000768 | R18: =(Table1[[#This Row],[CO2 Emissions (g CO2)]])/(Table1[[#This Row],[Generation (TWh)]]*10^9) -> 1511.3056
A19: kansai electric power co | B19: bioenergy: wood & other biomass (solids) | C19: =SUBSTITUTE(Table1[[#This Row],[Fuel]],", ",",") -> bioenergy: wood & other biomass (solids) | D19: bioenergy: wood & other biomass (solids) | G19: 200 | H19: operating | I19: 1982 | J19: N/A | K19: 34.774809 | L19: 134.45725 | M19: japan | N19: =Table1[[#This Row],[Capacity (MW)]]*8760*0.72*10^-6 -> 1.26144 | O19: {=AVERAGE(VLOOKUP(_xlfn.TEXTSPLIT(Table1[[#This Row],[Fuel (no space after comma)]], ","), FuelList_Final_EF!$A$2:$B$32, 2, FALSE))} -> 93.8 | P19: =(16112*Table1[[#This Row],[Generation (TWh)]]*10^9)/10^6 -> 20324321 | Q19: =Table1[[#This Row],[Emission Factor (kg CO2/ mmBtu)]]*Table1[[#This Row],[Fuel Consumption (mmBtu)]]*10^3 -> 1.9064213e+12 | R19: =(Table1[[#This Row],[CO2 Emissions (g CO2)]])/(Table1[[#This Row],[Generation (TWh)]]*10^9) -> 1511.3056
A20: alternative generating company 1 llc | B20: bioenergy: refuse (municipal and industrial wastes) | C20: =SUBSTITUTE(Table1[[#This Row],[Fuel]],", ",",") -> bioenergy: refuse (municipal and industrial wastes) | D20: bioenergy: refuse (municipal and industrial wastes) | G20: 70 | H20: construction | I20: 2024 | J20: N/A | K20: 55.676358 | L20: 38.241705 | M20: russia | N20: =Table1[[#This Row],[Capacity (MW)]]*8760*0.72*10^-6 -> 0.441504 | O20: {=AVERAGE(VLOOKUP(_xlfn.TEXTSPLIT(Table1[[#This Row],[Fuel (no space after comma)]], ","), FuelList_Final_EF!$A$2:$B$32, 2, FALSE))} -> 105.42963 | P20: =(16112*Table1[[#This Row],[Generation (TWh)]]*10^9)/10^6 -> 7113512.4 | Q20: =Table1[[#This Row],[Emission Factor (kg CO2/ mmBtu)]]*Table1[[#This Row],[Fuel Consumption (mmBtu)]]*10^3 -> 7.4997495e+11 | R20: =(Table1[[#This Row],[CO2 Emissions (g CO2)]])/(Table1[[#This Row],[Generation (TWh)]]*10^9) -> 1698.6821
A21: other | B21: bioenergy: refuse (municipal and industrial wastes) | C21: =SUBSTITUTE(Table1[[#This Row],[Fuel]],", ",",") -> bioenergy: refuse (municipal and industrial wastes) | D21: bioenergy: refuse (municipal and industrial wastes) | G21: 80 | H21: pre-construction | I21: N/A | J21: N/A | K21: 24.0293 | L21: 54.3973 | M21: united arab emirates | N21: =Table1[[#This Row],[Capacity (MW)]]*8760*0.72*10^-6 -> 0.504576 | O21: {=AVERAGE(VLOOKUP(_xlfn.TEXTSPLIT(Table1[[#This Row],[Fuel (no space after comma)]], ","), FuelList_Final_EF!$A$2:$B$32, 2, FALSE))} -> 105.42963 | P21: =(16112*Table1[[#This Row],[Generation (TWh)]]*10^9)/10^6 -> 8129728.5 | Q21: =Table1[[#This Row],[Emission Factor (kg CO2/ mmBtu)]]*Table1[[#This Row],[Fuel Consumption (mmBtu)]]*10^3 -> 8.5711423e+11 | R21: =(Table1[[#This Row],[CO2 Emissions (g CO2)]])/(Table1[[#This Row],[Generation (TWh)]]*10^9) -> 1698.6821
A22: alabama river cellulose llc | B22: bioenergy: paper mill wastes, bioenergy: wood & other biomass (solids) | C22: =SUBSTITUTE(Table1[[#This Row],[Fuel]],", ",",") -> bioenergy: paper mill wastes,bioenergy: wood & other biomass (solids) | D22: bioenergy: paper mill wastes | E22: bioenergy: wood & other biomass (solids) | G22: 69 | H22: operating | I22: 1991 | J22: N/A | K22: 31.5825 | L22: -87.4889 | M22: united states | N22: =Table1[[#This Row],[Capacity (MW)]]*8760*0.72*10^-6 -> 0.4351968 | O22: {=AVERAGE(VLOOKUP(_xlfn.TEXTSPLIT(Table1[[#This Row],[Fuel (no space after comma)]], ","), FuelList_Final_EF!$A$2:$B$32, 2, FALSE))} -> 97.137217 | P22: =(16112*Table1[[#This Row],[Generation (TWh)]]*10^9)/10^6 -> 7011890.8 | Q22: =Table1[[#This Row],[Emission Factor (kg CO2/ mmBtu)]]*Table1[[#This Row],[Fuel Consumption (mmBtu)]]*10^3 -> 6.8111556e+11 | R22: =(Table1[[#This Row],[CO2 Emissions (g CO2)]])/(Table1[[#This Row],[Generation (TWh)]]*10^9) -> 1565.0748
A23: alabama river cellulose llc | B23: bioenergy: paper mill wastes, bioenergy: wood & other biomass (solids) | C23: =SUBSTITUTE(Table1[[#This Row],[Fuel]],", ",",") -> bioenergy: paper mill wastes,bioenergy: wood & other biomass (solids) | D23: bioenergy: paper mill wastes | E23: bioenergy: wood & other biomass (solids) | G23: 48 | H23: operating | I23: 1978 | J23: N/A | K23: 31.5825 | L23: -87.4889 | M23: united states | N23: =Table1[[#This Row],[Capacity (MW)]]*8760*0.72*10^-6 -> 0.3027456 | O23: {=AVERAGE(VLOOKUP(_xlfn.TEXTSPLIT(Table1[[#This Row],[Fuel (no space after comma)]], ","), FuelList_Final_EF!$A$2:$B$32, 2, FALSE))} -> 97.137217 | P23: =(16112*Table1[[#This Row],[Generation (TWh)]]*10^9)/10^6 -> 4877837.1 | Q23: =Table1[[#This Row],[Emission Factor (kg CO2/ mmBtu)]]*Table1[[#This Row],[Fuel Consumption (mmBtu)]]*10^3 -> 4.7381952e+11 | R23: =(Table1[[#This Row],[CO2 Emissions (g CO2)]])/(Table1[[#This Row],[Generation (TWh)]]*10^9) -> 1565.0748
A24: nsl sugars ltd | B24: bioenergy: agricultural waste (solids), coal: unknown | C24: =SUBSTITUTE(Table1[[#This Row],[Fuel]],", ",",") -> bioenergy: agricultural waste (solids),coal: unknown | D24: bioenergy: agricultural waste (solids) | E24: coal: unknown | G24: 34 | H24: operating | I24: 2012 | J24: N/A | K24: 17.4622 | L24: 76.5651 | M24: india | N24: =Table1[[#This Row],[Capacity (MW)]]*8760*0.72*10^-6 -> 0.2144448 | O24: {=AVERAGE(VLOOKUP(_xlfn.TEXTSPLIT(Table1[[#This Row],[Fuel (no space after comma)]], ","), FuelList_Final_EF!$A$2:$B$32, 2, FALSE))} -> 109.63851 | P24: =(16112*Table1[[#This Row],[Generation (TWh)]]*10^9)/10^6 -> 3455134.6 | Q24: =Table1[[#This Row],[Emission Factor (kg CO2/ mmBtu)]]*Table1[[#This Row],[Fuel Consumption (mmBtu)]]*10^3 -> 3.788158e+11 | R24: =(Table1[[#This Row],[CO2 Emissions (g CO2)]])/(Table1[[#This Row],[Generation (TWh)]]*10^9) -> 1766.4956
A25: regenerate energy holdings llc | B25: bioenergy: wood & other biomass (solids), fossil gas: natural gas | C25: =SUBSTITUTE(Table1[[#This Row],[Fuel]],", ",",") -> bioenergy: wood & other biomass (solids),fossil gas: natural gas | D25: bioenergy: wood & other biomass (solids) | E25: fossil gas: natural gas | G25: 55 | H25: operating | I25: 2017 | J25: N/A | K25: 31.5559 | L25: -84.1103 | M25: united states | N25: =Table1[[#This Row],[Capacity (MW)]]*8760*0.72*10^-6 -> 0.346896 | O25: {=AVERAGE(VLOOKUP(_xlfn.TEXTSPLIT(Table1[[#This Row],[Fuel (no space after comma)]], ","), FuelList_Final_EF!$A$2:$B$32, 2, FALSE))} -> 73.43 | P25: =(16112*Table1[[#This Row],[Generation (TWh)]]*10^9)/10^6 -> 5589188.4 | Q25: =Table1[[#This Row],[Emission Factor (kg CO2/ mmBtu)]]*Table1[[#This Row],[Fuel Consumption (mmBtu)]]*10^3 -> 4.104141e+11 | R25: =(Table1[[#This Row],[CO2 Emissions (g CO2)]])/(Table1[[#This Row],[Generation (TWh)]]*10^9) -> 1183.1042
A26: green power cagayan philippines inc | B26: bioenergy: wood & other biomass (solids) | C26: =SUBSTITUTE(Table1[[#This Row],[Fuel]],", ",",") -> bioenergy: wood & other biomass (solids) | D26: bioenergy: wood & other biomass (solids) | G26: 30 | H26: cancelled | I26: N/A | J26: N/A | K26: 17.9405 | L26: 121.6818 | M26: philippines | N26: =Table1[[#This Row],[Capacity (MW)]]*8760*0.72*10^-6 -> 0.189216 | O26: {=AVERAGE(VLOOKUP(_xlfn.TEXTSPLIT(Table1[[#This Row],[Fuel (no space after comma)]], ","), FuelList_Final_EF!$A$2:$B$32, 2, FALSE))} -> 93.8 | P26: =(16112*Table1[[#This Row],[Generation (TWh)]]*10^9)/10^6 -> 3048648.2 | Q26: =Table1[[#This Row],[Emission Factor (kg CO2/ mmBtu)]]*Table1[[#This Row],[Fuel Consumption (mmBtu)]]*10^3 -> 2.859632e+11 | R26: =(Table1[[#This Row],[CO2 Emissions (g CO2)]])/(Table1[[#This Row],[Generation (TWh)]]*10^9) -> 1511.3056
A27: atvos bioenergia alcidia sa | B27: bioenergy: agricultural waste (solids) | C27: =SUBSTITUTE(Table1[[#This Row],[Fuel]],", ",",") -> bioenergy: agricultural waste (solids) | D27: bioenergy: agricultural waste (solids) | G27: 38 | H27: operating | I27: 2010 | J27: N/A | K27: -22.3497 | L27: -52.524 | M27: brazil | N27: =Table1[[#This Row],[Capacity (MW)]]*8760*0.72*10^-6 -> 0.2396736 | O27: {=AVERAGE(VLOOKUP(_xlfn.TEXTSPLIT(Table1[[#This Row],[Fuel (no space after comma)]], ","), FuelList_Final_EF!$A$2:$B$32, 2, FALSE))} -> 118.17 | P27: =(16112*Table1[[#This Row],[Generation (TWh)]]*10^9)/10^6 -> 3861621 | Q27: =Table1[[#This Row],[Emission Factor (kg CO2/ mmBtu)]]*Table1[[#This Row],[Fuel Consumption (mmBtu)]]*10^3 -> 4.5632776e+11 | R27: =(Table1[[#This Row],[CO2 Emissions (g CO2)]])/(Table1[[#This Row],[Generation (TWh)]]*10^9) -> 1903.955
A28: alcogroup sa | B28: bioenergy: agricultural waste (unknown) | C28: =SUBSTITUTE(Table1[[#This Row],[Fuel]],", ",",") -> bioenergy: agricultural waste (unknown) | D28: bioenergy: agricultural waste (unknown) | G28: 60 | H28: operating | I28: 2010 | J28: N/A | K28: 51.9248 | L28: 4.1815 | M28: netherlands | N28: =Table1[[#This Row],[Capacity (MW)]]*8760*0.72*10^-6 -> 0.378432 | O28: {=AVERAGE(VLOOKUP(_xlfn.TEXTSPLIT(Table1[[#This Row],[Fuel (no space after comma)]], ","), FuelList_Final_EF!$A$2:$B$32, 2, FALSE))} -> 72.350251 | P28: =(16112*Table1[[#This Row],[Generation (TWh)]]*10^9)/10^6 -> 6097296.4 | Q28: =Table1[[#This Row],[Emission Factor (kg CO2/ mmBtu)]]*Table1[[#This Row],[Fuel Consumption (mmBtu)]]*10^3 -> 4.4114093e+11 | R28: =(Table1[[#This Row],[CO2 Emissions (g CO2)]])/(Table1[[#This Row],[Generation (TWh)]]*10^9) -> 1165.7072
A29: companhia de álcool conceição da barra sa | B29: bioenergy: agricultural waste (solids) | C29: =SUBSTITUTE(Table1[[#This Row],[Fuel]],", ",",") -> bioenergy: agricultural waste (solids) | D29: bioenergy: agricultural waste (solids) | G29: 33 | H29: operating | I29: 2001 | J29: N/A | K29: -18.4574 | L29: -39.9454 | M29: brazil | N29: =Table1[[#This Row],[Capacity (MW)]]*8760*0.72*10^-6 -> 0.2081376 | O29: {=AVERAGE(VLOOKUP(_xlfn.TEXTSPLIT(Table1[[#This Row],[Fuel (no space after comma)]], ","), FuelList_Final_EF!$A$2:$B$32, 2, FALSE))} -> 118.17 | P29: =(16112*Table1[[#This Row],[Generation (TWh)]]*10^9)/10^6 -> 3353513 | Q29: =Table1[[#This Row],[Emission Factor (kg CO2/ mmBtu)]]*Table1[[#This Row],[Fuel Consumption (mmBtu)]]*10^3 -> 3.9628463e+11 | R29: =(Table1[[#This Row],[CO2 Emissions (g CO2)]])/(Table1[[#This Row],[Generation (TWh)]]*10^9) -> 1903.955
A30: fcc environment | B30: bioenergy: refuse (municipal and industrial wastes) | C30: =SUBSTITUTE(Table1[[#This Row],[Fuel]],", ",",") -> bioenergy: refuse (municipal and industrial wastes) | D30: bioenergy: refuse (municipal and industrial wastes) | G30: 43 | H30: operating | I30: 2008 | J30: N/A | K30: 51.2931 | L30: 0.4924 | M30: united kingdom | N30: =Table1[[#This Row],[Capacity (MW)]]*8760*0.72*10^-6 -> 0.2712096 | O30: {=AVERAGE(VLOOKUP(_xlfn.TEXTSPLIT(Table1[[#This Row],[Fuel (no space after comma)]], ","), FuelList_Final_EF!$A$2:$B$32, 2, FALSE))} -> 105.42963 | P30: =(16112*Table1[[#This Row],[Generation (TWh)]]*10^9)/10^6 -> 4369729.1 | Q30: =Table1[[#This Row],[Emission Factor (kg CO2/ mmBtu)]]*Table1[[#This Row],[Fuel Consumption (mmBtu)]]*10^3 -> 4.606989e+11 | R30: =(Table1[[#This Row],[CO2 Emissions (g CO2)]])/(Table1[[#This Row],[Generation (TWh)]]*10^9) -> 1698.6821
A31: alberta pacific forest industries inc | B31: bioenergy: paper mill wastes | C31: =SUBSTITUTE(Table1[[#This Row],[Fuel]],", ",",") -> bioenergy: paper mill wastes | D31: bioenergy: paper mill wastes | G31: 41 | H31: operating | I31: 1993 | J31: N/A | K31: 54.921 | L31: -112.8622 | M31: canada | N31: =Table1[[#This Row],[Capacity (MW)]]*8760*0.72*10^-6 -> 0.2585952 | O31: {=AVERAGE(VLOOKUP(_xlfn.TEXTSPLIT(Table1[[#This Row],[Fuel (no space after comma)]], ","), FuelList_Final_EF!$A$2:$B$32, 2, FALSE))} -> 100.47443 | P31: =(16112*Table1[[#This Row],[Generation (TWh)]]*10^9)/10^6 -> 4166485.9 | Q31: =Table1[[#This Row],[Emission Factor (kg CO2/ mmBtu)]]*Table1[[#This Row],[Fuel Consumption (mmBtu)]]*10^3 -> 4.1862531e+11 | R31: =(Table1[[#This Row],[CO2 Emissions (g CO2)]])/(Table1[[#This Row],[Generation (TWh)]]*10^9) -> 1618.8441
A32: alberta pacific forest industries inc | B32: bioenergy: paper mill wastes | C32: =SUBSTITUTE(Table1[[#This Row],[Fuel]],", ",",") -> bioenergy: paper mill wastes | D32: bioenergy: paper mill wastes | G32: 41 | H32: operating | I32: 1993 | J32: N/A | K32: 54.921 | L32: -112.8622 | M32: canada | N32: =Table1[[#This Row],[Capacity (MW)]]*8760*0.72*10^-6 -> 0.2585952 | O32: {=AVERAGE(VLOOKUP(_xlfn.TEXTSPLIT(Table1[[#This Row],[Fuel (no space after comma)]], ","), FuelList_Final_EF!$A$2:$B$32, 2, FALSE))} -> 100.47443 | P32: =(16112*Table1[[#This Row],[Generation (TWh)]]*10^9)/10^6 -> 4166485.9 | Q32: =Table1[[#This Row],[Emission Factor (kg CO2/ mmBtu)]]*Table1[[#This Row],[Fuel Consumption (mmBtu)]]*10^3 -> 4.1862531e+11 | R32: =(Table1[[#This Row],[CO2 Emissions (g CO2)]])/(Table1[[#This Row],[Generation (TWh)]]*10^9) -> 1618.8441
A33: usina alta mogiana sa | B33: bioenergy: agricultural waste (solids) | C33: =SUBSTITUTE(Table1[[#This Row],[Fuel]],", ",",") -> bioenergy: agricultural waste (solids) | D33: bioenergy: agricultural waste (solids) | G33: 71 | H33: operating | I33: 1994 | J33: N/A | K33: -20.4818 | L33: -47.8662 | M33: brazil | N33: =Table1[[#This Row],[Capacity (MW)]]*8760*0.72*10^-6 -> 0.4478112 | O33: {=AVERAGE(VLOOKUP(_xlfn.TEXTSPLIT(Table1[[#This Row],[Fuel (no space after comma)]], ","), FuelList_Final_EF!$A$2:$B$32, 2, FALSE))} -> 118.17 | P33: =(16112*Table1[[#This Row],[Generation (TWh)]]*10^9)/10^6 -> 7215134.1 | Q33: =Table1[[#This Row],[Emission Factor (kg CO2/ mmBtu)]]*Table1[[#This Row],[Fuel Consumption (mmBtu)]]*10^3 -> 8.5261239e+11 | R33: =(Table1[[#This Row],[CO2 Emissions (g CO2)]])/(Table1[[#This Row],[Generation (TWh)]]*10^9) -> 1903.955
A34: virginia electric and power co | B34: bioenergy: wood & other biomass (solids), fossil gas: natural gas | C34: =SUBSTITUTE(Table1[[#This Row],[Fuel]],", ",",") -> bioenergy: wood & other biomass (solids),fossil gas: natural gas | D34: bioenergy: wood & other biomass (solids) | E34: fossil gas: natural gas | G34: 71 | H34: operating | I34: 1992 | J34: N/A | K34: 37.118481 | L34: -79.273027 | M34: united states | N34: =Table1[[#This Row],[Capacity (MW)]]*8760*0.72*10^-6 -> 0.4478112 | O34: {=AVERAGE(VLOOKUP(_xlfn.TEXTSPLIT(Table1[[#This Row],[Fuel (no space after comma)]], ","), FuelList_Final_EF!$A$2:$B$32, 2, FALSE))} -> 73.43 | P34: =(16112*Table1[[#This Row],[Generation (TWh)]]*10^9)/10^6 -> 7215134.1 | Q34: =Table1[[#This Row],[Emission Factor (kg CO2/ mmBtu)]]*Table1[[#This Row],[Fuel Consumption (mmBtu)]]*10^3 -> 5.2980729e+11 | R34: =(Table1[[#This Row],[CO2 Emissions (g CO2)]])/(Table1[[#This Row],[Generation (TWh)]]*10^9) -> 1183.1042
A35: i/s amager resourcecenter | B35: bioenergy: refuse (municipal and industrial wastes) | C35: =SUBSTITUTE(Table1[[#This Row],[Fuel]],", ",",") -> bioenergy: refuse (municipal and industrial wastes) | D35: bioenergy: refuse (municipal and industrial wastes) | G35: 63 | H35: operating | I35: 2019 | J35: N/A | K35: 55.6842 | L35: 12.6193 | M35: denmark | N35: =Table1[[#This Row],[Capacity (MW)]]*8760*0.72*10^-6 -> 0.3973536 | O35: {=AVERAGE(VLOOKUP(_xlfn.TEXTSPLIT(Table1[[#This Row],[Fuel (no space after comma)]], ","), FuelList_Final_EF!$A$2:$B$32, 2, FALSE))} -> 105.42963 | P35: =(16112*Table1[[#This Row],[Generation (TWh)]]*10^9)/10^6 -> 6402161.2 | Q35: =Table1[[#This Row],[Emission Factor (kg CO2/ mmBtu)]]*Table1[[#This Row],[Fuel Consumption (mmBtu)]]*10^3 -> 6.7497746e+11 | R35: =(Table1[[#This Row],[CO2 Emissions (g CO2)]])/(Table1[[#This Row],[Generation (TWh)]]*10^9) -> 1698.6821
A36: hofor a/s | B36: bioenergy: wood & other biomass (solids) | C36: =SUBSTITUTE(Table1[[#This Row],[Fuel]],", ",",") -> bioenergy: wood & other biomass (solids) | D36: bioenergy: wood & other biomass (solids) | G36: 68 | H36: operating | I36: 1971 | J36: N/A | K36: 55.686777 | L36: 12.627702 | M36: denmark | N36: =Table1[[#This Row],[Capacity (MW)]]*8760*0.72*10^-6 -> 0.4288896 | O36: {=AVERAGE(VLOOKUP(_xlfn.TEXTSPLIT(Table1[[#This Row],[Fuel (no space after comma)]], ","), FuelList_Final_EF!$A$2:$B$32, 2, FALSE))} -> 93.8 | P36: =(16112*Table1[[#This Row],[Generation (TWh)]]*10^9)/10^6 -> 6910269.2 | Q36: =Table1[[#This Row],[Emission Factor (kg CO2/ mmBtu)]]*Table1[[#This Row],[Fuel Consumption (mmBtu)]]*10^3 -> 6.4818325e+11 | R36: =(Table1[[#This Row],[CO2 Emissions (g CO2)]])/(Table1[[#This Row],[Generation (TWh)]]*10^9) -> 1511.3056
A37: hofor a/s | B37: bioenergy: wood & other biomass (solids) | C37: =SUBSTITUTE(Table1[[#This Row],[Fuel]],", ",",") -> bioenergy: wood & other biomass (solids) | D37: bioenergy: wood & other biomass (solids) | G37: 150 | H37: operating | I37: 2020 | J37: N/A | K37: 55.686777 | L37: 12.627702 | M37: denmark | N37: =Table1[[#This Row],[Capacity (MW)]]*8760*0.72*10^-6 -> 0.94608 | O37: {=AVERAGE(VLOOKUP(_xlfn.TEXTSPLIT(Table1[[#This Row],[Fuel (no space after comma)]], ","), FuelList_Final_EF!$A$2:$B$32, 2, FALSE))} -> 93.8 | P37: =(16112*Table1[[#This Row],[Generation (TWh)]]*10^9)/10^6 -> 15243241 | Q37: =Table1[[#This Row],[Emission Factor (kg CO2/ mmBtu)]]*Table1[[#This Row],[Fuel Consumption (mmBtu)]]*10^3 -> 1429816002048 | R37: =(Table1[[#This Row],[CO2 Emissions (g CO2)]])/(Table1[[#This Row],[Generation (TWh)]]*10^9) -> 1511.3056
A38: brazil adecoagro participações sa | B38: bioenergy: agricultural waste (solids) | C38: =SUBSTITUTE(Table1[[#This Row],[Fuel]],", ",",") -> bioenergy: agricultural waste (solids) | D38: bioenergy: agricultural waste (solids) | G38: 40 | H38: operating | I38: 2018 | J38: N/A | K38: -22.3251 | L38: -53.8212 | M38: brazil | N38: =Table1[[#This Row],[Capacity (MW)]]*8760*0.72*10^-6 -> 0.252288 | O38: {=AVERAGE(VLOOKUP(_xlfn.TEXTSPLIT(Table1[[#This Row],[Fuel (no space after comma)]], ","), FuelList_Final_EF!$A$2:$B$32, 2, FALSE))} -> 118.17 | P38: =(16112*Table1[[#This Row],[Generation (TWh)]]*10^9)/10^6 -> 4064864.3 | Q38: =Table1[[#This Row],[Emission Factor (kg CO2/ mmBtu)]]*Table1[[#This Row],[Fuel Consumption (mmBtu)]]*10^3 -> 4.8034501e+11 | R38: =(Table1[[#This Row],[CO2 Emissions (g CO2)]])/(Table1[[#This Row],[Generation (TWh)]]*10^9) -> 1903.955
A39: ivinhema energia ltda | B39: bioenergy: agricultural waste (solids) | C39: =SUBSTITUTE(Table1[[#This Row],[Fuel]],", ",",") -> bioenergy: agricultural waste (solids) | D39: bioenergy: agricultural waste (solids) | G39: 40 | H39: pre-construction | I39: N/A | J39: N/A | K39: -22.3956 | L39: -53.8904 | M39: brazil | N39: =Table1[[#This Row],[Capacity (MW)]]*8760*0.72*10^-6 -> 0.252288 | O39: {=AVERAGE(VLOOKUP(_xlfn.TEXTSPLIT(Table1[[#This Row],[Fuel (no space after comma)]], ","), FuelList_Final_EF!$A$2:$B$32, 2, FALSE))} -> 118.17 | P39: =(16112*Table1[[#This Row],[Generation (TWh)]]*10^9)/10^6 -> 4064864.3 | Q39: =Table1[[#This Row],[Emission Factor (kg CO2/ mmBtu)]]*Table1[[#This Row],[Fuel Consumption (mmBtu)]]*10^3 -> 4.8034501e+11 | R39: =(Table1[[#This Row],[CO2 Emissions (g CO2)]])/(Table1[[#This Row],[Generation (TWh)]]*10^9) -> 1903.955
A40: adecoagro vale do ivinhema sa | B40: bioenergy: agricultural waste (solids) | C40: =SUBSTITUTE(Table1[[#This Row],[Fuel]],", ",",") -> bioenergy: agricultural waste (solids) | D40: bioenergy: agricultural waste (solids) | G40: 40 | H40: operating | I40: 2014 | J40: N/A | K40: -22.4381 | L40: -53.5781 | M40: brazil | N40: =Table1[[#This Row],[Capacity (MW)]]*8760*0.72*10^-6 -> 0.252288 | O40: {=AVERAGE(VLOOKUP(_xlfn.TEXTSPLIT(Table1[[#This Row],[Fuel (no space after comma)]], ","), FuelList_Final_EF!$A$2:$B$32, 2, FALSE))} -> 118.17 | P40: =(16112*Table1[[#This Row],[Generation (TWh)]]*10^9)/10^6 -> 4064864.3 | Q40: =Table1[[#This Row],[Emission Factor (kg CO2/ mmBtu)]]*Table1[[#This Row],[Fuel Consumption (mmBtu)]]*10^3 -> 4.8034501e+11 | R40: =(Table1[[#This Row],[CO2 Emissions (g CO2)]])/(Table1[[#This Row],[Generation (TWh)]]*10^9) -> 1903.955
A41: adecoagro vale do ivinhema sa | B41: bioenergy: agricultural waste (solids) | C41: =SUBSTITUTE(Table1[[#This Row],[Fuel]],", ",",") -> bioenergy: agricultural waste (solids) | D41: bioenergy: agricultural waste (solids) | G41: 40 | H41: operating | I41: 2014 | J41: N/A | K41: -22.4381 | L41: -53.5781 | M41: brazil | N41: =Table1[[#This Row],[Capacity (MW)]]*8760*0.72*10^-6 -> 0.252288 | O41: {=AVERAGE(VLOOKUP(_xlfn.TEXTSPLIT(Table1[[#This Row],[Fuel (no space after comma)]], ","), FuelList_Final_EF!$A$2:$B$32, 2, FALSE))} -> 118.17 | P41: =(16112*Table1[[#This Row],[Generation (TWh)]]*10^9)/10^6 -> 4064864.3 | Q41: =Table1[[#This Row],[Emission Factor (kg CO2/ mmBtu)]]*Table1[[#This Row],[Fuel Consumption (mmBtu)]]*10^3 -> 4.8034501e+11 | R41: =(Table1[[#This Row],[CO2 Emissions (g CO2)]])/(Table1[[#This Row],[Generation (TWh)]]*10^9) -> 1903.955
A42: rwe ag | B42: bioenergy: wood & other biomass (solids), coal: bituminous | C42: =SUBSTITUTE(Table1[[#This Row],[Fuel]],", ",",") -> bioenergy: wood & other biomass (solids),coal: bituminous | D42: bioenergy: wood & other biomass (solids) | E42: coal: bituminous | G42: 600 | H42: operating | I42: 2023 | J42: N/A | K42: 51.709806 | L42: 4.843661 | M42: netherlands | N42: =Table1[[#This Row],[Capacity (MW)]]*8760*0.72*10^-6 -> 3.78432 | O42: {=AVERAGE(VLOOKUP(_xlfn.TEXTSPLIT(Table1[[#This Row],[Fuel (no space after comma)]], ","), FuelList_Final_EF!$A$2:$B$32, 2, FALSE))} -> 96.768213 | P42: =(16112*Table1[[#This Row],[Generation (TWh)]]*10^9)/10^6 -> 60972964 | Q42: =Table1[[#This Row],[Emission Factor (kg CO2/ mmBtu)]]*Table1[[#This Row],[Fuel Consumption (mmBtu)]]*10^3 -> 5.9002448e+12 | R42: =(Table1[[#This Row],[CO2 Emissions (g CO2)]])/(Table1[[#This Row],[Generation (TWh)]]*10^9) -> 1559.1294
A43: china machinery engineering corp | B43: bioenergy: refuse (municipal and industrial wastes) | C43: =SUBSTITUTE(Table1[[#This Row],[Fuel]],", ",",") -> bioenergy: refuse (municipal and industrial wastes) | D43: bioenergy: refuse (municipal and industrial wastes) | G43: 42 | H43: pre-construction | I43: 2025 | J43: N/A | K43: 23.795258 | L43: 90.298461 | M43: bangladesh | N43: =Table1[[#This Row],[Capacity (MW)]]*8760*0.72*10^-6 -> 0.2649024 | O43: {=AVERAGE(VLOOKUP(_xlfn.TEXTSPLIT(Table1[[#This Row],[Fuel (no space after comma)]], ","), FuelList_Final_EF!$A$2:$B$32, 2, FALSE))} -> 105.42963 | P43: =(16112*Table1[[#This Row],[Generation (TWh)]]*10^9)/10^6 -> 4268107.5 | Q43: =Table1[[#This Row],[Emission Factor (kg CO2/ mmBtu)]]*Table1[[#This Row],[Fuel Consumption (mmBtu)]]*10^3 -> 4.4998497e+11 | R43: =(Table1[[#This Row],[CO2 Emissions (g CO2)]])/(Table1[[#This Row],[Generation (TWh)]]*10^9) -> 1698.6821
A44: oji green energy tokushima co ltd | B44: bioenergy: wood & other biomass (solids) | C44: =SUBSTITUTE(Table1[[#This Row],[Fuel]],", ",",") -> bioenergy: wood & other biomass (solids) | D44: bioenergy: wood & other biomass (solids) | G44: 75 | H44: mothballed | I44: 2022 | J44: N/A | K44: 33.9377 | L44: 134.6966 | M44: japan | N44: =Table1[[#This Row],[Capacity (MW)]]*8760*0.72*10^-6 -> 0.47304 | O44: {=AVERAGE(VLOOKUP(_xlfn.TEXTSPLIT(Table1[[#This Row],[Fuel (no space after comma)]], ","), FuelList_Final_EF!$A$2:$B$32, 2, FALSE))} -> 93.8 | P44: =(16112*Table1[[#This Row],[Generation (TWh)]]*10^9)/10^6 -> 7621620.5 | Q44: =Table1[[#This Row],[Emission Factor (kg CO2/ mmBtu)]]*Table1[[#This Row],[Fuel Consumption (mmBtu)]]*10^3 -> 714908001024 | R44: =(Table1[[#This Row],[CO2 Emissions (g CO2)]])/(Table1[[#This Row],[Generation (TWh)]]*10^9) -> 1511.3056
A45: engie energía chile sa | B45: bioenergy: unknown | C45: =SUBSTITUTE(Table1[[#This Row],[Fuel]],", ",",") -> bioenergy: unknown | D45: bioenergy: unknown | G45: 177 | H45: announced | I45: 2025 | J45: N/A | K45: -23.087707 | L45: -70.407472 | M45: chile | N45: =Table1[[#This Row],[Capacity (MW)]]*8760*0.72*10^-6 -> 1.1163744 | O45: {=AVERAGE(VLOOKUP(_xlfn.TEXTSPLIT(Table1[[#This Row],[Fuel (no space after comma)]], ","), FuelList_Final_EF!$A$2:$B$32, 2, FALSE))} -> 72.785606 | P45: =(16112*Table1[[#This Row],[Generation (TWh)]]*10^9)/10^6 -> 17987024 | Q45: =Table1[[#This Row],[Emission Factor (kg CO2/ mmBtu)]]*Table1[[#This Row],[Fuel Consumption (mmBtu)]]*10^3 -> 1.3091965e+12 | R45: =(Table1[[#This Row],[CO2 Emissions (g CO2)]])/(Table1[[#This Row],[Generation (TWh)]]*10^9) -> 1172.7217
A46: engie energía chile sa | B46: bioenergy: unknown | C46: =SUBSTITUTE(Table1[[#This Row],[Fuel]],", ",",") -> bioenergy: unknown | D46: bioenergy: unknown | G46: 178 | H46: announced | I46: 2025 | J46: N/A | K46: -23.087707 | L46: -70.407472 | M46: chile | N46: =Table1[[#This Row],[Capacity (MW)]]*8760*0.72*10^-6 -> 1.1226816 | O46: {=AVERAGE(VLOOKUP(_xlfn.TEXTSPLIT(Table1[[#This Row],[Fuel (no space after comma)]], ","), FuelList_Final_EF!$A$2:$B$32, 2, FALSE))} -> 72.785606 | P46: =(16112*Table1[[#This Row],[Generation (TWh)]]*10^9)/10^6 -> 18088646 | Q46: =Table1[[#This Row],[Emission Factor (kg CO2/ mmBtu)]]*Table1[[#This Row],[Fuel Consumption (mmBtu)]]*10^3 -> 1.3165931e+12 | R46: =(Table1[[#This Row],[CO2 Emissions (g CO2)]])/(Table1[[#This Row],[Generation (TWh)]]*10^9) -> 1172.7217
A47: pixelle androscoggin llc | B47: bioenergy: paper mill wastes, bioenergy: wood & other biomass (solids), bioenergy: wastewater and sewage sludge (solids or biogas) | C47: =SUBSTITUTE(Table1[[#This Row],[Fuel]],", ",",") -> bioenergy: paper mill wastes,bioenergy: wood & other biomass (solids),bioenergy: wastewater and sewage sludge (solids or biogas) | D47: bioenergy: paper mill wastes | E47: bioenergy: wood & other biomass (solids) | F47: bioenergy: wastewater and sewage sludge (solids or biogas) | G47: 30 | H47: operating | I47: 1974 | J47: N/A | K47: 44.5063 | L47: -70.2395 | M47: united states | N47: =Table1[[#This Row],[Capacity (MW)]]*8760*0.72*10^-6 -> 0.189216 | O47: {=AVERAGE(VLOOKUP(_xlfn.TEXTSPLIT(Table1[[#This Row],[Fuel (no space after comma)]], ","), FuelList_Final_EF!$A$2:$B$32, 2, FALSE))} -> 83.946336 | P47: =(16112*Table1[[#This Row],[Generation (TWh)]]*10^9)/10^6 -> 3048648.2 | Q47: =Table1[[#This Row],[Emission Factor (kg CO2/ mmBtu)]]*Table1[[#This Row],[Fuel Consumption (mmBtu)]]*10^3 -> 2.5592285e+11 | R47: =(Table1[[#This Row],[CO2 Emissions (g CO2)]])/(Table1[[#This Row],[Generation (TWh)]]*10^9) -> 1352.5434
A48: adecoagro vale do ivinhema sa | B48: bioenergy: agricultural waste (solids) | C48: =SUBSTITUTE(Table1[[#This Row],[Fuel]],", ",",") -> bioenergy: agricultural waste (solids) | D48: bioenergy: agricultural waste (solids) | G48: 70 | H48: operating | I48: 2009 | J48: N/A | K48: -22.0409 | L48: -53.8419 | M48: brazil | N48: =Table1[[#This Row],[Capacity (MW)]]*8760*0.72*10^-6 -> 0.441504 | O48: {=AVERAGE(VLOOKUP(_xlfn.TEXTSPLIT(Table1[[#This Row],[Fuel (no space after comma)]], ","), FuelList_Final_EF!$A$2:$B$32, 2, FALSE))} -> 118.17 | P48: =(16112*Table1[[#This Row],[Generation (TWh)]]*10^9)/10^6 -> 7113512.4 | Q48: =Table1[[#This Row],[Emission Factor (kg CO2/ mmBtu)]]*Table1[[#This Row],[Fuel Consumption (mmBtu)]]*10^3 -> 8.4060377e+11 | R48: =(Table1[[#This Row],[CO2 Emissions (g CO2)]])/(Table1[[#This Row],[Generation (TWh)]]*10^9) -> 1903.955
A49: anhui anqing development investment (group) co ltd | B49: bioenergy: paper mill wastes, bioenergy: wood & other biomass (solids) | C49: =SUBSTITUTE(Table1[[#This Row],[Fuel]],", ",",") -> bioenergy: paper mill wastes,bioenergy: wood & other biomass (solids) | D49: bioenergy: paper mill wastes | E49: bioenergy: wood & other biomass (solids) | G49: 6 | H49: operating | I49: 2012 | J49: N/A | K49: 30.5526 | L49: 117.2059 | M49: china | N49: =Table1[[#This Row],[Capacity (MW)]]*8760*0.72*10^-6 -> 0.0378432 | O49: {=AVERAGE(VLOOKUP(_xlfn.TEXTSPLIT(Table1[[#This Row],[Fuel (no space after comma)]], ","), FuelList_Final_EF!$A$2:$B$32, 2, FALSE))} -> 97.137217 | P49: =(16112*Table1[[#This Row],[Generation (TWh)]]*10^9)/10^6 -> 609729.64 | Q49: =Table1[[#This Row],[Emission Factor (kg CO2/ mmBtu)]]*Table1[[#This Row],[Fuel Consumption (mmBtu)]]*10^3 -> 5.922744e+10 | R49: =(Table1[[#This Row],[CO2 Emissions (g CO2)]])/(Table1[[#This Row],[Generation (TWh)]]*10^9) -> 1565.0748
A50: shandong huatai paper industry shareholding co ltd | B50: bioenergy: paper mill wastes, bioenergy: wood & other biomass (solids) | C50: =SUBSTITUTE(Table1[[#This Row],[Fuel]],", ",",") -> bioenergy: paper mill wastes,bioenergy: wood & other biomass (solids) | D50: bioenergy: paper mill wastes | E50: bioenergy: wood & other biomass (solids) | G50: 34 | H50: operating | I50: 2012 | J50: N/A | K50: 30.5526 | L50: 117.2059 | M50: china | N50: =Table1[[#This Row],[Capacity (MW)]]*8760*0.72*10^-6 -> 0.2144448 | O50: {=AVERAGE(VLOOKUP(_xlfn.TEXTSPLIT(Table1[[#This Row],[Fuel (no space after comma)]], ","), FuelList_Final_EF!$A$2:$B$32, 2, FALSE))} -> 97.137217 | P50: =(16112*Table1[[#This Row],[Generation (TWh)]]*10^9)/10^6 -> 3455134.6 | Q50: =Table1[[#This Row],[Emission Factor (kg CO2/ mmBtu)]]*Table1[[#This Row],[Fuel Consumption (mmBtu)]]*10^3 -> 3.3562216e+11 | R50: =(Table1[[#This Row],[CO2 Emissions (g CO2)]])/(Table1[[#This Row],[Generation (TWh)]]*10^9) -> 1565.0748
A51: anhui guozhen ecological technology co ltd | B51: bioenergy: agricultural waste (solids), bioenergy: wood & other biomass (solids) | C51: =SUBSTITUTE(Table1[[#This Row],[Fuel]],", ",",") -> bioenergy: agricultural waste (solids),bioenergy: wood & other biomass (solids) | D51: bioenergy: agricultural waste (solids) | E51: bioenergy: wood & other biomass (solids) | G51: 30 | H51: operating | I51: 2018 | J51: N/A | K51: 33.7704 | L51: 115.7386 | M51: china | N51: =Table1[[#This Row],[Capacity (MW)]]*8760*0.72*10^-6 -> 0.189216 | O51: {=AVERAGE(VLOOKUP(_xlfn.TEXTSPLIT(Table1[[#This Row],[Fuel (no space after comma)]], ","), FuelList_Final_EF!$A$2:$B$32, 2, FALSE))} -> 105.985 | P51: =(16112*Table1[[#This Row],[Generation (TWh)]]*10^9)/10^6 -> 3048648.2 | Q51: =Table1[[#This Row],[Emission Factor (kg CO2/ mmBtu)]]*Table1[[#This Row],[Fuel Consumption (mmBtu)]]*10^3 -> 3.2311098e+11 | R51: =(Table1[[#This Row],[CO2 Emissions (g CO2)]])/(Table1[[#This Row],[Generation (TWh)]]*10^9) -> 1707.6303
A52: anhui wanneng environmental technology co ltd | B52: bioenergy: agricultural waste (solids) | C52: =SUBSTITUTE(Table1[[#This Row],[Fuel]],", ",",") -> bioenergy: agricultural waste (solids) | D52: bioenergy: agricultural waste (solids) | G52: 30 | H52: operating | I52: 2021 | J52: N/A | K52: 32.3995 | L52: 117.2453 | M52: china | N52: =Table1[[#This Row],[Capacity (MW)]]*8760*0.72*10^-6 -> 0.189216 | O52: {=AVERAGE(VLOOKUP(_xlfn.TEXTSPLIT(Table1[[#This Row],[Fuel (no space after comma)]], ","), FuelList_Final_EF!$A$2:$B$32, 2, FALSE))} -> 118.17 | P52: =(16112*Table1[[#This Row],[Generation (TWh)]]*10^9)/10^6 -> 3048648.2 | Q52: =Table1[[#This Row],[Emission Factor (kg CO2/ mmBtu)]]*Table1[[#This Row],[Fuel Consumption (mmBtu)]]*10^3 -> 3.6025876e+11 | R52: =(Table1[[#This Row],[CO2 Emissions (g CO2)]])/(Table1[[#This Row],[Generation (TWh)]]*10^9) -> 1903.955
A53: hangzhou jinxu holding co ltd | B53: bioenergy: agricultural waste (solids), bioenergy: wood & other biomass (solids) | C53: =SUBSTITUTE(Table1[[#This Row],[Fuel]],", ",",") -> bioenergy: agricultural waste (solids),bioenergy: wood & other biomass (solids) | D53: bioenergy: agricultural waste (solids) | E53: bioenergy: wood & other biomass (solids) | G53: 21 | H53: operating | I53: 2018 | J53: N/A | K53: 31.7995 | L53: 117.7628 | M53: china | N53: =Table1[[#This Row],[Capacity (MW)]]*8760*0.72*10^-6 -> 0.1324512 | O53: {=AVERAGE(VLOOKUP(_xlfn.TEXTSPLIT(Table1[[#This Row],[Fuel (no space after comma)]], ","), FuelList_Final_EF!$A$2:$B$32, 2, FALSE))} -> 105.985 | P53: =(16112*Table1[[#This Row],[Generation (TWh)]]*10^9)/10^6 -> 2134053.7 | Q53: =Table1[[#This Row],[Emission Factor (kg CO2/ mmBtu)]]*Table1[[#This Row],[Fuel Consumption (mmBtu)]]*10^3 -> 2.2617769e+11 | R53: =(Table1[[#This Row],[CO2 Emissions (g CO2)]])/(Table1[[#This Row],[Generation (TWh)]]*10^9) -> 1707.6303
A54: natural person(s) | B54: bioenergy: agricultural waste (solids), bioenergy: wood & other biomass (solids) | C54: =SUBSTITUTE(Table1[[#This Row],[Fuel]],", ",",") -> bioenergy: agricultural waste (solids),bioenergy: wood & other biomass (solids) | D54: bioenergy: agricultural waste (solids) | E54: bioenergy: wood & other biomass (solids) | G54: 9 | H54: operating | I54: 2018 | J54: N/A | K54: 31.7995 | L54: 117.7628 | M54: china | N54: =Table1[[#This Row],[Capacity (MW)]]*8760*0.72*10^-6 -> 0.0567648 | O54: {=AVERAGE(VLOOKUP(_xlfn.TEXTSPLIT(Table1[[#This Row],[Fuel (no space after comma)]], ","), FuelList_Final_EF!$A$2:$B$32, 2, FALSE))} -> 105.985 | P54: =(16112*Table1[[#This Row],[Generation (TWh)]]*10^9)/10^6 -> 914594.46 | Q54: =Table1[[#This Row],[Emission Factor (kg CO2/ mmBtu)]]*Table1[[#This Row],[Fuel Consumption (mmBtu)]]*10^3 -> 9.6933294e+10 | R54: =(Table1[[#This Row],[CO2 Emissions (g CO2)]])/(Table1[[#This Row],[Generation (TWh)]]*10^9) -> 1707.6303
A55: everbright green bioenergy (anhui) holdings co ltd | B55: bioenergy: agricultural waste (solids), bioenergy: wood & other biomass (solids) | C55: =SUBSTITUTE(Table1[[#This Row],[Fuel]],", ",",") -> bioenergy: agricultural waste (solids),bioenergy: wood & other biomass (solids) | D55: bioenergy: agricultural waste (solids) | E55: bioenergy: wood & other biomass (solids) | G55: 30 | H55: operating | I55: 2011 | J55: N/A | K55: 34.4144 | L55: 116.4146 | M55: china | N55: =Table1[[#This Row],[Capacity (MW)]]*8760*0.72*10^-6 -> 0.189216 | O55: {=AVERAGE(VLOOKUP(_xlfn.TEXTSPLIT(Table1[[#This Row],[Fuel (no space after comma)]], ","), FuelList_Final_EF!$A$2:$B$32, 2, FALSE))} -> 105.985 | P55: =(16112*Table1[[#This Row],[Generation (TWh)]]*10^9)/10^6 -> 3048648.2 | Q55: =Table1[[#This Row],[Emission Factor (kg CO2/ mmBtu)]]*Table1[[#This Row],[Fuel Consumption (mmBtu)]]*10^3 -> 3.2311098e+11 | R55: =(Table1[[#This Row],[CO2 Emissions (g CO2)]])/(Table1[[#This Row],[Generation (TWh)]]*10^9) -> 1707.6303
A56: anhui jinxuan technology co ltd | B56: bioenergy: agricultural waste (solids) | C56: =SUBSTITUTE(Table1[[#This Row],[Fuel]],", ",",") -> bioenergy: agricultural waste (solids) | D56: bioenergy: agricultural waste (solids) | G56: 30 | H56: operating | I56: 2019 | J56: N/A | K56: 32.5828 | L56: 117.2782 | M56: china | N56: =Table1[[#This Row],[Capacity (MW)]]*8760*0.72*10^-6 -> 0.189216 | O56: {=AVERAGE(VLOOKUP(_xlfn.TEXTSPLIT(Table1[[#This Row],[Fuel (no space after comma)]], ","), FuelList_Final_EF!$A$2:$B$32, 2, FALSE))} -> 118.17 | P56: =(16112*Table1[[#This Row],[Generation (TWh)]]*10^9)/10^6 -> 3048648.2 | Q56: =Table1[[#This Row],[Emission Factor (kg CO2/ mmBtu)]]*Table1[[#This Row],[Fuel Consumption (mmBtu)]]*10^3 -> 3.6025876e+11 | R56: =(Table1[[#This Row],[CO2 Emissions (g CO2)]])/(Table1[[#This Row],[Generation (TWh)]]*10^9) -> 1903.955
A57: everbright green renewable energy (anhui) holdings co ltd | B57: bioenergy: agricultural waste (solids) | C57: =SUBSTITUTE(Table1[[#This Row],[Fuel]],", ",",") -> bioenergy: agricultural waste (solids) | D57: bioenergy: agricultural waste (solids) | G57: 30 | H57: operating | I57: 2016 | J57: N/A | K57: 32.3084 | L57: 117.6105 | M57: china | N57: =Table1[[#This Row],[Capacity (MW)]]*8760*0.72*10^-6 -> 0.189216 | O57: {=AVERAGE(VLOOKUP(_xlfn.TEXTSPLIT(Table1[[#This Row],[Fuel (no space after comma)]], ","), FuelList_Final_EF!$A$2:$B$32, 2, FALSE))} -> 118.17 | P57: =(16112*Table1[[#This Row],[Generation (TWh)]]*10^9)/10^6 -> 3048648.2 | Q57: =Table1[[#This Row],[Emission Factor (kg CO2/ mmBtu)]]*Table1[[#This Row],[Fuel Consumption (mmBtu)]]*10^3 -> 3.6025876e+11 | R57: =(Table1[[#This Row],[CO2 Emissions (g CO2)]])/(Table1[[#This Row],[Generation (TWh)]]*10^9) -> 1903.955
A58: anhui waneng environmental protection power generation co ltd | B58: bioenergy: refuse (municipal and industrial wastes) | C58: =SUBSTITUTE(Table1[[#This Row],[Fuel]],", ",",") -> bioenergy: refuse (municipal and industrial wastes) | D58: bioenergy: refuse (municipal and industrial wastes) | G58: 40 | H58: operating | I58: 2021 | J58: N/A | K58: 31.7957 | L58: 117.5671 | M58: china | N58: =Table1[[#This Row],[Capacity (MW)]]*8760*0.72*10^-6 -> 0.252288 | O58: {=AVERAGE(VLOOKUP(_xlfn.TEXTSPLIT(Table1[[#This Row],[Fuel (no space after comma)]], ","), FuelList_Final_EF!$A$2:$B$32, 2, FALSE))} -> 105.42963 | P58: =(16112*Table1[[#This Row],[Generation (TWh)]]*10^9)/10^6 -> 4064864.3 | Q58: =Table1[[#This Row],[Emission Factor (kg CO2/ mmBtu)]]*Table1[[#This Row],[Fuel Consumption (mmBtu)]]*10^3 -> 4.2855712e+11 | R58: =(Table1[[#This Row],[CO2 Emissions (g CO2)]])/(Table1[[#This Row],[Generation (TWh)]]*10^9) -> 1698.6821
A59: anhui waneng environmental protection power generation co ltd | B59: bioenergy: refuse (municipal and industrial wastes) | C59: =SUBSTITUTE(Table1[[#This Row],[Fuel]],", ",",") -> bioenergy: refuse (municipal and industrial wastes) | D59: bioenergy: refuse (municipal and industrial wastes) | G59: 40 | H59: operating | I59: 2021 | J59: N/A | K59: 31.7957 | L59: 117.5671 | M59: china | N59: =Table1[[#This Row],[Capacity (MW)]]*8760*0.72*10^-6 -> 0.252288 | O59: {=AVERAGE(VLOOKUP(_xlfn.TEXTSPLIT(Table1[[#This Row],[Fuel (no space after comma)]], ","), FuelList_Final_EF!$A$2:$B$32, 2, FALSE))} -> 105.42963 | P59: =(16112*Table1[[#This Row],[Generation (TWh)]]*10^9)/10^6 -> 4064864.3 | Q59: =Table1[[#This Row],[Emission Factor (kg CO2/ mmBtu)]]*Table1[[#This Row],[Fuel Consumption (mmBtu)]]*10^3 -> 4.2855712e+11 | R59: =(Table1[[#This Row],[CO2 Emissions (g CO2)]])/(Table1[[#This Row],[Generation (TWh)]]*10^9) -> 1698.6821
A60: hong kong china power new energy holdings ltd | B60: bioenergy: agricultural waste (solids) | C60: =SUBSTITUTE(Table1[[#This Row],[Fuel]],", ",",") -> bioenergy: agricultural waste (solids) | D60: bioenergy: agricultural waste (solids) | G60: 30 | H60: operating | I60: 2020 | J60: N/A | K60: 32.8997 | L60: 116.4206 | M60: china | N60: =Table1[[#This Row],[Capacity (MW)]]*8760*0.72*10^-6 -> 0.189216 | O60: {=AVERAGE(VLOOKUP(_xlfn.TEXTSPLIT(Table1[[#This Row],[Fuel (no space after comma)]], ","), FuelList_Final_EF!$A$2:$B$32, 2, FALSE))} -> 118.17 | P60: =(16112*Table1[[#This Row],[Generation (TWh)]]*10^9)/10^6 -> 3048648.2 | Q60: =Table1[[#This Row],[Emission Factor (kg CO2/ mmBtu)]]*Table1[[#This Row],[Fuel Consumption (mmBtu)]]*10^3 -> 3.6025876e+11 | R60: =(Table1[[#This Row],[CO2 Emissions (g CO2)]])/(Table1[[#This Row],[Generation (TWh)]]*10^9) -> 1903.955
A61: everbright green renewable energy (anhui) holdings co ltd | B61: bioenergy: agricultural waste (solids) | C61: =SUBSTITUTE(Table1[[#This Row],[Fuel]],", ",",") -> bioenergy: agricultural waste (solids) | D61: bioenergy: agricultural waste (solids) | G61: 30 | H61: operating | I61: 2017 | J61: N/A | K61: 32.9194 | L61: 117.6822 | M61: china | N61: =Table1[[#This Row],[Capacity (MW)]]*8760*0.72*10^-6 -> 0.189216 | O61: {=AVERAGE(VLOOKUP(_xlfn.TEXTSPLIT(Table1[[#This Row],[Fuel (no space after comma)]], ","), FuelList_Final_EF!$A$2:$B$32, 2, FALSE))} -> 118.17 | P61: =(16112*Table1[[#This Row],[Generation (TWh)]]*10^9)/10^6 -> 3048648.2 | Q61: =Table1[[#This Row],[Emission Factor (kg CO2/ mmBtu)]]*Table1[[#This Row],[Fuel Consumption (mmBtu)]]*10^3 -> 3.6025876e+11 | R61: =(Table1[[#This Row],[CO2 Emissions (g CO2)]])/(Table1[[#This Row],[Generation (TWh)]]*10^9) -> 1903.955
A62: csic (shanghai) new energy co ltd | B62: bioenergy: agricultural waste (solids), bioenergy: wood & other biomass (solids) | C62: =SUBSTITUTE(Table1[[#This Row],[Fuel]],", ",",") -> bioenergy: agricultural waste (solids),bioenergy: wood & other biomass (solids) | D62: bioenergy: agricultural waste (solids) | E62: bioenergy: wood & other biomass (solids) | G62: 3 | H62: operating | I62: 2016 | J62: N/A | K62: 32.6468 | L62: 115.6476 | M62: china | N62: =Table1[[#This Row],[Capacity (MW)]]*8760*0.72*10^-6 -> 0.0189216 | O62: {=AVERAGE(VLOOKUP(_xlfn.TEXTSPLIT(Table1[[#This Row],[Fuel (no space after comma)]], ","), FuelList_Final_EF!$A$2:$B$32, 2, FALSE))} -> 105.985 | P62: =(16112*Table1[[#This Row],[Generation (TWh)]]*10^9)/10^6 -> 304864.82 | Q62: =Table1[[#This Row],[Emission Factor (kg CO2/ mmBtu)]]*Table1[[#This Row],[Fuel Consumption (mmBtu)]]*10^3 -> 3.2311098e+10 | R62: =(Table1[[#This Row],[CO2 Emissions (g CO2)]])/(Table1[[#This Row],[Generation (TWh)]]*10^9) -> 1707.6303
A63: ningbo energy group co ltd | B63: bioenergy: agricultural waste (solids), bioenergy: wood & other biomass (solids) | C63: =SUBSTITUTE(Table1[[#This Row],[Fuel]],", ",",") -> bioenergy: agricultural waste (solids),bioenergy: wood & other biomass (solids) | D63: bioenergy: agricultural waste (solids) | E63: bioenergy: wood & other biomass (solids) | G63: 27 | H63: operating | I63: 2016 | J63: N/A | K63: 32.6468 | L63: 115.6476 | M63: china | N63: =Table1[[#This Row],[Capacity (MW)]]*8760*0.72*10^-6 -> 0.1702944 | O63: {=AVERAGE(VLOOKUP(_xlfn.TEXTSPLIT(Table1[[#This Row],[Fuel (no space after comma)]], ","), FuelList_Final_EF!$A$2:$B$32, 2, FALSE))} -> 105.985 | P63: =(16112*Table1[[#This Row],[Generation (TWh)]]*10^9)/10^6 -> 2743783.4 | Q63: =Table1[[#This Row],[Emission Factor (kg CO2/ mmBtu)]]*Table1[[#This Row],[Fuel Consumption (mmBtu)]]*10^3 -> 2.9079988e+11 | R63: =(Table1[[#This Row],[CO2 Emissions (g CO2)]])/(Table1[[#This Row],[Generation (TWh)]]*10^9) -> 1707.6303
A64: xianna management consulting co ltd | B64: bioenergy: agricultural waste (solids), bioenergy: wood & other biomass (solids) | C64: =SUBSTITUTE(Table1[[#This Row],[Fuel]],", ",",") -> bioenergy: agricultural waste (solids),bioenergy: wood & other biomass (solids) | D64: bioenergy: agricultural waste (solids) | E64: bioenergy: wood & other biomass (solids) | G64: 1.5 | H64: operating | I64: 2017 | J64: N/A | K64: 32.8684 | L64: 115.8609 | M64: china | N64: =Table1[[#This Row],[Capacity (MW)]]*8760*0.72*10^-6 -> 0.0094608 | O64: {=AVERAGE(VLOOKUP(_xlfn.TEXTSPLIT(Table1[[#This Row],[Fuel (no space after comma)]], ","), FuelList_Final_EF!$A$2:$B$32, 2, FALSE))} -> 105.985 | P64: =(16112*Table1[[#This Row],[Generation (TWh)]]*10^9)/10^6 -> 152432.41 | Q64: =Table1[[#This Row],[Emission Factor (kg CO2/ mmBtu)]]*Table1[[#This Row],[Fuel Consumption (mmBtu)]]*10^3 -> 1.6155549e+10 | R64: =(Table1[[#This Row],[CO2 Emissions (g CO2)]])/(Table1[[#This Row],[Generation (TWh)]]*10^9) -> 1707.6303
A65: anhui guozhen ecological technology co ltd | B65: bioenergy: agricultural waste (solids), bioenergy: wood & other biomass (solids) | C65: =SUBSTITUTE(Table1[[#This Row],[Fuel]],", ",",") -> bioenergy: agricultural waste (solids),bioenergy: wood & other biomass (solids) | D65: bioenergy: agricultural waste (solids) | E65: bioenergy: wood & other biomass (solids) | G65: 28.5 | H65: operating | I65: 2017 | J65: N/A | K65: 32.8684 | L65: 115.8609 | M65: china | N65: =Table1[[#This Row],[Capacity (MW)]]*8760*0.72*10^-6 -> 0.1797552 | O65: {=AVERAGE(VLOOKUP(_xlfn.TEXTSPLIT(Table1[[#This Row],[Fuel (no space after comma)]], ","), FuelList_Final_EF!$A$2:$B$32, 2, FALSE))} -> 105.985 | P65: =(16112*Table1[[#This Row],[Generation (TWh)]]*10^9)/10^6 -> 2896215.8 | Q65: =Table1[[#This Row],[Emission Factor (kg CO2/ mmBtu)]]*Table1[[#This Row],[Fuel Consumption (mmBtu)]]*10^3 -> 3.0695543e+11 | R65: =(Table1[[#This Row],[CO2 Emissions (g CO2)]])/(Table1[[#This Row],[Generation (TWh)]]*10^9) -> 1707.6303
A66: everbright green renewable energy (anhui) holdings co ltd | B66: bioenergy: agricultural waste (solids), bioenergy: wood & other biomass (solids) | C66: =SUBSTITUTE(Table1[[#This Row],[Fuel]],", ",",") -> bioenergy: agricultural waste (solids),bioenergy: wood & other biomass (solids) | D66: bioenergy: agricultural waste (solids) | E66: bioenergy: wood & other biomass (solids) | G66: 30 | H66: operating | I66: 2019 | J66: N/A | K66: 33.445 | L66: 116.1465 | M66: china | N66: =Table1[[#This Row],[Capacity (MW)]]*8760*0.72*10^-6 -> 0.189216 | O66: {=AVERAGE(VLOOKUP(_xlfn.TEXTSPLIT(Table1[[#This Row],[Fuel (no space after comma)]], ","), FuelList_Final_EF!$A$2:$B$32, 2, FALSE))} -> 105.985 | P66: =(16112*Table1[[#This Row],[Generation (TWh)]]*10^9)/10^6 -> 3048648.2 | Q66: =Table1[[#This Row],[Emission Factor (kg CO2/ mmBtu)]]*Table1[[#This Row],[Fuel Consumption (mmBtu)]]*10^3 -> 3.2311098e+11 | R66: =(Table1[[#This Row],[CO2 Emissions (g CO2)]])/(Table1[[#This Row],[Generation (TWh)]]*10^9) -> 1707.6303
A67: national bio energy group ltd | B67: bioenergy: agricultural waste (solids) | C67: =SUBSTITUTE(Table1[[#This Row],[Fuel]],", ",",") -> bioenergy: agricultural waste (solids) | D67: bioenergy: agricultural waste (solids) | G67: 30 | H67: operating | I67: 2010 | J67: N/A | K67: 33.2331 | L67: 117.3372 | M67: china | N67: =Table1[[#This Row],[Capacity (MW)]]*8760*0.72*10^-6 -> 0.189216 | O67: {=AVERAGE(VLOOKUP(_xlfn.TEXTSPLIT(Table1[[#This Row],[Fuel (no space after comma)]], ","), FuelList_Final_EF!$A$2:$B$32, 2, FALSE))} -> 118.17 | P67: =(16112*Table1[[#This Row],[Generation (TWh)]]*10^9)/10^6 -> 3048648.2 | Q67: =Table1[[#This Row],[Emission Factor (kg CO2/ mmBtu)]]*Table1[[#This Row],[Fuel Consumption (mmBtu)]]*10^3 -> 3.6025876e+11 | R67: =(Table1[[#This Row],[CO2 Emissions (g CO2)]])/(Table1[[#This Row],[Generation (TWh)]]*10^9) -> 1903.955
A68: everbright green renewable energy (anhui) holdings co ltd | B68: bioenergy: agricultural waste (solids) | C68: =SUBSTITUTE(Table1[[#This Row],[Fuel]],", ",",") -> bioenergy: agricultural waste (solids) | D68: bioenergy: agricultural waste (solids) | G68: 30 | H68: operating | I68: 2014 | J68: N/A | K68: 31.5124 | L68: 118.0854 | M68: china | N68: =Table1[[#This Row],[Capacity (MW)]]*8760*0.72*10^-6 -> 0.189216 | O68: {=AVERAGE(VLOOKUP(_xlfn.TEXTSPLIT(Table1[[#This Row],[Fuel (no space after comma)]], ","), FuelList_Final_EF!$A$2:$B$32, 2, FALSE))} -> 118.17 | P68: =(16112*Table1[[#This Row],[Generation (TWh)]]*10^9)/10^6 -> 3048648.2 | Q68: =Table1[[#This Row],[Emission Factor (kg CO2/ mmBtu)]]*Table1[[#This Row],[Fuel Consumption (mmBtu)]]*10^3 -> 3.6025876e+11 | R68: =(Table1[[#This Row],[CO2 Emissions (g CO2)]])/(Table1[[#This Row],[Generation (TWh)]]*10^9) -> 1903.955
A69: everbright green renewable energy (anhui) holdings co ltd | B69: bioenergy: agricultural waste (solids), bioenergy: wood & other biomass (solids) | C69: =SUBSTITUTE(Table1[[#This Row],[Fuel]],", ",",") -> bioenergy: agricultural waste (solids),bioenergy: wood & other biomass (solids) | D69: bioenergy: agricultural waste (solids) | E69: bioenergy: wood & other biomass (solids) | G69: 30 | H69: operating | I69: 2016 | J69: N/A | K69: 32.9874 | L69: 117.1134 | M69: china | N69: =Table1[[#This Row],[Capacity (MW)]]*8760*0.72*10^-6 -> 0.189216 | O69: {=AVERAGE(VLOOKUP(_xlfn.TEXTSPLIT(Table1[[#This Row],[Fuel (no space after comma)]], ","), FuelList_Final_EF!$A$2:$B$32, 2, FALSE))} -> 105.985 | P69: =(16112*Table1[[#This Row],[Generation (TWh)]]*10^9)/10^6 -> 3048648.2 | Q69: =Table1[[#This Row],[Emission Factor (kg CO2/ mmBtu)]]*Table1[[#This Row],[Fuel Consumption (mmBtu)]]*10^3 -> 3.2311098e+11 | R69: =(Table1[[#This Row],[CO2 Emissions (g CO2)]])/(Table1[[#This Row],[Generation (TWh)]]*10^9) -> 1707.6303
A70: kaidi ecological and environmental technology co ltd | B70: bioenergy: agricultural waste (solids) | C70: =SUBSTITUTE(Table1[[#This Row],[Fuel]],", ",",") -> bioenergy: agricultural waste (solids) | D70: bioenergy: agricultural waste (solids) | G70: 30 | H70: operating | I70: 2013 | J70: N/A | K70: 32.3901 | L70: 116.2721 | M70: china | N70: =Table1[[#This Row],[Capacity (MW)]]*8760*0.72*10^-6 -> 0.189216 | O70: {=AVERAGE(VLOOKUP(_xlfn.TEXTSPLIT(Table1[[#This Row],[Fuel (no space after comma)]], ","), FuelList_Final_EF!$A$2:$B$32, 2, FALSE))} -> 118.17 | P70: =(16112*Table1[[#This Row],[Generation (TWh)]]*10^9)/10^6 -> 3048648.2 | Q70: =Table1[[#This Row],[Emission Factor (kg CO2/ mmBtu)]]*Table1[[#This Row],[Fuel Consumption (mmBtu)]]*10^3 -> 3.6025876e+11 | R70: =(Table1[[#This Row],[CO2 Emissions (g CO2)]])/(Table1[[#This Row],[Generation (TWh)]]*10^9) -> 1903.955
A71: anhui nenghui green energy co ltd | B71: bioenergy: agricultural waste (solids), bioenergy: wood & other biomass (solids) | C71: =SUBSTITUTE(Table1[[#This Row],[Fuel]],", ",",") -> bioenergy: agricultural waste (solids),bioenergy: wood & other biomass (solids) | D71: bioenergy: agricultural waste (solids) | E71: bioenergy: wood & other biomass (solids) | G71: 30 | H71: operating | I71: 2013 | J71: N/A | K71: 31.4277 | L71: 116.3726 | M71: china | N71: =Table1[[#This Row],[Capacity (MW)]]*8760*0.72*10^-6 -> 0.189216 | O71: {=AVERAGE(VLOOKUP(_xlfn.TEXTSPLIT(Table1[[#This Row],[Fuel (no space after comma)]], ","), FuelList_Final_EF!$A$2:$B$32, 2, FALSE))} -> 105.985 | P71: =(16112*Table1[[#This Row],[Generation (TWh)]]*10^9)/10^6 -> 3048648.2 | Q71: =Table1[[#This Row],[Emission Factor (kg CO2/ mmBtu)]]*Table1[[#This Row],[Fuel Consumption (mmBtu)]]*10^3 -> 3.2311098e+11 | R71: =(Table1[[#This Row],[CO2 Emissions (g CO2)]])/(Table1[[#This Row],[Generation (TWh)]]*10^9) -> 1707.6303
A72: kaidi sunshine bioenergy investment co ltd | B72: bioenergy: agricultural waste (solids), bioenergy: wood & other biomass (solids) | C72: =SUBSTITUTE(Table1[[#This Row],[Fuel]],", ",",") -> bioenergy: agricultural waste (solids),bioenergy: wood & other biomass (solids) | D72: bioenergy: agricultural waste (solids) | E72: bioenergy: wood & other biomass (solids) | G72: 30 | H72: operating | I72: 2013 | J72: N/A | K72: 31.7549 | L72: 115.9382 | M72: china | N72: =Table1[[#This Row],[Capacity (MW)]]*8760*0.72*10^-6 -> 0.189216 | O72: {=AVERAGE(VLOOKUP(_xlfn.TEXTSPLIT(Table1[[#This Row],[Fuel (no space after comma)]], ","), FuelList_Final_EF!$A$2:$B$32, 2, FALSE))} -> 105.985 | P72: =(16112*Table1[[#This Row],[Generation (TWh)]]*10^9)/10^6 -> 3048648.2 | Q72: =Table1[[#This Row],[Emission Factor (kg CO2/ mmBtu)]]*Table1[[#This Row],[Fuel Consumption (mmBtu)]]*10^3 -> 3.2311098e+11 | R72: =(Table1[[#This Row],[CO2 Emissions (g CO2)]])/(Table1[[#This Row],[Generation (TWh)]]*10^9) -> 1707.6303
A73: li'ang ecology energy co ltd | B73: bioenergy: agricultural waste (solids), bioenergy: wood & other biomass (solids) | C73: =SUBSTITUTE(Table1[[#This Row],[Fuel]],", ",",") -> bioenergy: agricultural waste (solids),bioenergy: wood & other biomass (solids) | D73: bioenergy: agricultural waste (solids) | E73: bioenergy: wood & other biomass (solids) | G73: 30 | H73: operating | I73: 2016 | J73: N/A | K73: 31.0045 | L73: 119.109 | M73: china | N73: =Table1[[#This Row],[Capacity (MW)]]*8760*0.72*10^-6 -> 0.189216 | O73: {=AVERAGE(VLOOKUP(_xlfn.TEXTSPLIT(Table1[[#This Row],[Fuel (no space after comma)]], ","), FuelList_Final_EF!$A$2:$B$32, 2, FALSE))} -> 105.985 | P73: =(16112*Table1[[#This Row],[Generation (TWh)]]*10^9)/10^6 -> 3048648.2 | Q73: =Table1[[#This Row],[Emission Factor (kg CO2/ mmBtu)]]*Table1[[#This Row],[Fuel Consumption (mmBtu)]]*10^3 -> 3.2311098e+11 | R73: =(Table1[[#This Row],[CO2 Emissions (g CO2)]])/(Table1[[#This Row],[Generation (TWh)]]*10^9) -> 1707.6303
A74: li'ang ecology energy co ltd | B74: bioenergy: agricultural waste (solids), bioenergy: wood & other biomass (solids) | C74: =SUBSTITUTE(Table1[[#This Row],[Fuel]],", ",",") -> bioenergy: agricultural waste (solids),bioenergy: wood & other biomass (solids) | D74: bioenergy: agricultural waste (solids) | E74: bioenergy: wood & other biomass (solids) | G74: 30 | H74: pre-construction | I74: N/A | J74: N/A | K74: 31.0045 | L74: 119.109 | M74: china | N74: =Table1[[#This Row],[Capacity (MW)]]*8760*0.72*10^-6 -> 0.189216 | O74: {=AVERAGE(VLOOKUP(_xlfn.TEXTSPLIT(Table1[[#This Row],[Fuel (no space after comma)]], ","), FuelList_Final_EF!$A$2:$B$32, 2, FALSE))} -> 105.985 | P74: =(16112*Table1[[#This Row],[Generation (TWh)]]*10^9)/10^6 -> 3048648.2 | Q74: =Table1[[#This Row],[Emission Factor (kg CO2/ mmBtu)]]*Table1[[#This Row],[Fuel Consumption (mmBtu)]]*10^3 -> 3.2311098e+11 | R74: =(Table1[[#This Row],[CO2 Emissions (g CO2)]])/(Table1[[#This Row],[Generation (TWh)]]*10^9) -> 1707.6303
A75: li'ang ecology energy co ltd | B75: bioenergy: agricultural waste (solids), bioenergy: wood & other biomass (solids) | C75: =SUBSTITUTE(Table1[[#This Row],[Fuel]],", ",",") -> bioenergy: agricultural waste (solids),bioenergy: wood & other biomass (solids) | D75: bioenergy: agricultural waste (solids) | E75: bioenergy: wood & other biomass (solids) | G75: 30 | H75: announced | I75: N/A | J75: N/A | K75: 31.0045 | L75: 119.109 | M75: china | N75: =Table1[[#This Row],[Capacity (MW)]]*8760*0.72*10^-6 -> 0.189216 | O75: {=AVERAGE(VLOOKUP(_xlfn.TEXTSPLIT(Table1[[#This Row],[Fuel (no space after comma)]], ","), FuelList_Final_EF!$A$2:$B$32, 2, FALSE))} -> 105.985 | P75: =(16112*Table1[[#This Row],[Generation (TWh)]]*10^9)/10^6 -> 3048648.2 | Q75: =Table1[[#This Row],[Emission Factor (kg CO2/ mmBtu)]]*Table1[[#This Row],[Fuel Consumption (mmBtu)]]*10^3 -> 3.2311098e+11 | R75: =(Table1[[#This Row],[CO2 Emissions (g CO2)]])/(Table1[[#This Row],[Generation (TWh)]]*10^9) -> 1707.6303
A76: li'ang ecology energy co ltd | B76: bioenergy: agricultural waste (solids), bioenergy: wood & other biomass (solids) | C76: =SUBSTITUTE(Table1[[#This Row],[Fuel]],", ",",") -> bioenergy: agricultural waste (solids),bioenergy: wood & other biomass (solids) | D76: bioenergy: agricultural waste (solids) | E76: bioenergy: wood & other biomass (solids) | G76: 30 | H76: announced | I76: N/A | J76: N/A | K76: 31.0045 | L76: 119.109 | M76: china | N76: =Table1[[#This Row],[Capacity (MW)]]*8760*0.72*10^-6 -> 0.189216 | O76: {=AVERAGE(VLOOKUP(_xlfn.TEXTSPLIT(Table1[[#This Row],[Fuel (no space after comma)]], ","), FuelList_Final_EF!$A$2:$B$32, 2, FALSE))} -> 105.985 | P76: =(16112*Table1[[#This Row],[Generation (TWh)]]*10^9)/10^6 -> 3048648.2 | Q76: =Table1[[#This Row],[Emission Factor (kg CO2/ mmBtu)]]*Table1[[#This Row],[Fuel Consumption (mmBtu)]]*10^3 -> 3.2311098e+11 | R76: =(Table1[[#This Row],[CO2 Emissions (g CO2)]])/(Table1[[#This Row],[Generation (TWh)]]*10^9) -> 1707.6303
A77: nanjing keyuan smart energy investment co ltd | B77: bioenergy: agricultural waste (solids), bioenergy: wood & other biomass (solids) | C77: =SUBSTITUTE(Table1[[#This Row],[Fuel]],", ",",") -> bioenergy: agricultural waste (solids),bioenergy: wood & other biomass (solids) | D77: bioenergy: agricultural waste (solids) | E77: bioenergy: wood & other biomass (solids) | G77: 21 | H77: operating | I77: 2021 | J77: N/A | K77: 33.6094 | L77: 117.5601 | M77: china | N77: =Table1[[#This Row],[Capacity (MW)]]*8760*0.72*10^-6 -> 0.1324512 | O77: {=AVERAGE(VLOOKUP(_xlfn.TEXTSPLIT(Table1[[#This Row],[Fuel (no space after comma)]], ","), FuelList_Final_EF!$A$2:$B$32, 2, FALSE))} -> 105.985 | P77: =(16112*Table1[[#This Row],[Generation (TWh)]]*10^9)/10^6 -> 2134053.7 | Q77: =Table1[[#This Row],[Emission Factor (kg CO2/ mmBtu)]]*Table1[[#This Row],[Fuel Consumption (mmBtu)]]*10^3 -> 2.2617769e+11 | R77: =(Table1[[#This Row],[CO2 Emissions (g CO2)]])/(Table1[[#This Row],[Generation (TWh)]]*10^9) -> 1707.6303
A78: anhui guozhen ecological technology co ltd | B78: bioenergy: agricultural waste (solids), bioenergy: wood & other biomass (solids) | C78: =SUBSTITUTE(Table1[[#This Row],[Fuel]],", ",",") -> bioenergy: agricultural waste (solids),bioenergy: wood & other biomass (solids) | D78: bioenergy: agricultural waste (solids) | E78: bioenergy: wood & other biomass (solids) | G78: 9 | H78: operating | I78: 2021 | J78: N/A | K78: 33.6094 | L78: 117.5601 | M78: china | N78: =Table1[[#This Row],[Capacity (MW)]]*8760*0.72*10^-6 -> 0.0567648 | O78: {=AVERAGE(VLOOKUP(_xlfn.TEXTSPLIT(Table1[[#This Row],[Fuel (no space after comma)]], ","), FuelList_Final_EF!$A$2:$B$32, 2, FALSE))} -> 105.985 | P78: =(16112*Table1[[#This Row],[Generation (TWh)]]*10^9)/10^6 -> 914594.46 | Q78: =Table1[[#This Row],[Emission Factor (kg CO2/ mmBtu)]]*Table1[[#This Row],[Fuel Consumption (mmBtu)]]*10^3 -> 9.6933294e+10 | R78: =(Table1[[#This Row],[CO2 Emissions (g CO2)]])/(Table1[[#This Row],[Generation (TWh)]]*10^9) -> 1707.6303
A79: everbright green renewable energy (anhui) holdings co ltd | B79: bioenergy: agricultural waste (solids) | C79: =SUBSTITUTE(Table1[[#This Row],[Fuel]],", ",",") -> bioenergy: agricultural waste (solids) | D79: bioenergy: agricultural waste (solids) | G79: 30 | H79: operating | I79: 2017 | J79: N/A | K79: 33.7702 | L79: 117.4556 | M79: china | N79: =Table1[[#This Row],[Capacity (MW)]]*8760*0.72*10^-6 -> 0.189216 | O79: {=AVERAGE(VLOOKUP(_xlfn.TEXTSPLIT(Table1[[#This Row],[Fuel (no space after comma)]], ","), FuelList_Final_EF!$A$2:$B$32, 2, FALSE))} -> 118.17 | P79: =(16112*Table1[[#This Row],[Generation (TWh)]]*10^9)/10^6 -> 3048648.2 | Q79: =Table1[[#This Row],[Emission Factor (kg CO2/ mmBtu)]]*Table1[[#This Row],[Fuel Consumption (mmBtu)]]*10^3 -> 3.6025876e+11 | R79: =(Table1[[#This Row],[CO2 Emissions (g CO2)]])/(Table1[[#This Row],[Generation (TWh)]]*10^9) -> 1903.955
A80: national bio energy group ltd | B80: bioenergy: agricultural waste (solids), bioenergy: wood & other biomass (solids) | C80: =SUBSTITUTE(Table1[[#This Row],[Fuel]],", ",",") -> bioenergy: agricultural waste (solids),bioenergy: wood & other biomass (solids) | D80: bioenergy: agricultural waste (solids) | E80: bioenergy: wood & other biomass (solids) | G80: 35 | H80: operating | I80: 2021 | J80: N/A | K80: 33.0183 | L80: 115.3415 | M80: china | N80: =Table1[[#This Row],[Capacity (MW)]]*8760*0.72*10^-6 -> 0.220752 | O80: {=AVERAGE(VLOOKUP(_xlfn.TEXTSPLIT(Table1[[#This Row],[Fuel (no space after comma)]], ","), FuelList_Final_EF!$A$2:$B$32, 2, FALSE))} -> 105.985 | P80: =(16112*Table1[[#This Row],[Generation (TWh)]]*10^9)/10^6 -> 3556756.2 | Q80: =Table1[[#This Row],[Emission Factor (kg CO2/ mmBtu)]]*Table1[[#This Row],[Fuel Consumption (mmBtu)]]*10^3 -> 3.7696281e+11 | R80: =(Table1[[#This Row],[CO2 Emissions (g CO2)]])/(Table1[[#This Row],[Generation (TWh)]]*10^9) -> 1707.6303
A81: anhui wanneng environmental technology co ltd | B81: bioenergy: agricultural waste (solids) | C81: =SUBSTITUTE(Table1[[#This Row],[Fuel]],", ",",") -> bioenergy: agricultural waste (solids) | D81: bioenergy: agricultural waste (solids) | G81: 30 | H81: operating | I81: 2022 | J81: N/A | K81: 33.2428 | L81: 116.0563 | M81: china | N81: =Table1[[#This Row],[Capacity (MW)]]*8760*0.72*10^-6 -> 0.189216 | O81: {=AVERAGE(VLOOKUP(_xlfn.TEXTSPLIT(Table1[[#This Row],[Fuel (no space after comma)]], ","), FuelList_Final_EF!$A$2:$B$32, 2, FALSE))} -> 118.17 | P81: =(16112*Table1[[#This Row],[Generation (TWh)]]*10^9)/10^6 -> 3048648.2 | Q81: =Table1[[#This Row],[Emission Factor (kg CO2/ mmBtu)]]*Table1[[#This Row],[Fuel Consumption (mmBtu)]]*10^3 -> 3.6025876e+11 | R81: =(Table1[[#This Row],[CO2 Emissions (g CO2)]])/(Table1[[#This Row],[Generation (TWh)]]*10^9) -> 1903.955
A82: china energy conservation (shandong) investment development co ltd | B82: bioenergy: agricultural waste (solids), bioenergy: wood & other biomass (solids) | C82: =SUBSTITUTE(Table1[[#This Row],[Fuel]],", ",",") -> bioenergy: agricultural waste (solids),bioenergy: wood & other biomass (solids) | D82: bioenergy: agricultural waste (solids) | E82: bioenergy: wood & other biomass (solids) | G82: 21 | H82: operating | I82: 2015 | J82: N/A | K82: 31.3832 | L82: 116.9812 | M82: china | N82: =Table1[[#This Row],[Capacity (MW)]]*8760*0.72*10^-6 -> 0.1324512 | O82: {=AVERAGE(VLOOKUP(_xlfn.TEXTSPLIT(Table1[[#This Row],[Fuel (no space after comma)]], ","), FuelList_Final_EF!$A$2:$B$32, 2, FALSE))} -> 105.985 | P82: =(16112*Table1[[#This Row],[Generation (TWh)]]*10^9)/10^6 -> 2134053.7 | Q82: =Table1[[#This Row],[Emission Factor (kg CO2/ mmBtu)]]*Table1[[#This Row],[Fuel Consumption (mmBtu)]]*10^3 -> 2.2617769e+11 | R82: =(Table1[[#This Row],[CO2 Emissions (g CO2)]])/(Table1[[#This Row],[Generation (TWh)]]*10^9) -> 1707.6303
A83: shucheng yingqi new energy co ltd | B83: bioenergy: agricultural waste (solids), bioenergy: wood & other biomass (solids) | C83: =SUBSTITUTE(Table1[[#This Row],[Fuel]],", ",",") -> bioenergy: agricultural waste (solids),bioenergy: wood & other biomass (solids) | D83: bioenergy: agricultural waste (solids) | E83: bioenergy: wood & other biomass (solids) | G83: 9 | H83: operating | I83: 2015 | J83: N/A | K83: 31.3832 | L83: 116.9812 | M83: china | N83: =Table1[[#This Row],[Capacity (MW)]]*8760*0.72*10^-6 -> 0.0567648 | O83: {=AVERAGE(VLOOKUP(_xlfn.TEXTSPLIT(Table1[[#This Row],[Fuel (no space after comma)]], ","), FuelList_Final_EF!$A$2:$B$32, 2, FALSE))} -> 105.985 | P83: =(16112*Table1[[#This Row],[Generation (TWh)]]*10^9)/10^6 -> 914594.46 | Q83: =Table1[[#This Row],[Emission Factor (kg CO2/ mmBtu)]]*Table1[[#This Row],[Fuel Consumption (mmBtu)]]*10^3 -> 9.6933294e+10 | R83: =(Table1[[#This Row],[CO2 Emissions (g CO2)]])/(Table1[[#This Row],[Generation (TWh)]]*10^9) -> 1707.6303
A84: kaidi ecological and environmental technology co ltd | B84: bioenergy: agricultural waste (solids) | C84: =SUBSTITUTE(Table1[[#This Row],[Fuel]],", ",",") -> bioenergy: agricultural waste (solids) | D84: bioenergy: agricultural waste (solids) | G84: 30 | H84: operating | I84: 2013 | J84: N/A | K84: 31.2499 | L84: 117.2283 | M84: china | N84: =Table1[[#This Row],[Capacity (MW)]]*8760*0.72*10^-6 -> 0.189216 | O84: {=AVERAGE(VLOOKUP(_xlfn.TEXTSPLIT(Table1[[#This Row],[Fuel (no space after comma)]], ","), FuelList_Final_EF!$A$2:$B$32, 2, FALSE))} -> 118.17 | P84: =(16112*Table1[[#This Row],[Generation (TWh)]]*10^9)/10^6 -> 3048648.2 | Q84: =Table1[[#This Row],[Emission Factor (kg CO2/ mmBtu)]]*Table1[[#This Row],[Fuel Consumption (mmBtu)]]*10^3 -> 3.6025876e+11 | R84: =(Table1[[#This Row],[CO2 Emissions (g CO2)]])/(Table1[[#This Row],[Generation (TWh)]]*10^9) -> 1903.955
A85: shanying international holdings co ltd | B85: bioenergy: paper mill wastes | C85: =SUBSTITUTE(Table1[[#This Row],[Fuel]],", ",",") -> bioenergy: paper mill wastes | D85: bioenergy: paper mill wastes | G85: 30 | H85: operating | I85: 2022 | J85: N/A | K85: 31.7369 | L85: 118.4895 | M85: china | N85: =Table1[[#This Row],[Capacity (MW)]]*8760*0.72*10^-6 -> 0.189216 | O85: {=AVERAGE(VLOOKUP(_xlfn.TEXTSPLIT(Table1[[#This Row],[Fuel (no space after comma)]], ","), FuelList_Final_EF!$A$2:$B$32, 2, FALSE))} -> 100.47443 | P85: =(16112*Table1[[#This Row],[Generation (TWh)]]*10^9)/10^6 -> 3048648.2 | Q85: =Table1[[#This Row],[Emission Factor (kg CO2/ mmBtu)]]*Table1[[#This Row],[Fuel Consumption (mmBtu)]]*10^3 -> 3.063112e+11 | R85: =(Table1[[#This Row],[CO2 Emissions (g CO2)]])/(Table1[[#This Row],[Generation (TWh)]]*10^9) -> 1618.8441
A86: national bio energy group ltd | B86: bioenergy: agricultural waste (solids), bioenergy: wood & other biomass (solids) | C86: =SUBSTITUTE(Table1[[#This Row],[Fuel]],", ",",") -> bioenergy: agricultural waste (solids),bioenergy: wood & other biomass (solids) | D86: bioenergy: agricultural waste (solids) | E86: bioenergy: wood & other biomass (solids) | G86: 30 | H86: operating | I86: 2015 | J86: N/A | K86: 33.2717 | L86: 116.508 | M86: china | N86: =Table1[[#This Row],[Capacity (MW)]]*8760*0.72*10^-6 -> 0.189216 | O86: {=AVERAGE(VLOOKUP(_xlfn.TEXTSPLIT(Table1[[#This Row],[Fuel (no space after comma)]], ","), FuelList_Final_EF!$A$2:$B$32, 2, FALSE))} -> 105.985 | P86: =(16112*Table1[[#This Row],[Generation (TWh)]]*10^9)/10^6 -> 3048648.2 | Q86: =Table1[[#This Row],[Emission Factor (kg CO2/ mmBtu)]]*Table1[[#This Row],[Fuel Consumption (mmBtu)]]*10^3 -> 3.2311098e+11 | R86: =(Table1[[#This Row],[CO2 Emissions (g CO2)]])/(Table1[[#This Row],[Generation (TWh)]]*10^9) -> 1707.6303
A87: anhui guozhen ecological technology co ltd | B87: bioenergy: agricultural waste (solids), bioenergy: wood & other biomass (solids) | C87: =SUBSTITUTE(Table1[[#This Row],[Fuel]],", ",",") -> bioenergy: agricultural waste (solids),bioenergy: wood & other biomass (solids) | D87: bioenergy: agricultural waste (solids) | E87: bioenergy: wood & other biomass (solids) | G87: 30 | H87: operating | I87: 2019 | J87: N/A | K87: 32.8582 | L87: 118.0843 | M87: china | N87: =Table1[[#This Row],[Capacity (MW)]]*8760*0.72*10^-6 -> 0.189216 | O87: {=AVERAGE(VLOOKUP(_xlfn.TEXTSPLIT(Table1[[#This Row],[Fuel (no space after comma)]], ","), FuelList_Final_EF!$A$2:$B$32, 2, FALSE))} -> 105.985 | P87: =(16112*Table1[[#This Row],[Generation (TWh)]]*10^9)/10^6 -> 3048648.2 | Q87: =Table1[[#This Row],[Emission Factor (kg CO2/ mmBtu)]]*Table1[[#This Row],[Fuel Consumption (mmBtu)]]*10^3 -> 3.2311098e+11 | R87: =(Table1[[#This Row],[CO2 Emissions (g CO2)]])/(Table1[[#This Row],[Generation (TWh)]]*10^9) -> 1707.6303
A88: kaidi ecological and environmental technology co ltd | B88: bioenergy: agricultural waste (solids), bioenergy: wood & other biomass (solids) | C88: =SUBSTITUTE(Table1[[#This Row],[Fuel]],", ",",") -> bioenergy: agricultural waste (solids),bioenergy: wood & other biomass (solids) | D88: bioenergy: agricultural waste (solids) | E88: bioenergy: wood & other biomass (solids) | G88: 30 | H88: operating | I88: 2012 | J88: N/A | K88: 30.9186 | L88: 118.2692 | M88: china | N88: =Table1[[#This Row],[Capacity (MW)]]*8760*0.72*10^-6 -> 0.189216 | O88: {=AVERAGE(VLOOKUP(_xlfn.TEXTSPLIT(Table1[[#This Row],[Fuel (no space after comma)]], ","), FuelList_Final_EF!$A$2:$B$32, 2, FALSE))} -> 105.985 | P88: =(16112*Table1[[#This Row],[Generation (TWh)]]*10^9)/10^6 -> 3048648.2 | Q88: =Table1[[#This Row],[Emission Factor (kg CO2/ mmBtu)]]*Table1[[#This Row],[Fuel Consumption (mmBtu)]]*10^3 -> 3.2311098e+11 | R88: =(Table1[[#This Row],[CO2 Emissions (g CO2)]])/(Table1[[#This Row],[Generation (TWh)]]*10^9) -> 1707.6303
A89: everbright green renewable energy (anhui) holdings co ltd | B89: bioenergy: agricultural waste (solids) | C89: =SUBSTITUTE(Table1[[#This Row],[Fuel]],", ",",") -> bioenergy: agricultural waste (solids) | D89: bioenergy: agricultural waste (solids) | G89: 30 | H89: operating | I89: 2017 | J89: N/A | K89: 32.4524 | L89: 118.292 | M89: china | N89: =Table1[[#This Row],[Capacity (MW)]]*8760*0.72*10^-6 -> 0.189216 | O89: {=AVERAGE(VLOOKUP(_xlfn.TEXTSPLIT(Table1[[#This Row],[Fuel (no space after comma)]], ","), FuelList_Final_EF!$A$2:$B$32, 2, FALSE))} -> 118.17 | P89: =(16112*Table1[[#This Row],[Generation (TWh)]]*10^9)/10^6 -> 3048648.2 | Q89: =Table1[[#This Row],[Emission Factor (kg CO2/ mmBtu)]]*Table1[[#This Row],[Fuel Consumption (mmBtu)]]*10^3 -> 3.6025876e+11 | R89: =(Table1[[#This Row],[CO2 Emissions (g CO2)]])/(Table1[[#This Row],[Generation (TWh)]]*10^9) -> 1903.955
A90: kaidi ecological and environmental technology co ltd | B90: bioenergy: agricultural waste (solids), bioenergy: wood & other biomass (solids) | C90: =SUBSTITUTE(Table1[[#This Row],[Fuel]],", ",",") -> bioenergy: agricultural waste (solids),bioenergy: wood & other biomass (solids) | D90: bioenergy: agricultural waste (solids) | E90: bioenergy: wood & other biomass (solids) | G90: 30 | H90: operating | I90: 2018 | J90: N/A | K90: 30.697 | L90: 118.9249 | M90: china | N90: =Table1[[#This Row],[Capacity (MW)]]*8760*0.72*10^-6 -> 0.189216 | O90: {=AVERAGE(VLOOKUP(_xlfn.TEXTSPLIT(Table1[[#This Row],[Fuel (no space after comma)]], ","), FuelList_Final_EF!$A$2:$B$32, 2, FALSE))} -> 105.985 | P90: =(16112*Table1[[#This Row],[Generation (TWh)]]*10^9)/10^6 -> 3048648.2 | Q90: =Table1[[#This Row],[Emission Factor (kg CO2/ mmBtu)]]*Table1[[#This Row],[Fuel Consumption (mmBtu)]]*10^3 -> 3.2311098e+11 | R90: =(Table1[[#This Row],[CO2 Emissions (g CO2)]])/(Table1[[#This Row],[Generation (TWh)]]*10^9) -> 1707.6303
A91: ningguo ninggang industrial investment co ltd | B91: bioenergy: agricultural waste (solids) | C91: =SUBSTITUTE(Table1[[#This Row],[Fuel]],", ",",") -> bioenergy: agricultural waste (solids) | D91: bioenergy: agricultural waste (solids) | G91: 30 | H91: construction | I91: N/A | J91: N/A | K91: 30.7039 | L91: 118.8798 | M91: china | N91: =Table1[[#This Row],[Capacity (MW)]]*8760*0.72*10^-6 -> 0.189216 | O91: {=AVERAGE(VLOOKUP(_xlfn.TEXTSPLIT(Table1[[#This Row],[Fuel (no space after comma)]], ","), FuelList_Final_EF!$A$2:$B$32, 2, FALSE))} -> 118.17 | P91: =(16112*Table1[[#This Row],[Generation (TWh)]]*10^9)/10^6 -> 3048648.2 | Q91: =Table1[[#This Row],[Emission Factor (kg CO2/ mmBtu)]]*Table1[[#This Row],[Fuel Consumption (mmBtu)]]*10^3 -> 3.6025876e+11 | R91: =(Table1[[#This Row],[CO2 Emissions (g CO2)]])/(Table1[[#This Row],[Generation (TWh)]]*10^9) -> 1903.955
A92: national bio energy group ltd | B92: bioenergy: agricultural waste (solids) | C92: =SUBSTITUTE(Table1[[#This Row],[Fuel]],", ",",") -> bioenergy: agricultural waste (solids) | D92: bioenergy: agricultural waste (solids) | G92: 30 | H92: operating | I92: 2013 | J92: N/A | K92: 32.4928 | L92: 116.7235 | M92: china | N92: =Table1[[#This Row],[Capacity (MW)]]*8760*0.72*10^-6 -> 0.189216 | O92: {=AVERAGE(VLOOKUP(_xlfn.TEXTSPLIT(Table1[[#This Row],[Fuel (no space after comma)]], ","), FuelList_Final_EF!$A$2:$B$32, 2, FALSE))} -> 118.17 | P92: =(16112*Table1[[#This Row],[Generation (TWh)]]*10^9)/10^6 -> 3048648.2 | Q92: =Table1[[#This Row],[Emission Factor (kg CO2/ mmBtu)]]*Table1[[#This Row],[Fuel Consumption (mmBtu)]]*10^3 -> 3.6025876e+11 | R92: =(Table1[[#This Row],[CO2 Emissions (g CO2)]])/(Table1[[#This Row],[Generation (TWh)]]*10^9) -> 1903.955
A93: shenzhen energy environmental protection co ltd | B93: bioenergy: agricultural waste (solids), bioenergy: wood & other biomass (solids) | C93: =SUBSTITUTE(Table1[[#This Row],[Fuel]],", ",",") -> bioenergy: agricultural waste (solids),bioenergy: wood & other biomass (solids) | D93: bioenergy: agricultural waste (solids) | E93: bioenergy: wood & other biomass (solids) | G93: 40 | H93: operating | I93: 2020 | J93: N/A | K93: 33.5684 | L93: 117.8978 | M93: china | N93: =Table1[[#This Row],[Capacity (MW)]]*8760*0.72*10^-6 -> 0.252288 | O93: {=AVERAGE(VLOOKUP(_xlfn.TEXTSPLIT(Table1[[#This Row],[Fuel (no space after comma)]], ","), FuelList_Final_EF!$A$2:$B$32, 2, FALSE))} -> 105.985 | P93: =(16112*Table1[[#This Row],[Generation (TWh)]]*10^9)/10^6 -> 4064864.3 | Q93: =Table1[[#This Row],[Emission Factor (kg CO2/ mmBtu)]]*Table1[[#This Row],[Fuel Consumption (mmBtu)]]*10^3 -> 4.3081464e+11 | R93: =(Table1[[#This Row],[CO2 Emissions (g CO2)]])/(Table1[[#This Row],[Generation (TWh)]]*10^9) -> 1707.6303
A94: shanghai electrical equipment (anhui) investment co ltd | B94: bioenergy: agricultural waste (solids), bioenergy: wood & other biomass (solids) | C94: =SUBSTITUTE(Table1[[#This Row],[Fuel]],", ",",") -> bioenergy: agricultural waste (solids),bioenergy: wood & other biomass (solids) | D94: bioenergy: agricultural waste (solids) | E94: bioenergy: wood & other biomass (solids) | G94: 26.7 | H94: operating | I94: 2020 | J94: N/A | K94: 33.5301 | L94: 116.8807 | M94: china | N94: =Table1[[#This Row],[Capacity (MW)]]*8760*0.72*10^-6 -> 0.16840224 | O94: {=AVERAGE(VLOOKUP(_xlfn.TEXTSPLIT(Table1[[#This Row],[Fuel (no space after comma)]], ","), FuelList_Final_EF!$A$2:$B$32, 2, FALSE))} -> 105.985 | P94: =(16112*Table1[[#This Row],[Generation (TWh)]]*10^9)/10^6 -> 2713296.9 | Q94: =Table1[[#This Row],[Emission Factor (kg CO2/ mmBtu)]]*Table1[[#This Row],[Fuel Consumption (mmBtu)]]*10^3 -> 2.8756877e+11 | R94: =(Table1[[#This Row],[CO2 Emissions (g CO2)]])/(Table1[[#This Row],[Generation (TWh)]]*10^9) -> 1707.6303
A95: other | B95: bioenergy: agricultural waste (solids), bioenergy: wood & other biomass (solids) | C95: =SUBSTITUTE(Table1[[#This Row],[Fuel]],", ",",") -> bioenergy: agricultural waste (solids),bioenergy: wood & other biomass (solids) | D95: bioenergy: agricultural waste (solids) | E95: bioenergy: wood & other biomass (solids) | G95: 0.3 | H95: operating | I95: 2020 | J95: N/A | K95: 33.5301 | L95: 116.8807 | M95: china | N95: =Table1[[#This Row],[Capacity (MW)]]*8760*0.72*10^-6 -> 0.00189216 | O95: {=AVERAGE(VLOOKUP(_xlfn.TEXTSPLIT(Table1[[#This Row],[Fuel (no space after comma)]], ","), FuelList_Final_EF!$A$2:$B$32, 2, FALSE))} -> 105.985 | P95: =(16112*Table1[[#This Row],[Generation (TWh)]]*10^9)/10^6 -> 30486.482 | Q95: =Table1[[#This Row],[Emission Factor (kg CO2/ mmBtu)]]*Table1[[#This Row],[Fuel Consumption (mmBtu)]]*10^3 -> 3.2311098e+09 | R95: =(Table1[[#This Row],[CO2 Emissions (g CO2)]])/(Table1[[#This Row],[Generation (TWh)]]*10^9) -> 1707.6303
A96: shengyi holdings investment co ltd | B96: bioenergy: agricultural waste (solids), bioenergy: wood & other biomass (solids) | C96: =SUBSTITUTE(Table1[[#This Row],[Fuel]],", ",",") -> bioenergy: agricultural waste (solids),bioenergy: wood & other biomass (solids) | D96: bioenergy: agricultural waste (solids) | E96: bioenergy: wood & other biomass (solids) | G96: 2.7 | H96: operating | I96: 2020 | J96: N/A | K96: 33.5301 | L96: 116.8807 | M96: china | N96: =Table1[[#This Row],[Capacity (MW)]]*8760*0.72*10^-6 -> 0.01702944 | O96: {=AVERAGE(VLOOKUP(_xlfn.TEXTSPLIT(Table1[[#This Row],[Fuel (no space after comma)]], ","), FuelList_Final_EF!$A$2:$B$32, 2, FALSE))} -> 105.985 | P96: =(16112*Table1[[#This Row],[Generation (TWh)]]*10^9)/10^6 -> 274378.34 | Q96: =Table1[[#This Row],[Emission Factor (kg CO2/ mmBtu)]]*Table1[[#This Row],[Fuel Consumption (mmBtu)]]*10^3 -> 2.9079988e+10 | R96: =(Table1[[#This Row],[CO2 Emissions (g CO2)]])/(Table1[[#This Row],[Generation (TWh)]]*10^9) -> 1707.6303
A97: shanghai pudong environmental development co ltd | B97: bioenergy: agricultural waste (solids) | C97: =SUBSTITUTE(Table1[[#This Row],[Fuel]],", ",",") -> bioenergy: agricultural waste (solids) | D97: bioenergy: agricultural waste (solids) | G97: 30 | H97: operating | I97: 2018 | J97: N/A | K97: 33.8416 | L97: 116.7081 | M97: china | N97: =Table1[[#This Row],[Capacity (MW)]]*8760*0.72*10^-6 -> 0.189216 | O97: {=AVERAGE(VLOOKUP(_xlfn.TEXTSPLIT(Table1[[#This Row],[Fuel (no space after comma)]], ","), FuelList_Final_EF!$A$2:$B$32, 2, FALSE))} -> 118.17 | P97: =(16112*Table1[[#This Row],[Generation (TWh)]]*10^9)/10^6 -> 3048648.2 | Q97: =Table1[[#This Row],[Emission Factor (kg CO2/ mmBtu)]]*Table1[[#This Row],[Fuel Consumption (mmBtu)]]*10^3 -> 3.6025876e+11 | R97: =(Table1[[#This Row],[CO2 Emissions (g CO2)]])/(Table1[[#This Row],[Generation (TWh)]]*10^9) -> 1903.955
A98: shanying international holdings co ltd | B98: bioenergy: agricultural waste (solids) | C98: =SUBSTITUTE(Table1[[#This Row],[Fuel]],", ",",") -> bioenergy: agricultural waste (solids) | D98: bioenergy: agricultural waste (solids) | G98: 30 | H98: construction | I98: 2024 | J98: N/A | K98: 33.6814 | L98: 117.2694 | M98: china | N98: =Table1[[#This Row],[Capacity (MW)]]*8760*0.72*10^-6 -> 0.189216 | O98: {=AVERAGE(VLOOKUP(_xlfn.TEXTSPLIT(Table1[[#This Row],[Fuel (no space after comma)]], ","), FuelList_Final_EF!$A$2:$B$32, 2, FALSE))} -> 118.17 | P98: =(16112*Table1[[#This Row],[Generation (TWh)]]*10^9)/10^6 -> 3048648.2 | Q98: =Table1[[#This Row],[Emission Factor (kg CO2/ mmBtu)]]*Table1[[#This Row],[Fuel Consumption (mmBtu)]]*10^3 -> 3.6025876e+11 | R98: =(Table1[[#This Row],[CO2 Emissions (g CO2)]])/(Table1[[#This Row],[Generation (TWh)]]*10^9) -> 1903.955
A99: shanying international holdings co ltd | B99: bioenergy: agricultural waste (solids) | C99: =SUBSTITUTE(Table1[[#This Row],[Fuel]],", ",",") -> bioenergy: agricultural waste (solids) | D99: bioenergy: agricultural waste (solids) | G99: 30 | H99: construction | I99: 2024 | J99: N/A | K99: 33.6814 | L99: 117.2694 | M99: china | N99: =Table1[[#This Row],[Capacity (MW)]]*8760*0.72*10^-6 -> 0.189216 | O99: {=AVERAGE(VLOOKUP(_xlfn.TEXTSPLIT(Table1[[#This Row],[Fuel (no space after comma)]], ","), FuelList_Final_EF!$A$2:$B$32, 2, FALSE))} -> 118.17 | P99: =(16112*Table1[[#This Row],[Generation (TWh)]]*10^9)/10^6 -> 3048648.2 | Q99: =Table1[[#This Row],[Emission Factor (kg CO2/ mmBtu)]]*Table1[[#This Row],[Fuel Consumption (mmBtu)]]*10^3 -> 3.6025876e+11 | R99: =(Table1[[#This Row],[CO2 Emissions (g CO2)]])/(Table1[[#This Row],[Generation (TWh)]]*10^9) -> 1903.955
A100: everbright green bioenergy (anhui) holdings co ltd | B100: bioenergy: agricultural waste (solids), bioenergy: wood & other biomass (solids) | C100: =SUBSTITUTE(Table1[[#This Row],[Fuel]],", ",",") -> bioenergy: agricultural waste (solids),bioenergy: wood & other biomass (solids) | D100: bioenergy: agricultural waste (solids) | E100: bioenergy: wood & other biomass (solids) | G100: 30 | H100: operating | I100: 2020 | J100: N/A | K100: 33.5705 | L100: 117.0746 | M100: china | N100: =Table1[[#This Row],[Capacity (MW)]]*8760*0.72*10^-6 -> 0.189216 | O100: {=AVERAGE(VLOOKUP(_xlfn.TEXTSPLIT(Table1[[#This Row],[Fuel (no space after comma)]], ","), FuelList_Final_EF!$A$2:$B$32, 2, FALSE))} -> 105.985 | P100: =(16112*Table1[[#This Row],[Generation (TWh)]]*10^9)/10^6 -> 3048648.2 | Q100: =Table1[[#This Row],[Emission Factor (kg CO2/ mmBtu)]]*Table1[[#This Row],[Fuel Consumption (mmBtu)]]*10^3 -> 3.2311098e+11 | R100: =(Table1[[#This Row],[CO2 Emissions (g CO2)]])/(Table1[[#This Row],[Generation (TWh)]]*10^9) -> 1707.6303
...

Sheet FuelList_Final_EF
A1: Fuel | B1: Emission Factor (kg CO2/ mmBtu) | C1: Source | D1: Comment
A2: {=_xlfn.UNIQUE(FuelList_IntermediateStep!A2:A58)} -> bioenergy: refuse (municipal and industrial wastes) | B2: =100000/948.5 -> 105.42963 | C2: https://www.ipcc-nggip.iges.or.jp/public/2006gl/pdf/2_Volume2/V2_2_Ch2_Stationary_Combustion.pdf | D2: Municipal wastes biomass-fraction
A3: bioenergy: wood & other biomass (solids) | B3: 93.8 | C3: https://www.epa.gov/system/files/documents/2025-01/ghg-emission-factors-hub-2025.pdf
A4: bioenergy: biodiesel | B4: 73.84 | C4: https://www.epa.gov/system/files/documents/2025-01/ghg-emission-factors-hub-2025.pdf
A5: bioenergy: agricultural waste (biogas) | B5: 52.07 | C5: https://www.epa.gov/system/files/documents/2025-01/ghg-emission-factors-hub-2025.pdf
A6: bioenergy: agricultural waste (solids) | B6: 118.17 | C6: https://www.epa.gov/system/files/documents/2025-01/ghg-emission-factors-hub-2025.pdf
A7: bioenergy: paper mill wastes | B7: =95300/948.5 -> 100.47443 | C7: https://www.ipcc-nggip.iges.or.jp/public/2006gl/pdf/2_Volume2/V2_2_Ch2_Stationary_Combustion.pdf
A8: bioenergy: agricultural waste (unknown) | B8: =AVERAGE(B5,B6,B13) -> 72.350251 | C8: Average of "bioenergy: agricultural waste"
A9: bioenergy: unknown | B9: =AVERAGE(B2,B3,B4,B5,B6,B7,B10,B11,B12,B13,B14,B15,B17) -> 72.785606 | C9: Average of "bioenergy:"
A10: bioenergy: refuse (syngas) | B10: =44400/948.5 -> 46.810754 | C10: https://www.ipcc-nggip.iges.or.jp/public/2006gl/pdf/2_Volume2/V2_2_Ch2_Stationary_Combustion.pdf | D10: Gas works gas
A11: bioenergy: refuse (landfill gas) | B11: 52.07 | C11: https://www.epa.gov/system/files/documents/2025-01/ghg-emission-factors-hub-2025.pdf
A12: bioenergy: wastewater and sewage sludge (solids or biogas) | B12: =54600/948.5 -> 57.564576 | C12: https://www.ipcc-nggip.iges.or.jp/public/2006gl/pdf/2_Volume2/V2_2_Ch2_Stationary_Combustion.pdf | D12: Sewage gas
A13: bioenergy: agricultural waste (syngas) | B13: =44400/948.5 -> 46.810754 | C13: https://www.ipcc-nggip.iges.or.jp/public/2006gl/pdf/2_Volume2/V2_2_Ch2_Stationary_Combustion.pdf | D13: Gas works gas
A14: bioenergy: wood & other biomass (biocoal) | B14: =79600/948.5 -> 83.921982 | C14: https://www.ipcc-nggip.iges.or.jp/public/2006gl/pdf/2_Volume2/V2_2_Ch2_Stationary_Combustion.pdf | D14: Other liquid biofuels
A15: bioenergy: ethanol | B15: 68.44 | C15: https://www.epa.gov/system/files/documents/2025-01/ghg-emission-factors-hub-2025.pdf
A16: 0
A17: bioenergy: wood & other biomass (syngas) | B17: =44400/948.5 -> 46.810754 | C17: https://www.ipcc-nggip.iges.or.jp/public/2006gl/pdf/2_Volume2/V2_2_Ch2_Stationary_Combustion.pdf | D17: Gas works gas
A18: fossil liquids: waste/other oil | B18: =73300/948.5 -> 77.279916 | C18: https://www.ipcc-nggip.iges.or.jp/public/2006gl/pdf/2_Volume2/V2_2_Ch2_Stationary_Combustion.pdf
A19: coal: unknown | B19: =AVERAGE(B21,B23,B28,B29) -> 101.10701 | C19: Average of "coal:"
A20: fossil gas: natural gas | B20: 53.06 | C20: https://www.epa.gov/system/files/documents/2025-01/ghg-emission-factors-hub-2025.pdf
A21: coal: bituminous | B21: =94600/948.5 -> 99.736426 | C21: https://www.ipcc-nggip.iges.or.jp/public/2006gl/pdf/2_Volume2/V2_2_Ch2_Stationary_Combustion.pdf
A22: fossil liquids: heavy fuel oil | B22: =77400/948.5 -> 81.60253 | C22: https://www.sciencedirect.com/topics/engineering/specific-emission-factor
A23: coal: subbituminous | B23: =96100/948.5 -> 101.31787 | C23: https://www.ipcc-nggip.iges.or.jp/public/2006gl/pdf/2_Volume2/V2_2_Ch2_Stationary_Combustion.pdf
A24: other: other | B24: =AVERAGE(B32) -> 85.97 | C24: Average of "other:"
A25: fossil liquids: petroleum coke | B25: 102.41 | C25: https://www.epa.gov/system/files/documents/2025-01/ghg-emission-factors-hub-2025.pdf
A26: fossil liquids: unknown | B26: =AVERAGE(B18,B22,B25,B27) -> 84.849782 | C26: Average of "fossil liquids:"
A27: fossil liquids: fuel oil | B27: =0.2665/0.003412 -> 78.106682 | C27: https://www.volker-quaschning.de/datserv/CO2-spez/index_e.php
A28: coal: anthracite | B28: =98300/948.5 -> 103.63732 | C28: https://www.ipcc-nggip.iges.or.jp/public/2006gl/pdf/2_Volume2/V2_2_Ch2_Stationary_Combustion.pdf
A29: coal: waste coal | B29: =94600/948.5 -> 99.736426 | C29: https://www.ipcc-nggip.iges.or.jp/public/2006gl/pdf/2_Volume2/V2_2_Ch2_Stationary_Combustion.pdf
A30: fossil gas: unknown | B30: =AVERAGE(B20,B31) -> 60.37291 | C30: Average of "fossil gas:"
A31: fossil gas: lng | B31: =64200/948.5 -> 67.68582 | C31: https://www.ipcc-nggip.iges.or.jp/public/2006gl/pdf/2_Volume2/V2_2_Ch2_Stationary_Combustion.pdf
A32: other: tires | B32: 85.97 | C32: https://www.ipcc-nggip.iges.or.jp/public/2006gl/pdf/2_Volume2/V2_2_Ch2_Stationary_Combustion.pdf

Sheet FuelList_IntermediateStep
A1: Fuel: Intermediate Step
A2: {=_xlfn.UNIQUE(Bioenergy_Data!D2:D2837)} -> bioenergy: refuse (municipal and industrial wastes)
A3: bioenergy: wood & other biomass (solids)
A4: bioenergy: biodiesel
A5: bioenergy: agricultural waste (biogas)
A6: bioenergy: agricultural waste (solids)
A7: bioenergy: paper mill wastes
A8: bioenergy: agricultural waste (unknown)
A9: bioenergy: unknown
A10: bioenergy: refuse (syngas)
A11: bioenergy: refuse (landfill gas)
A12: bioenergy: wastewater and sewage sludge (solids or biogas)
A13: bioenergy: agricultural waste (syngas)
A14: bioenergy: wood & other biomass (biocoal)
A15: bioenergy: ethanol
A16: {=_xlfn.UNIQUE(Bioenergy_Data!E2:E2837)} -> 0
A17: bioenergy: wood & other biomass (syngas)
A18: fossil liquids: waste/other oil
A19: bioenergy: wastewater and sewage sludge (solids or biogas)
A20: bioenergy: wood & other biomass (solids)
A21: coal: unknown
A22: fossil gas: natural gas
A23: coal: bituminous
A24: fossil liquids: heavy fuel oil
A25: coal: subbituminous
A26: bioenergy: refuse (municipal and industrial wastes)
A27: bioenergy: agricultural waste (solids)
A28: other: other
... A38: bioenergy: refuse (landfill gas)
A39: {=_xlfn.UNIQUE(Bioenergy_Data!F2:F2837)} -> 0
A40: bioenergy: wastewater and sewage sludge (solids or biogas)
A41: fossil gas: natural gas
A42: fossil liquids: heavy fuel oil
A43: coal: unknown
A44: fossil liquids: unknown
A45: fossil gas: unknown
A46: coal: bituminous
A47: other: other
A48: fossil liquids: waste/other oil
A49: bioenergy: wood & other biomass (solids)
A50: fossil liquids: fuel oil
A51: bioenergy: agricultural waste (solids)
... A58: bioenergy: refuse (municipal and industrial wastes)
