Workbook

Sheet Gas_Oil_Data
A1: Owner | B1: Fuel | C1: Fuel (no space after comma) | D1: Fuel 1 | E1: Fuel 2 | F1: Fuel 3 | G1: Fuel 4 | H1: Turbine/Engine Technology | I1: Capacity (MW) | J1: Status | K1: Start Year | L1: Retired Year | M1: Planned retire | N1: Latitude | O1: Longitude | P1: Country/Area | Q1: Generation (TWh) | R1: Emission Factor (kg CO2/ mmBtu) | S1: Fuel Consumption (mmBtu) | T1: Emissions (g CO2) | U1: Carbon Intensity (g CO2/ kWh)
A2: bayat power electricity services distributor co | B2: fossil gas: natural gas | C2: =SUBSTITUTE(Table1[[#This Row],[Fuel]],", ",",") -> fossil gas: natural gas | D2: fossil gas: natural gas | H2: gas turbine | I2: 80 | J2: shelved - inferred 2 y | K2: N/A | L2: N/A | M2: N/A | N2: 36.692494 | O2: 65.985089 | P2: afghanistan | Q2: =Table1[[#This Row],[Capacity (MW)]]*0.395*8760*10^-6 -> 0.276816 | R2: {=AVERAGE(VLOOKUP(_xlfn.TEXTSPLIT(Table1[[#This Row],[Fuel (no space after comma)]], ","), FuelList_Final_EF!$A$2:$B$65, 2, FALSE))} -> 53.06 | S2: =Table1[[#This Row],[Generation (TWh)]]*10^9*VLOOKUP(Table1[[#This Row],[Turbine/Engine Technology]],Technology_HR!$A$2:$B$11,2,FALSE)*10^-6 -> 3047744.2 | T2: =Table1[[#This Row],[Fuel Consumption (mmBtu)]]*Table1[[#This Row],[Emission Factor (kg CO2/ mmBtu)]]*10^3 -> 1.6171331e+11 | U2: =Table1[[#This Row],[Emissions (g CO2)]]/(Table1[[#This Row],[Generation (TWh)]]*10^9) -> 584.1906
A3: bayat power electricity services distributor co | B3: fossil gas: natural gas | C3: =SUBSTITUTE(Table1[[#This Row],[Fuel]],", ",",") -> fossil gas: natural gas | D3: fossil gas: natural gas | H3: gas turbine | I3: 80 | J3: shelved - inferred 2 y | K3: N/A | L3: N/A | M3: N/A | N3: 36.692494 | O3: 65.985089 | P3: afghanistan | Q3: =Table1[[#This Row],[Capacity (MW)]]*0.395*8760*10^-6 -> 0.276816 | R3: {=AVERAGE(VLOOKUP(_xlfn.TEXTSPLIT(Table1[[#This Row],[Fuel (no space after comma)]], ","), FuelList_Final_EF!$A$2:$B$65, 2, FALSE))} -> 53.06 | S3: =Table1[[#This Row],[Generation (TWh)]]*10^9*VLOOKUP(Table1[[#This Row],[Turbine/Engine Technology]],Technology_HR!$A$2:$B$11,2,FALSE)*10^-6 -> 3047744.2 | T3: =Table1[[#This Row],[Fuel Consumption (mmBtu)]]*Table1[[#This Row],[Emission Factor (kg CO2/ mmBtu)]]*10^3 -> 1.6171331e+11 | U3: =Table1[[#This Row],[Emissions (g CO2)]]/(Table1[[#This Row],[Generation (TWh)]]*10^9) -> 584.1906
A4: ghazanfar group llc | B4: fossil gas: natural gas | C4: =SUBSTITUTE(Table1[[#This Row],[Fuel]],", ",",") -> fossil gas: natural gas | D4: fossil gas: natural gas | H4: internal combustion | I4: 59 | J4: shelved | K4: N/A | L4: N/A | M4: N/A | N4: 36.7032 | O4: 67.13556 | P4: afghanistan | Q4: =Table1[[#This Row],[Capacity (MW)]]*0.395*8760*10^-6 -> 0.2041518 | R4: {=AVERAGE(VLOOKUP(_xlfn.TEXTSPLIT(Table1[[#This Row],[Fuel (no space after comma)]], ","), FuelList_Final_EF!$A$2:$B$65, 2, FALSE))} -> 53.06 | S4: =Table1[[#This Row],[Generation (TWh)]]*10^9*VLOOKUP(Table1[[#This Row],[Turbine/Engine Technology]],Technology_HR!$A$2:$B$11,2,FALSE)*10^-6 -> 1816951 | T4: =Table1[[#This Row],[Fuel Consumption (mmBtu)]]*Table1[[#This Row],[Emission Factor (kg CO2/ mmBtu)]]*10^3 -> 9.6407421e+10 | U4: =Table1[[#This Row],[Emissions (g CO2)]]/(Table1[[#This Row],[Generation (TWh)]]*10^9) -> 472.234
A5: united states agency for international development | B5: fossil gas: natural gas, fossil liquids: diesel | C5: =SUBSTITUTE(Table1[[#This Row],[Fuel]],", ",",") -> fossil gas: natural gas,fossil liquids: diesel | D5: fossil gas: natural gas | E5: fossil liquids: diesel | H5: internal combustion | I5: 105 | J5: operating | K5: 2009 | L5: N/A | M5: N/A | N5: 34.561557 | O5: 69.294854 | P5: afghanistan | Q5: =Table1[[#This Row],[Capacity (MW)]]*0.395*8760*10^-6 -> 0.363321 | R5: {=AVERAGE(VLOOKUP(_xlfn.TEXTSPLIT(Table1[[#This Row],[Fuel (no space after comma)]], ","), FuelList_Final_EF!$A$2:$B$65, 2, FALSE))} -> 65.583341 | S5: =Table1[[#This Row],[Generation (TWh)]]*10^9*VLOOKUP(Table1[[#This Row],[Turbine/Engine Technology]],Technology_HR!$A$2:$B$11,2,FALSE)*10^-6 -> 3233556.9 | T5: =Table1[[#This Row],[Fuel Consumption (mmBtu)]]*Table1[[#This Row],[Emission Factor (kg CO2/ mmBtu)]]*10^3 -> 2.1206747e+11 | U5: =Table1[[#This Row],[Emissions (g CO2)]]/(Table1[[#This Row],[Generation (TWh)]]*10^9) -> 583.69174
A6: fier thermoelectric | B6: fossil gas: natural gas | C6: =SUBSTITUTE(Table1[[#This Row],[Fuel]],", ",",") -> fossil gas: natural gas | D6: fossil gas: natural gas | H6: combined cycle | I6: 170 | J6: pre-construction | K6: N/A | L6: N/A | M6: N/A | N6: 40.737819 | O6: 19.703411 | P6: albania | Q6: =Table1[[#This Row],[Capacity (MW)]]*0.395*8760*10^-6 -> 0.588234 | R6: {=AVERAGE(VLOOKUP(_xlfn.TEXTSPLIT(Table1[[#This Row],[Fuel (no space after comma)]], ","), FuelList_Final_EF!$A$2:$B$65, 2, FALSE))} -> 53.06 | S6: =Table1[[#This Row],[Generation (TWh)]]*10^9*VLOOKUP(Table1[[#This Row],[Turbine/Engine Technology]],Technology_HR!$A$2:$B$11,2,FALSE)*10^-6 -> 4440578.5 | T6: =Table1[[#This Row],[Fuel Consumption (mmBtu)]]*Table1[[#This Row],[Emission Factor (kg CO2/ mmBtu)]]*10^3 -> 2.3561709e+11 | U6: =Table1[[#This Row],[Emissions (g CO2)]]/(Table1[[#This Row],[Generation (TWh)]]*10^9) -> 400.54994
A7: excelerate energy lp | B7: fossil liquids: heavy fuel oil | C7: =SUBSTITUTE(Table1[[#This Row],[Fuel]],", ",",") -> fossil liquids: heavy fuel oil | D7: fossil liquids: heavy fuel oil | H7: internal combustion | I7: 52.2 | J7: mothballed | K7: 2023 | L7: N/A | M7: N/A | N7: 40.473319 | O7: 19.445376 | P7: albania | Q7: =Table1[[#This Row],[Capacity (MW)]]*0.395*8760*10^-6 -> 0.18062244 | R7: {=AVERAGE(VLOOKUP(_xlfn.TEXTSPLIT(Table1[[#This Row],[Fuel (no space after comma)]], ","), FuelList_Final_EF!$A$2:$B$65, 2, FALSE))} -> 81.60253 | S7: =Table1[[#This Row],[Generation (TWh)]]*10^9*VLOOKUP(Table1[[#This Row],[Turbine/Engine Technology]],Technology_HR!$A$2:$B$11,2,FALSE)*10^-6 -> 1607539.7 | T7: =Table1[[#This Row],[Fuel Consumption (mmBtu)]]*Table1[[#This Row],[Emission Factor (kg CO2/ mmBtu)]]*10^3 -> 1.3117931e+11 | U7: =Table1[[#This Row],[Emissions (g CO2)]]/(Table1[[#This Row],[Generation (TWh)]]*10^9) -> 726.26252
A8: excelerate energy lp | B8: fossil liquids: heavy fuel oil | C8: =SUBSTITUTE(Table1[[#This Row],[Fuel]],", ",",") -> fossil liquids: heavy fuel oil | D8: fossil liquids: heavy fuel oil | H8: internal combustion | I8: 58 | J8: mothballed | K8: 2023 | L8: N/A | M8: N/A | N8: 40.473319 | O8: 19.445376 | P8: albania | Q8: =Table1[[#This Row],[Capacity (MW)]]*0.395*8760*10^-6 -> 0.2006916 | R8: {=AVERAGE(VLOOKUP(_xlfn.TEXTSPLIT(Table1[[#This Row],[Fuel (no space after comma)]], ","), FuelList_Final_EF!$A$2:$B$65, 2, FALSE))} -> 81.60253 | S8: =Table1[[#This Row],[Generation (TWh)]]*10^9*VLOOKUP(Table1[[#This Row],[Turbine/Engine Technology]],Technology_HR!$A$2:$B$11,2,FALSE)*10^-6 -> 1786155.2 | T8: =Table1[[#This Row],[Fuel Consumption (mmBtu)]]*Table1[[#This Row],[Emission Factor (kg CO2/ mmBtu)]]*10^3 -> 1.4575479e+11 | U8: =Table1[[#This Row],[Emissions (g CO2)]]/(Table1[[#This Row],[Generation (TWh)]]*10^9) -> 726.26252
A9: korporata elektroenergjitike shqiptare sha | B9: fossil gas: lng | C9: =SUBSTITUTE(Table1[[#This Row],[Fuel]],", ",",") -> fossil gas: lng | D9: fossil gas: lng | H9: unknown | I9: 100 | J9: pre-construction | K9: N/A | L9: N/A | M9: N/A | N9: 40.490183 | O9: 19.435491 | P9: albania | Q9: =Table1[[#This Row],[Capacity (MW)]]*0.395*8760*10^-6 -> 0.34602 | R9: {=AVERAGE(VLOOKUP(_xlfn.TEXTSPLIT(Table1[[#This Row],[Fuel (no space after comma)]], ","), FuelList_Final_EF!$A$2:$B$65, 2, FALSE))} -> 67.68582 | S9: =Table1[[#This Row],[Generation (TWh)]]*10^9*VLOOKUP(Table1[[#This Row],[Turbine/Engine Technology]],Technology_HR!$A$2:$B$11,2,FALSE)*10^-6 -> 2870408.9 | T9: =Table1[[#This Row],[Fuel Consumption (mmBtu)]]*Table1[[#This Row],[Emission Factor (kg CO2/ mmBtu)]]*10^3 -> 1.9428598e+11 | U9: =Table1[[#This Row],[Emissions (g CO2)]]/(Table1[[#This Row],[Generation (TWh)]]*10^9) -> 561.48772
A10: korporata elektroenergjitike shqiptare sha | B10: fossil gas: lng | C10: =SUBSTITUTE(Table1[[#This Row],[Fuel]],", ",",") -> fossil gas: lng | D10: fossil gas: lng | H10: unknown | I10: 150 | J10: pre-construction | K10: N/A | L10: N/A | M10: N/A | N10: 40.490183 | O10: 19.435491 | P10: albania | Q10: =Table1[[#This Row],[Capacity (MW)]]*0.395*8760*10^-6 -> 0.51903 | R10: {=AVERAGE(VLOOKUP(_xlfn.TEXTSPLIT(Table1[[#This Row],[Fuel (no space after comma)]], ","), FuelList_Final_EF!$A$2:$B$65, 2, FALSE))} -> 67.68582 | S10: =Table1[[#This Row],[Generation (TWh)]]*10^9*VLOOKUP(Table1[[#This Row],[Turbine/Engine Technology]],Technology_HR!$A$2:$B$11,2,FALSE)*10^-6 -> 4305613.4 | T10: =Table1[[#This Row],[Fuel Consumption (mmBtu)]]*Table1[[#This Row],[Emission Factor (kg CO2/ mmBtu)]]*10^3 -> 2.9142897e+11 | U10: =Table1[[#This Row],[Emissions (g CO2)]]/(Table1[[#This Row],[Generation (TWh)]]*10^9) -> 561.48772
A11: korporata elektroenergjitike shqiptare sha | B11: fossil gas: lng | C11: =SUBSTITUTE(Table1[[#This Row],[Fuel]],", ",",") -> fossil gas: lng | D11: fossil gas: lng | H11: unknown | I11: 100 | J11: pre-construction | K11: N/A | L11: N/A | M11: N/A | N11: 40.490183 | O11: 19.435491 | P11: albania | Q11: =Table1[[#This Row],[Capacity (MW)]]*0.395*8760*10^-6 -> 0.34602 | R11: {=AVERAGE(VLOOKUP(_xlfn.TEXTSPLIT(Table1[[#This Row],[Fuel (no space after comma)]], ","), FuelList_Final_EF!$A$2:$B$65, 2, FALSE))} -> 67.68582 | S11: =Table1[[#This Row],[Generation (TWh)]]*10^9*VLOOKUP(Table1[[#This Row],[Turbine/Engine Technology]],Technology_HR!$A$2:$B$11,2,FALSE)*10^-6 -> 2870408.9 | T11: =Table1[[#This Row],[Fuel Consumption (mmBtu)]]*Table1[[#This Row],[Emission Factor (kg CO2/ mmBtu)]]*10^3 -> 1.9428598e+11 | U11: =Table1[[#This Row],[Emissions (g CO2)]]/(Table1[[#This Row],[Generation (TWh)]]*10^9) -> 561.48772
A12: société algérienne de production de l'electricité spa | B12: fossil gas: natural gas, fossil liquids: diesel | C12: =SUBSTITUTE(Table1[[#This Row],[Fuel]],", ",",") -> fossil gas: natural gas,fossil liquids: diesel | D12: fossil gas: natural gas | E12: fossil liquids: diesel | H12: combined cycle | I12: 338 | J12: operating | K12: 2019 | L12: N/A | M12: N/A | N12: 36.157607 | O12: 5.206548 | P12: algeria | Q12: =Table1[[#This Row],[Capacity (MW)]]*0.395*8760*10^-6 -> 1.1695476 | R12: {=AVERAGE(VLOOKUP(_xlfn.TEXTSPLIT(Table1[[#This Row],[Fuel (no space after comma)]], ","), FuelList_Final_EF!$A$2:$B$65, 2, FALSE))} -> 65.583341 | S12: =Table1[[#This Row],[Generation (TWh)]]*10^9*VLOOKUP(Table1[[#This Row],[Turbine/Engine Technology]],Technology_HR!$A$2:$B$11,2,FALSE)*10^-6 -> 8828914.8 | T12: =Table1[[#This Row],[Fuel Consumption (mmBtu)]]*Table1[[#This Row],[Emission Factor (kg CO2/ mmBtu)]]*10^3 -> 5.7902973e+11 | U12: =Table1[[#This Row],[Emissions (g CO2)]]/(Table1[[#This Row],[Generation (TWh)]]*10^9) -> 495.08864
A13: société algérienne de production de l'electricité spa | B13: fossil gas: natural gas, fossil liquids: diesel | C13: =SUBSTITUTE(Table1[[#This Row],[Fuel]],", ",",") -> fossil gas: natural gas,fossil liquids: diesel | D13: fossil gas: natural gas | E13: fossil liquids: diesel | H13: combined cycle | I13: 338 | J13: operating | K13: 2019 | L13: N/A | M13: N/A | N13: 36.157607 | O13: 5.206548 | P13: algeria | Q13: =Table1[[#This Row],[Capacity (MW)]]*0.395*8760*10^-6 -> 1.1695476 | R13: {=AVERAGE(VLOOKUP(_xlfn.TEXTSPLIT(Table1[[#This Row],[Fuel (no space after comma)]], ","), FuelList_Final_EF!$A$2:$B$65, 2, FALSE))} -> 65.583341 | S13: =Table1[[#This Row],[Generation (TWh)]]*10^9*VLOOKUP(Table1[[#This Row],[Turbine/Engine Technology]],Technology_HR!$A$2:$B$11,2,FALSE)*10^-6 -> 8828914.8 | T13: =Table1[[#This Row],[Fuel Consumption (mmBtu)]]*Table1[[#This Row],[Emission Factor (kg CO2/ mmBtu)]]*10^3 -> 5.7902973e+11 | U13: =Table1[[#This Row],[Emissions (g CO2)]]/(Table1[[#This Row],[Generation (TWh)]]*10^9) -> 495.08864
A14: société algérienne de production de l'electricité spa | B14: fossil gas: natural gas, fossil liquids: diesel | C14: =SUBSTITUTE(Table1[[#This Row],[Fuel]],", ",",") -> fossil gas: natural gas,fossil liquids: diesel | D14: fossil gas: natural gas | E14: fossil liquids: diesel | H14: combined cycle | I14: 338 | J14: operating | K14: 2019 | L14: N/A | M14: N/A | N14: 36.157607 | O14: 5.206548 | P14: algeria | Q14: =Table1[[#This Row],[Capacity (MW)]]*0.395*8760*10^-6 -> 1.1695476 | R14: {=AVERAGE(VLOOKUP(_xlfn.TEXTSPLIT(Table1[[#This Row],[Fuel (no space after comma)]], ","), FuelList_Final_EF!$A$2:$B$65, 2, FALSE))} -> 65.583341 | S14: =Table1[[#This Row],[Generation (TWh)]]*10^9*VLOOKUP(Table1[[#This Row],[Turbine/Engine Technology]],Technology_HR!$A$2:$B$11,2,FALSE)*10^-6 -> 8828914.8 | T14: =Table1[[#This Row],[Fuel Consumption (mmBtu)]]*Table1[[#This Row],[Emission Factor (kg CO2/ mmBtu)]]*10^3 -> 5.7902973e+11 | U14: =Table1[[#This Row],[Emissions (g CO2)]]/(Table1[[#This Row],[Generation (TWh)]]*10^9) -> 495.08864
A15: société algérienne de production de l'electricité spa | B15: fossil gas: natural gas, fossil liquids: fuel oil | C15: =SUBSTITUTE(Table1[[#This Row],[Fuel]],", ",",") -> fossil gas: natural gas,fossil liquids: fuel oil | D15: fossil gas: natural gas | E15: fossil liquids: fuel oil | H15: gas turbine | I15: 126 | J15: operating | K15: 2010 | L15: N/A | M15: N/A | N15: 35.8678 | O15: 6.025637 | P15: algeria | Q15: =Table1[[#This Row],[Capacity (MW)]]*0.395*8760*10^-6 -> 0.4359852 | R15: {=AVERAGE(VLOOKUP(_xlfn.TEXTSPLIT(Table1[[#This Row],[Fuel (no space after comma)]], ","), FuelList_Final_EF!$A$2:$B$65, 2, FALSE))} -> 65.583341 | S15: =Table1[[#This Row],[Generation (TWh)]]*10^9*VLOOKUP(Table1[[#This Row],[Turbine/Engine Technology]],Technology_HR!$A$2:$B$11,2,FALSE)*10^-6 -> 4800197.1 | T15: =Table1[[#This Row],[Fuel Consumption (mmBtu)]]*Table1[[#This Row],[Emission Factor (kg CO2/ mmBtu)]]*10^3 -> 3.1481296e+11 | U15: =Table1[[#This Row],[Emissions (g CO2)]]/(Table1[[#This Row],[Generation (TWh)]]*10^9) -> 722.07259
A16: société algérienne de production de l'electricité spa | B16: fossil gas: natural gas, fossil liquids: fuel oil | C16: =SUBSTITUTE(Table1[[#This Row],[Fuel]],", ",",") -> fossil gas: natural gas,fossil liquids: fuel oil | D16: fossil gas: natural gas | E16: fossil liquids: fuel oil | H16: gas turbine | I16: 126 | J16: operating | K16: 2010 | L16: N/A | M16: N/A | N16: 35.8678 | O16: 6.025637 | P16: algeria | Q16: =Table1[[#This Row],[Capacity (MW)]]*0.395*8760*10^-6 -> 0.4359852 | R16: {=AVERAGE(VLOOKUP(_xlfn.TEXTSPLIT(Table1[[#This Row],[Fuel (no space after comma)]], ","), FuelList_Final_EF!$A$2:$B$65, 2, FALSE))} -> 65.583341 | S16: =Table1[[#This Row],[Generation (TWh)]]*10^9*VLOOKUP(Table1[[#This Row],[Turbine/Engine Technology]],Technology_HR!$A$2:$B$11,2,FALSE)*10^-6 -> 4800197.1 | T16: =Table1[[#This Row],[Fuel Consumption (mmBtu)]]*Table1[[#This Row],[Emission Factor (kg CO2/ mmBtu)]]*10^3 -> 3.1481296e+11 | U16: =Table1[[#This Row],[Emissions (g CO2)]]/(Table1[[#This Row],[Generation (TWh)]]*10^9) -> 722.07259
A17: société algérienne de production de l'electricité spa | B17: fossil gas: natural gas, fossil liquids: fuel oil | C17: =SUBSTITUTE(Table1[[#This Row],[Fuel]],", ",",") -> fossil gas: natural gas,fossil liquids: fuel oil | D17: fossil gas: natural gas | E17: fossil liquids: fuel oil | H17: gas turbine | I17: 132 | J17: operating | K17: 2014 | L17: N/A | M17: N/A | N17: 35.8678 | O17: 6.025637 | P17: algeria | Q17: =Table1[[#This Row],[Capacity (MW)]]*0.395*8760*10^-6 -> 0.4567464 | R17: {=AVERAGE(VLOOKUP(_xlfn.TEXTSPLIT(Table1[[#This Row],[Fuel (no space after comma)]], ","), FuelList_Final_EF!$A$2:$B$65, 2, FALSE))} -> 65.583341 | S17: =Table1[[#This Row],[Generation (TWh)]]*10^9*VLOOKUP(Table1[[#This Row],[Turbine/Engine Technology]],Technology_HR!$A$2:$B$11,2,FALSE)*10^-6 -> 5028777.9 | T17: =Table1[[#This Row],[Fuel Consumption (mmBtu)]]*Table1[[#This Row],[Emission Factor (kg CO2/ mmBtu)]]*10^3 -> 3.2980405e+11 | U17: =Table1[[#This Row],[Emissions (g CO2)]]/(Table1[[#This Row],[Generation (TWh)]]*10^9) -> 722.07259
A18: société algérienne de production de l'electricité spa | B18: fossil gas: natural gas, fossil liquids: fuel oil | C18: =SUBSTITUTE(Table1[[#This Row],[Fuel]],", ",",") -> fossil gas: natural gas,fossil liquids: fuel oil | D18: fossil gas: natural gas | E18: fossil liquids: fuel oil | H18: gas turbine | I18: 132 | J18: operating | K18: 2014 | L18: N/A | M18: N/A | N18: 35.8678 | O18: 6.025637 | P18: algeria | Q18: =Table1[[#This Row],[Capacity (MW)]]*0.395*8760*10^-6 -> 0.4567464 | R18: {=AVERAGE(VLOOKUP(_xlfn.TEXTSPLIT(Table1[[#This Row],[Fuel (no space after comma)]], ","), FuelList_Final_EF!$A$2:$B$65, 2, FALSE))} -> 65.583341 | S18: =Table1[[#This Row],[Generation (TWh)]]*10^9*VLOOKUP(Table1[[#This Row],[Turbine/Engine Technology]],Technology_HR!$A$2:$B$11,2,FALSE)*10^-6 -> 5028777.9 | T18: =Table1[[#This Row],[Fuel Consumption (mmBtu)]]*Table1[[#This Row],[Emission Factor (kg CO2/ mmBtu)]]*10^3 -> 3.2980405e+11 | U18: =Table1[[#This Row],[Emissions (g CO2)]]/(Table1[[#This Row],[Generation (TWh)]]*10^9) -> 722.07259
A19: société algérienne de production de l'electricité spa | B19: fossil gas: natural gas, fossil liquids: fuel oil | C19: =SUBSTITUTE(Table1[[#This Row],[Fuel]],", ",",") -> fossil gas: natural gas,fossil liquids: fuel oil | D19: fossil gas: natural gas | E19: fossil liquids: fuel oil | H19: gas turbine | I19: 138.8 | J19: operating | K19: 2019 | L19: N/A | M19: N/A | N19: 35.8678 | O19: 6.025637 | P19: algeria | Q19: =Table1[[#This Row],[Capacity (MW)]]*0.395*8760*10^-6 -> 0.48027576 | R19: {=AVERAGE(VLOOKUP(_xlfn.TEXTSPLIT(Table1[[#This Row],[Fuel (no space after comma)]], ","), FuelList_Final_EF!$A$2:$B$65, 2, FALSE))} -> 65.583341 | S19: =Table1[[#This Row],[Generation (TWh)]]*10^9*VLOOKUP(Table1[[#This Row],[Turbine/Engine Technology]],Technology_HR!$A$2:$B$11,2,FALSE)*10^-6 -> 5287836.1 | T19: =Table1[[#This Row],[Fuel Consumption (mmBtu)]]*Table1[[#This Row],[Emission Factor (kg CO2/ mmBtu)]]*10^3 -> 3.4679396e+11 | U19: =Table1[[#This Row],[Emissions (g CO2)]]/(Table1[[#This Row],[Generation (TWh)]]*10^9) -> 722.07259
A20: société algérienne de production de l'electricité spa | B20: fossil gas: natural gas, fossil liquids: fuel oil | C20: =SUBSTITUTE(Table1[[#This Row],[Fuel]],", ",",") -> fossil gas: natural gas,fossil liquids: fuel oil | D20: fossil gas: natural gas | E20: fossil liquids: fuel oil | H20: gas turbine | I20: 138.8 | J20: operating | K20: 2019 | L20: N/A | M20: N/A | N20: 35.8678 | O20: 6.025637 | P20: algeria | Q20: =Table1[[#This Row],[Capacity (MW)]]*0.395*8760*10^-6 -> 0.48027576 | R20: {=AVERAGE(VLOOKUP(_xlfn.TEXTSPLIT(Table1[[#This Row],[Fuel (no space after comma)]], ","), FuelList_Final_EF!$A$2:$B$65, 2, FALSE))} -> 65.583341 | S20: =Table1[[#This Row],[Generation (TWh)]]*10^9*VLOOKUP(Table1[[#This Row],[Turbine/Engine Technology]],Technology_HR!$A$2:$B$11,2,FALSE)*10^-6 -> 5287836.1 | T20: =Table1[[#This Row],[Fuel Consumption (mmBtu)]]*Table1[[#This Row],[Emission Factor (kg CO2/ mmBtu)]]*10^3 -> 3.4679396e+11 | U20: =Table1[[#This Row],[Emissions (g CO2)]]/(Table1[[#This Row],[Generation (TWh)]]*10^9) -> 722.07259
A21: société algérienne de production de l'electricité spa | B21: fossil gas: natural gas | C21: =SUBSTITUTE(Table1[[#This Row],[Fuel]],", ",",") -> fossil gas: natural gas | D21: fossil gas: natural gas | H21: combined cycle | I21: 699 | J21: operating | K21: 2022 | L21: N/A | M21: N/A | N21: 36.739578 | O21: 6.251014 | P21: algeria | Q21: =Table1[[#This Row],[Capacity (MW)]]*0.395*8760*10^-6 -> 2.4186798 | R21: {=AVERAGE(VLOOKUP(_xlfn.TEXTSPLIT(Table1[[#This Row],[Fuel (no space after comma)]], ","), FuelList_Final_EF!$A$2:$B$65, 2, FALSE))} -> 53.06 | S21: =Table1[[#This Row],[Generation (TWh)]]*10^9*VLOOKUP(Table1[[#This Row],[Turbine/Engine Technology]],Technology_HR!$A$2:$B$11,2,FALSE)*10^-6 -> 18258614 | T21: =Table1[[#This Row],[Fuel Consumption (mmBtu)]]*Table1[[#This Row],[Emission Factor (kg CO2/ mmBtu)]]*10^3 -> 9.6880205e+11 | U21: =Table1[[#This Row],[Emissions (g CO2)]]/(Table1[[#This Row],[Generation (TWh)]]*10^9) -> 400.54994
A22: société algérienne de production de l'electricité spa | B22: fossil gas: natural gas | C22: =SUBSTITUTE(Table1[[#This Row],[Fuel]],", ",",") -> fossil gas: natural gas | D22: fossil gas: natural gas | H22: combined cycle | I22: 699 | J22: operating | K22: 2022 | L22: N/A | M22: N/A | N22: 36.739578 | O22: 6.251014 | P22: algeria | Q22: =Table1[[#This Row],[Capacity (MW)]]*0.395*8760*10^-6 -> 2.4186798 | R22: {=AVERAGE(VLOOKUP(_xlfn.TEXTSPLIT(Table1[[#This Row],[Fuel (no space after comma)]], ","), FuelList_Final_EF!$A$2:$B$65, 2, FALSE))} -> 53.06 | S22: =Table1[[#This Row],[Generation (TWh)]]*10^9*VLOOKUP(Table1[[#This Row],[Turbine/Engine Technology]],Technology_HR!$A$2:$B$11,2,FALSE)*10^-6 -> 18258614 | T22: =Table1[[#This Row],[Fuel Consumption (mmBtu)]]*Table1[[#This Row],[Emission Factor (kg CO2/ mmBtu)]]*10^3 -> 9.6880205e+11 | U22: =Table1[[#This Row],[Emissions (g CO2)]]/(Table1[[#This Row],[Generation (TWh)]]*10^9) -> 400.54994
A23: shariket kahraba berrouaghia spa | B23: fossil gas: natural gas, fossil liquids: fuel oil | C23: =SUBSTITUTE(Table1[[#This Row],[Fuel]],", ",",") -> fossil gas: natural gas,fossil liquids: fuel oil | D23: fossil gas: natural gas | E23: fossil liquids: fuel oil | H23: gas turbine | I23: 244.5 | J23: operating | K23: 2007 | L23: N/A | M23: N/A | N23: 36.140101 | O23: 2.93022 | P23: algeria | Q23: =Table1[[#This Row],[Capacity (MW)]]*0.395*8760*10^-6 -> 0.8460189 | R23: {=AVERAGE(VLOOKUP(_xlfn.TEXTSPLIT(Table1[[#This Row],[Fuel (no space after comma)]], ","), FuelList_Final_EF!$A$2:$B$65, 2, FALSE))} -> 65.583341 | S23: =Table1[[#This Row],[Generation (TWh)]]*10^9*VLOOKUP(Table1[[#This Row],[Turbine/Engine Technology]],Technology_HR!$A$2:$B$11,2,FALSE)*10^-6 -> 9314668.1 | T23: =Table1[[#This Row],[Fuel Consumption (mmBtu)]]*Table1[[#This Row],[Emission Factor (kg CO2/ mmBtu)]]*10^3 -> 6.1088705e+11 | U23: =Table1[[#This Row],[Emissions (g CO2)]]/(Table1[[#This Row],[Generation (TWh)]]*10^9) -> 722.07259
A24: shariket kahraba berrouaghia spa | B24: fossil gas: natural gas, fossil liquids: fuel oil | C24: =SUBSTITUTE(Table1[[#This Row],[Fuel]],", ",",") -> fossil gas: natural gas,fossil liquids: fuel oil | D24: fossil gas: natural gas | E24: fossil liquids: fuel oil | H24: gas turbine | I24: 244.5 | J24: operating | K24: 2007 | L24: N/A | M24: N/A | N24: 36.140101 | O24: 2.93022 | P24: algeria | Q24: =Table1[[#This Row],[Capacity (MW)]]*0.395*8760*10^-6 -> 0.8460189 | R24: {=AVERAGE(VLOOKUP(_xlfn.TEXTSPLIT(Table1[[#This Row],[Fuel (no space after comma)]], ","), FuelList_Final_EF!$A$2:$B$65, 2, FALSE))} -> 65.583341 | S24: =Table1[[#This Row],[Generation (TWh)]]*10^9*VLOOKUP(Table1[[#This Row],[Turbine/Engine Technology]],Technology_HR!$A$2:$B$11,2,FALSE)*10^-6 -> 9314668.1 | T24: =Table1[[#This Row],[Fuel Consumption (mmBtu)]]*Table1[[#This Row],[Emission Factor (kg CO2/ mmBtu)]]*10^3 -> 6.1088705e+11 | U24: =Table1[[#This Row],[Emissions (g CO2)]]/(Table1[[#This Row],[Generation (TWh)]]*10^9) -> 722.07259
A25: société algérienne de production de l'electricité spa | B25: fossil gas: natural gas, fossil liquids: fuel oil | C25: =SUBSTITUTE(Table1[[#This Row],[Fuel]],", ",",") -> fossil gas: natural gas,fossil liquids: fuel oil | D25: fossil gas: natural gas | E25: fossil liquids: fuel oil | H25: gas turbine | I25: 250 | J25: operating | K25: 2016 | L25: N/A | M25: N/A | N25: 36.596922 | O25: 2.878541 | P25: algeria | Q25: =Table1[[#This Row],[Capacity (MW)]]*0.395*8760*10^-6 -> 0.86505 | R25: {=AVERAGE(VLOOKUP(_xlfn.TEXTSPLIT(Table1[[#This Row],[Fuel (no space after comma)]], ","), FuelList_Final_EF!$A$2:$B$65, 2, FALSE))} -> 65.583341 | S25: =Table1[[#This Row],[Generation (TWh)]]*10^9*VLOOKUP(Table1[[#This Row],[Turbine/Engine Technology]],Technology_HR!$A$2:$B$11,2,FALSE)*10^-6 -> 9524200.5 | T25: =Table1[[#This Row],[Fuel Consumption (mmBtu)]]*Table1[[#This Row],[Emission Factor (kg CO2/ mmBtu)]]*10^3 -> 6.2462889e+11 | U25: =Table1[[#This Row],[Emissions (g CO2)]]/(Table1[[#This Row],[Generation (TWh)]]*10^9) -> 722.07259
A26: société algérienne de production de l'electricité spa | B26: fossil gas: natural gas, fossil liquids: fuel oil | C26: =SUBSTITUTE(Table1[[#This Row],[Fuel]],", ",",") -> fossil gas: natural gas,fossil liquids: fuel oil | D26: fossil gas: natural gas | E26: fossil liquids: fuel oil | H26: gas turbine | I26: 250 | J26: operating | K26: 2016 | L26: N/A | M26: N/A | N26: 36.596922 | O26: 2.878541 | P26: algeria | Q26: =Table1[[#This Row],[Capacity (MW)]]*0.395*8760*10^-6 -> 0.86505 | R26: {=AVERAGE(VLOOKUP(_xlfn.TEXTSPLIT(Table1[[#This Row],[Fuel (no space after comma)]], ","), FuelList_Final_EF!$A$2:$B$65, 2, FALSE))} -> 65.583341 | S26: =Table1[[#This Row],[Generation (TWh)]]*10^9*VLOOKUP(Table1[[#This Row],[Turbine/Engine Technology]],Technology_HR!$A$2:$B$11,2,FALSE)*10^-6 -> 9524200.5 | T26: =Table1[[#This Row],[Fuel Consumption (mmBtu)]]*Table1[[#This Row],[Emission Factor (kg CO2/ mmBtu)]]*10^3 -> 6.2462889e+11 | U26: =Table1[[#This Row],[Emissions (g CO2)]]/(Table1[[#This Row],[Generation (TWh)]]*10^9) -> 722.07259
A27: société algérienne de production de l'electricité spa | B27: fossil gas: natural gas, fossil liquids: fuel oil | C27: =SUBSTITUTE(Table1[[#This Row],[Fuel]],", ",",") -> fossil gas: natural gas,fossil liquids: fuel oil | D27: fossil gas: natural gas | E27: fossil liquids: fuel oil | H27: gas turbine | I27: 250 | J27: operating | K27: 2016 | L27: N/A | M27: N/A | N27: 36.596922 | O27: 2.878541 | P27: algeria | Q27: =Table1[[#This Row],[Capacity (MW)]]*0.395*8760*10^-6 -> 0.86505 | R27: {=AVERAGE(VLOOKUP(_xlfn.TEXTSPLIT(Table1[[#This Row],[Fuel (no space after comma)]], ","), FuelList_Final_EF!$A$2:$B$65, 2, FALSE))} -> 65.583341 | S27: =Table1[[#This Row],[Generation (TWh)]]*10^9*VLOOKUP(Table1[[#This Row],[Turbine/Engine Technology]],Technology_HR!$A$2:$B$11,2,FALSE)*10^-6 -> 9524200.5 | T27: =Table1[[#This Row],[Fuel Consumption (mmBtu)]]*Table1[[#This Row],[Emission Factor (kg CO2/ mmBtu)]]*10^3 -> 6.2462889e+11 | U27: =Table1[[#This Row],[Emissions (g CO2)]]/(Table1[[#This Row],[Generation (TWh)]]*10^9) -> 722.07259
A28: société algérienne de production de l'electricité spa | B28: fossil gas: natural gas | C28: =SUBSTITUTE(Table1[[#This Row],[Fuel]],", ",",") -> fossil gas: natural gas | D28: fossil gas: natural gas | H28: gas turbine | I28: 225 | J28: operating | K28: 2019 | L28: N/A | M28: N/A | N28: 35.5658 | O28: -0.9386 | P28: algeria | Q28: =Table1[[#This Row],[Capacity (MW)]]*0.395*8760*10^-6 -> 0.778545 | R28: {=AVERAGE(VLOOKUP(_xlfn.TEXTSPLIT(Table1[[#This Row],[Fuel (no space after comma)]], ","), FuelList_Final_EF!$A$2:$B$65, 2, FALSE))} -> 53.06 | S28: =Table1[[#This Row],[Generation (TWh)]]*10^9*VLOOKUP(Table1[[#This Row],[Turbine/Engine Technology]],Technology_HR!$A$2:$B$11,2,FALSE)*10^-6 -> 8571780.4 | T28: =Table1[[#This Row],[Fuel Consumption (mmBtu)]]*Table1[[#This Row],[Emission Factor (kg CO2/ mmBtu)]]*10^3 -> 454818670677 | U28: =Table1[[#This Row],[Emissions (g CO2)]]/(Table1[[#This Row],[Generation (TWh)]]*10^9) -> 584.1906
A29: société algérienne de production de l'electricité spa | B29: fossil gas: natural gas | C29: =SUBSTITUTE(Table1[[#This Row],[Fuel]],", ",",") -> fossil gas: natural gas | D29: fossil gas: natural gas | H29: gas turbine | I29: 225 | J29: operating | K29: 2020 | L29: N/A | M29: N/A | N29: 35.5658 | O29: -0.9386 | P29: algeria | Q29: =Table1[[#This Row],[Capacity (MW)]]*0.395*8760*10^-6 -> 0.778545 | R29: {=AVERAGE(VLOOKUP(_xlfn.TEXTSPLIT(Table1[[#This Row],[Fuel (no space after comma)]], ","), FuelList_Final_EF!$A$2:$B$65, 2, FALSE))} -> 53.06 | S29: =Table1[[#This Row],[Generation (TWh)]]*10^9*VLOOKUP(Table1[[#This Row],[Turbine/Engine Technology]],Technology_HR!$A$2:$B$11,2,FALSE)*10^-6 -> 8571780.4 | T29: =Table1[[#This Row],[Fuel Consumption (mmBtu)]]*Table1[[#This Row],[Emission Factor (kg CO2/ mmBtu)]]*10^3 -> 454818670677 | U29: =Table1[[#This Row],[Emissions (g CO2)]]/(Table1[[#This Row],[Generation (TWh)]]*10^9) -> 584.1906
A30: société algérienne de production de l'electricité spa | B30: fossil gas: natural gas, fossil liquids: fuel oil | C30: =SUBSTITUTE(Table1[[#This Row],[Fuel]],", ",",") -> fossil gas: natural gas,fossil liquids: fuel oil | D30: fossil gas: natural gas | E30: fossil liquids: fuel oil | H30: combined cycle | I30: 600 | J30: pre-construction | K30: N/A | L30: N/A | M30: N/A | N30: 35.439261 | O30: 2.96076 | P30: algeria | Q30: =Table1[[#This Row],[Capacity (MW)]]*0.395*8760*10^-6 -> 2.07612 | R30: {=AVERAGE(VLOOKUP(_xlfn.TEXTSPLIT(Table1[[#This Row],[Fuel (no space after comma)]], ","), FuelList_Final_EF!$A$2:$B$65, 2, FALSE))} -> 65.583341 | S30: =Table1[[#This Row],[Generation (TWh)]]*10^9*VLOOKUP(Table1[[#This Row],[Turbine/Engine Technology]],Technology_HR!$A$2:$B$11,2,FALSE)*10^-6 -> 15672630 | T30: =Table1[[#This Row],[Fuel Consumption (mmBtu)]]*Table1[[#This Row],[Emission Factor (kg CO2/ mmBtu)]]*10^3 -> 1.0278634e+12 | U30: =Table1[[#This Row],[Emissions (g CO2)]]/(Table1[[#This Row],[Generation (TWh)]]*10^9) -> 495.08864
A31: société algérienne de production de l'electricité spa | B31: fossil gas: natural gas, fossil liquids: fuel oil | C31: =SUBSTITUTE(Table1[[#This Row],[Fuel]],", ",",") -> fossil gas: natural gas,fossil liquids: fuel oil | D31: fossil gas: natural gas | E31: fossil liquids: fuel oil | H31: combined cycle | I31: 600 | J31: pre-construction | K31: N/A | L31: N/A | M31: N/A | N31: 35.439261 | O31: 2.96076 | P31: algeria | Q31: =Table1[[#This Row],[Capacity (MW)]]*0.395*8760*10^-6 -> 2.07612 | R31: {=AVERAGE(VLOOKUP(_xlfn.TEXTSPLIT(Table1[[#This Row],[Fuel (no space after comma)]], ","), FuelList_Final_EF!$A$2:$B$65, 2, FALSE))} -> 65.583341 | S31: =Table1[[#This Row],[Generation (TWh)]]*10^9*VLOOKUP(Table1[[#This Row],[Turbine/Engine Technology]],Technology_HR!$A$2:$B$11,2,FALSE)*10^-6 -> 15672630 | T31: =Table1[[#This Row],[Fuel Consumption (mmBtu)]]*Table1[[#This Row],[Emission Factor (kg CO2/ mmBtu)]]*10^3 -> 1.0278634e+12 | U31: =Table1[[#This Row],[Emissions (g CO2)]]/(Table1[[#This Row],[Generation (TWh)]]*10^9) -> 495.08864
A32: sonelgaz spa | B32: fossil gas: natural gas | C32: =SUBSTITUTE(Table1[[#This Row],[Fuel]],", ",",") -> fossil gas: natural gas | D32: fossil gas: natural gas | H32: gas turbine | I32: 80 | J32: construction | K32: N/A | L32: N/A | M32: N/A | N32: 27.183923 | O32: 2.435821 | P32: algeria | Q32: =Table1[[#This Row],[Capacity (MW)]]*0.395*8760*10^-6 -> 0.276816 | R32: {=AVERAGE(VLOOKUP(_xlfn.TEXTSPLIT(Table1[[#This Row],[Fuel (no space after comma)]], ","), FuelList_Final_EF!$A$2:$B$65, 2, FALSE))} -> 53.06 | S32: =Table1[[#This Row],[Generation (TWh)]]*10^9*VLOOKUP(Table1[[#This Row],[Turbine/Engine Technology]],Technology_HR!$A$2:$B$11,2,FALSE)*10^-6 -> 3047744.2 | T32: =Table1[[#This Row],[Fuel Consumption (mmBtu)]]*Table1[[#This Row],[Emission Factor (kg CO2/ mmBtu)]]*10^3 -> 1.6171331e+11 | U32: =Table1[[#This Row],[Emissions (g CO2)]]/(Table1[[#This Row],[Generation (TWh)]]*10^9) -> 584.1906
A33: sonelgaz spa | B33: fossil gas: natural gas | C33: =SUBSTITUTE(Table1[[#This Row],[Fuel]],", ",",") -> fossil gas: natural gas | D33: fossil gas: natural gas | H33: gas turbine | I33: 80 | J33: construction | K33: N/A | L33: N/A | M33: N/A | N33: 27.183923 | O33: 2.435821 | P33: algeria | Q33: =Table1[[#This Row],[Capacity (MW)]]*0.395*8760*10^-6 -> 0.276816 | R33: {=AVERAGE(VLOOKUP(_xlfn.TEXTSPLIT(Table1[[#This Row],[Fuel (no space after comma)]], ","), FuelList_Final_EF!$A$2:$B$65, 2, FALSE))} -> 53.06 | S33: =Table1[[#This Row],[Generation (TWh)]]*10^9*VLOOKUP(Table1[[#This Row],[Turbine/Engine Technology]],Technology_HR!$A$2:$B$11,2,FALSE)*10^-6 -> 3047744.2 | T33: =Table1[[#This Row],[Fuel Consumption (mmBtu)]]*Table1[[#This Row],[Emission Factor (kg CO2/ mmBtu)]]*10^3 -> 1.6171331e+11 | U33: =Table1[[#This Row],[Emissions (g CO2)]]/(Table1[[#This Row],[Generation (TWh)]]*10^9) -> 584.1906
A34: société algérienne de production de l'electricité spa | B34: fossil gas: natural gas, fossil liquids: fuel oil | C34: =SUBSTITUTE(Table1[[#This Row],[Fuel]],", ",",") -> fossil gas: natural gas,fossil liquids: fuel oil | D34: fossil gas: natural gas | E34: fossil liquids: fuel oil | H34: gas turbine | I34: 146 | J34: operating | K34: 2004 | L34: N/A | M34: N/A | N34: 35.7666 | O34: 7.3619 | P34: algeria | Q34: =Table1[[#This Row],[Capacity (MW)]]*0.395*8760*10^-6 -> 0.5051892 | R34: {=AVERAGE(VLOOKUP(_xlfn.TEXTSPLIT(Table1[[#This Row],[Fuel (no space after comma)]], ","), FuelList_Final_EF!$A$2:$B$65, 2, FALSE))} -> 65.583341 | S34: =Table1[[#This Row],[Generation (TWh)]]*10^9*VLOOKUP(Table1[[#This Row],[Turbine/Engine Technology]],Technology_HR!$A$2:$B$11,2,FALSE)*10^-6 -> 5562133.1 | T34: =Table1[[#This Row],[Fuel Consumption (mmBtu)]]*Table1[[#This Row],[Emission Factor (kg CO2/ mmBtu)]]*10^3 -> 3.6478327e+11 | U34: =Table1[[#This Row],[Emissions (g CO2)]]/(Table1[[#This Row],[Generation (TWh)]]*10^9) -> 722.07259
A35: société algérienne de production de l'electricité spa | B35: fossil gas: natural gas, fossil liquids: fuel oil | C35: =SUBSTITUTE(Table1[[#This Row],[Fuel]],", ",",") -> fossil gas: natural gas,fossil liquids: fuel oil | D35: fossil gas: natural gas | E35: fossil liquids: fuel oil | H35: gas turbine | I35: 146 | J35: operating | K35: 2004 | L35: N/A | M35: N/A | N35: 35.7666 | O35: 7.3619 | P35: algeria | Q35: =Table1[[#This Row],[Capacity (MW)]]*0.395*8760*10^-6 -> 0.5051892 | R35: {=AVERAGE(VLOOKUP(_xlfn.TEXTSPLIT(Table1[[#This Row],[Fuel (no space after comma)]], ","), FuelList_Final_EF!$A$2:$B$65, 2, FALSE))} -> 65.583341 | S35: =Table1[[#This Row],[Generation (TWh)]]*10^9*VLOOKUP(Table1[[#This Row],[Turbine/Engine Technology]],Technology_HR!$A$2:$B$11,2,FALSE)*10^-6 -> 5562133.1 | T35: =Table1[[#This Row],[Fuel Consumption (mmBtu)]]*Table1[[#This Row],[Emission Factor (kg CO2/ mmBtu)]]*10^3 -> 3.6478327e+11 | U35: =Table1[[#This Row],[Emissions (g CO2)]]/(Table1[[#This Row],[Generation (TWh)]]*10^9) -> 722.07259
A36: sharikat kahraba hadjret en nouss spa | B36: fossil gas: natural gas, fossil liquids: fuel oil | C36: =SUBSTITUTE(Table1[[#This Row],[Fuel]],", ",",") -> fossil gas: natural gas,fossil liquids: fuel oil | D36: fossil gas: natural gas | E36: fossil liquids: fuel oil | H36: combined cycle | I36: 409 | J36: operating | K36: 2009 | L36: N/A | M36: N/A | N36: 36.5767 | O36: 2.0797 | P36: algeria | Q36: =Table1[[#This Row],[Capacity (MW)]]*0.395*8760*10^-6 -> 1.4152218 | R36: {=AVERAGE(VLOOKUP(_xlfn.TEXTSPLIT(Table1[[#This Row],[Fuel (no space after comma)]], ","), FuelList_Final_EF!$A$2:$B$65, 2, FALSE))} -> 65.583341 | S36: =Table1[[#This Row],[Generation (TWh)]]*10^9*VLOOKUP(Table1[[#This Row],[Turbine/Engine Technology]],Technology_HR!$A$2:$B$11,2,FALSE)*10^-6 -> 10683509 | T36: =Table1[[#This Row],[Fuel Consumption (mmBtu)]]*Table1[[#This Row],[Emission Factor (kg CO2/ mmBtu)]]*10^3 -> 7.0066024e+11 | U36: =Table1[[#This Row],[Emissions (g CO2)]]/(Table1[[#This Row],[Generation (TWh)]]*10^9) -> 495.08864
A37: sharikat kahraba hadjret en nouss spa | B37: fossil gas: natural gas, fossil liquids: fuel oil | C37: =SUBSTITUTE(Table1[[#This Row],[Fuel]],", ",",") -> fossil gas: natural gas,fossil liquids: fuel oil | D37: fossil gas: natural gas | E37: fossil liquids: fuel oil | H37: combined cycle | I37: 409 | J37: operating | K37: 2009 | L37: N/A | M37: N/A | N37: 36.5767 | O37: 2.0797 | P37: algeria | Q37: =Table1[[#This Row],[Capacity (MW)]]*0.395*8760*10^-6 -> 1.4152218 | R37: {=AVERAGE(VLOOKUP(_xlfn.TEXTSPLIT(Table1[[#This Row],[Fuel (no space after comma)]], ","), FuelList_Final_EF!$A$2:$B$65, 2, FALSE))} -> 65.583341 | S37: =Table1[[#This Row],[Generation (TWh)]]*10^9*VLOOKUP(Table1[[#This Row],[Turbine/Engine Technology]],Technology_HR!$A$2:$B$11,2,FALSE)*10^-6 -> 10683509 | T37: =Table1[[#This Row],[Fuel Consumption (mmBtu)]]*Table1[[#This Row],[Emission Factor (kg CO2/ mmBtu)]]*10^3 -> 7.0066024e+11 | U37: =Table1[[#This Row],[Emissions (g CO2)]]/(Table1[[#This Row],[Generation (TWh)]]*10^9) -> 495.08864
A38: sharikat kahraba hadjret en nouss spa | B38: fossil gas: natural gas, fossil liquids: fuel oil | C38: =SUBSTITUTE(Table1[[#This Row],[Fuel]],", ",",") -> fossil gas: natural gas,fossil liquids: fuel oil | D38: fossil gas: natural gas | E38: fossil liquids: fuel oil | H38: combined cycle | I38: 409 | J38: operating | K38: 2009 | L38: N/A | M38: N/A | N38: 36.5767 | O38: 2.0797 | P38: algeria | Q38: =Table1[[#This Row],[Capacity (MW)]]*0.395*8760*10^-6 -> 1.4152218 | R38: {=AVERAGE(VLOOKUP(_xlfn.TEXTSPLIT(Table1[[#This Row],[Fuel (no space after comma)]], ","), FuelList_Final_EF!$A$2:$B$65, 2, FALSE))} -> 65.583341 | S38: =Table1[[#This Row],[Generation (TWh)]]*10^9*VLOOKUP(Table1[[#This Row],[Turbine/Engine Technology]],Technology_HR!$A$2:$B$11,2,FALSE)*10^-6 -> 10683509 | T38: =Table1[[#This Row],[Fuel Consumption (mmBtu)]]*Table1[[#This Row],[Emission Factor (kg CO2/ mmBtu)]]*10^3 -> 7.0066024e+11 | U38: =Table1[[#This Row],[Emissions (g CO2)]]/(Table1[[#This Row],[Generation (TWh)]]*10^9) -> 495.08864
A39: société algérienne de production de l'electricité spa | B39: fossil gas: natural gas, fossil liquids: fuel oil | C39: =SUBSTITUTE(Table1[[#This Row],[Fuel]],", ",",") -> fossil gas: natural gas,fossil liquids: fuel oil | D39: fossil gas: natural gas | E39: fossil liquids: fuel oil | H39: gas turbine | I39: 209 | J39: operating | K39: 2002 | L39: N/A | M39: N/A | N39: 36.7489 | O39: 3.0823 | P39: algeria | Q39: =Table1[[#This Row],[Capacity (MW)]]*0.395*8760*10^-6 -> 0.7231818 | R39: {=AVERAGE(VLOOKUP(_xlfn.TEXTSPLIT(Table1[[#This Row],[Fuel (no space after comma)]], ","), FuelList_Final_EF!$A$2:$B$65, 2, FALSE))} -> 65.583341 | S39: =Table1[[#This Row],[Generation (TWh)]]*10^9*VLOOKUP(Table1[[#This Row],[Turbine/Engine Technology]],Technology_HR!$A$2:$B$11,2,FALSE)*10^-6 -> 7962231.6 | T39: =Table1[[#This Row],[Fuel Consumption (mmBtu)]]*Table1[[#This Row],[Emission Factor (kg CO2/ mmBtu)]]*10^3 -> 5.2218975e+11 | U39: =Table1[[#This Row],[Emissions (g CO2)]]/(Table1[[#This Row],[Generation (TWh)]]*10^9) -> 722.07259
A40: société algérienne de production de l'electricité spa | B40: fossil gas: natural gas, fossil liquids: fuel oil | C40: =SUBSTITUTE(Table1[[#This Row],[Fuel]],", ",",") -> fossil gas: natural gas,fossil liquids: fuel oil | D40: fossil gas: natural gas | E40: fossil liquids: fuel oil | H40: gas turbine | I40: 209 | J40: operating | K40: 2002 | L40: N/A | M40: N/A | N40: 36.7489 | O40: 3.0823 | P40: algeria | Q40: =Table1[[#This Row],[Capacity (MW)]]*0.395*8760*10^-6 -> 0.7231818 | R40: {=AVERAGE(VLOOKUP(_xlfn.TEXTSPLIT(Table1[[#This Row],[Fuel (no space after comma)]], ","), FuelList_Final_EF!$A$2:$B$65, 2, FALSE))} -> 65.583341 | S40: =Table1[[#This Row],[Generation (TWh)]]*10^9*VLOOKUP(Table1[[#This Row],[Turbine/Engine Technology]],Technology_HR!$A$2:$B$11,2,FALSE)*10^-6 -> 7962231.6 | T40: =Table1[[#This Row],[Fuel Consumption (mmBtu)]]*Table1[[#This Row],[Emission Factor (kg CO2/ mmBtu)]]*10^3 -> 5.2218975e+11 | U40: =Table1[[#This Row],[Emissions (g CO2)]]/(Table1[[#This Row],[Generation (TWh)]]*10^9) -> 722.07259
A41: sonelgaz spa | B41: fossil gas: natural gas | C41: =SUBSTITUTE(Table1[[#This Row],[Fuel]],", ",",") -> fossil gas: natural gas | D41: fossil gas: natural gas | H41: gas turbine | I41: 184 | J41: operating | K41: N/A | L41: N/A | M41: N/A | N41: 35.766621 | O41: -0.167885 | P41: algeria | Q41: =Table1[[#This Row],[Capacity (MW)]]*0.395*8760*10^-6 -> 0.6366768 | R41: {=AVERAGE(VLOOKUP(_xlfn.TEXTSPLIT(Table1[[#This Row],[Fuel (no space after comma)]], ","), FuelList_Final_EF!$A$2:$B$65, 2, FALSE))} -> 53.06 | S41: =Table1[[#This Row],[Generation (TWh)]]*10^9*VLOOKUP(Table1[[#This Row],[Turbine/Engine Technology]],Technology_HR!$A$2:$B$11,2,FALSE)*10^-6 -> 7009811.6 | T41: =Table1[[#This Row],[Fuel Consumption (mmBtu)]]*Table1[[#This Row],[Emission Factor (kg CO2/ mmBtu)]]*10^3 -> 3.719406e+11 | U41: =Table1[[#This Row],[Emissions (g CO2)]]/(Table1[[#This Row],[Generation (TWh)]]*10^9) -> 584.1906
A42: sonatrach spa | B42: fossil gas: natural gas | C42: =SUBSTITUTE(Table1[[#This Row],[Fuel]],", ",",") -> fossil gas: natural gas | D42: fossil gas: natural gas | H42: gas turbine | I42: 100 | J42: operating | K42: 2001 | L42: N/A | M42: N/A | N42: 30.823292 | O42: 8.03001 | P42: algeria | Q42: =Table1[[#This Row],[Capacity (MW)]]*0.395*8760*10^-6 -> 0.34602 | R42: {=AVERAGE(VLOOKUP(_xlfn.TEXTSPLIT(Table1[[#This Row],[Fuel (no space after comma)]], ","), FuelList_Final_EF!$A$2:$B$65, 2, FALSE))} -> 53.06 | S42: =Table1[[#This Row],[Generation (TWh)]]*10^9*VLOOKUP(Table1[[#This Row],[Turbine/Engine Technology]],Technology_HR!$A$2:$B$11,2,FALSE)*10^-6 -> 3809680.2 | T42: =Table1[[#This Row],[Fuel Consumption (mmBtu)]]*Table1[[#This Row],[Emission Factor (kg CO2/ mmBtu)]]*10^3 -> 202141631412 | U42: =Table1[[#This Row],[Emissions (g CO2)]]/(Table1[[#This Row],[Generation (TWh)]]*10^9) -> 584.1906
A43: sonatrach spa | B43: fossil gas: natural gas | C43: =SUBSTITUTE(Table1[[#This Row],[Fuel]],", ",",") -> fossil gas: natural gas | D43: fossil gas: natural gas | H43: gas turbine | I43: 100 | J43: operating | K43: 2001 | L43: N/A | M43: N/A | N43: 30.823292 | O43: 8.03001 | P43: algeria | Q43: =Table1[[#This Row],[Capacity (MW)]]*0.395*8760*10^-6 -> 0.34602 | R43: {=AVERAGE(VLOOKUP(_xlfn.TEXTSPLIT(Table1[[#This Row],[Fuel (no space after comma)]], ","), FuelList_Final_EF!$A$2:$B$65, 2, FALSE))} -> 53.06 | S43: =Table1[[#This Row],[Generation (TWh)]]*10^9*VLOOKUP(Table1[[#This Row],[Turbine/Engine Technology]],Technology_HR!$A$2:$B$11,2,FALSE)*10^-6 -> 3809680.2 | T43: =Table1[[#This Row],[Fuel Consumption (mmBtu)]]*Table1[[#This Row],[Emission Factor (kg CO2/ mmBtu)]]*10^3 -> 202141631412 | U43: =Table1[[#This Row],[Emissions (g CO2)]]/(Table1[[#This Row],[Generation (TWh)]]*10^9) -> 584.1906
A44: sonatrach spa | B44: fossil gas: natural gas | C44: =SUBSTITUTE(Table1[[#This Row],[Fuel]],", ",",") -> fossil gas: natural gas | D44: fossil gas: natural gas | H44: gas turbine | I44: 100 | J44: operating | K44: 2001 | L44: N/A | M44: N/A | N44: 30.823292 | O44: 8.03001 | P44: algeria | Q44: =Table1[[#This Row],[Capacity (MW)]]*0.395*8760*10^-6 -> 0.34602 | R44: {=AVERAGE(VLOOKUP(_xlfn.TEXTSPLIT(Table1[[#This Row],[Fuel (no space after comma)]], ","), FuelList_Final_EF!$A$2:$B$65, 2, FALSE))} -> 53.06 | S44: =Table1[[#This Row],[Generation (TWh)]]*10^9*VLOOKUP(Table1[[#This Row],[Turbine/Engine Technology]],Technology_HR!$A$2:$B$11,2,FALSE)*10^-6 -> 3809680.2 | T44: =Table1[[#This Row],[Fuel Consumption (mmBtu)]]*Table1[[#This Row],[Emission Factor (kg CO2/ mmBtu)]]*10^3 -> 202141631412 | U44: =Table1[[#This Row],[Emissions (g CO2)]]/(Table1[[#This Row],[Generation (TWh)]]*10^9) -> 584.1906
A45: sonatrach spa | B45: fossil gas: natural gas | C45: =SUBSTITUTE(Table1[[#This Row],[Fuel]],", ",",") -> fossil gas: natural gas | D45: fossil gas: natural gas | H45: gas turbine | I45: 100 | J45: operating | K45: 2016 | L45: N/A | M45: N/A | N45: 30.823292 | O45: 8.03001 | P45: algeria | Q45: =Table1[[#This Row],[Capacity (MW)]]*0.395*8760*10^-6 -> 0.34602 | R45: {=AVERAGE(VLOOKUP(_xlfn.TEXTSPLIT(Table1[[#This Row],[Fuel (no space after comma)]], ","), FuelList_Final_EF!$A$2:$B$65, 2, FALSE))} -> 53.06 | S45: =Table1[[#This Row],[Generation (TWh)]]*10^9*VLOOKUP(Table1[[#This Row],[Turbine/Engine Technology]],Technology_HR!$A$2:$B$11,2,FALSE)*10^-6 -> 3809680.2 | T45: =Table1[[#This Row],[Fuel Consumption (mmBtu)]]*Table1[[#This Row],[Emission Factor (kg CO2/ mmBtu)]]*10^3 -> 202141631412 | U45: =Table1[[#This Row],[Emissions (g CO2)]]/(Table1[[#This Row],[Generation (TWh)]]*10^9) -> 584.1906
A46: société algérienne de production de l'electricité spa | B46: fossil gas: natural gas | C46: =SUBSTITUTE(Table1[[#This Row],[Fuel]],", ",",") -> fossil gas: natural gas | D46: fossil gas: natural gas | H46: gas turbine | I46: 100 | J46: operating | K46: 1988 | L46: N/A | M46: N/A | N46: 31.787607 | O46: 6.051812 | P46: algeria | Q46: =Table1[[#This Row],[Capacity (MW)]]*0.395*8760*10^-6 -> 0.34602 | R46: {=AVERAGE(VLOOKUP(_xlfn.TEXTSPLIT(Table1[[#This Row],[Fuel (no space after comma)]], ","), FuelList_Final_EF!$A$2:$B$65, 2, FALSE))} -> 53.06 | S46: =Table1[[#This Row],[Generation (TWh)]]*10^9*VLOOKUP(Table1[[#This Row],[Turbine/Engine Technology]],Technology_HR!$A$2:$B$11,2,FALSE)*10^-6 -> 3809680.2 | T46: =Table1[[#This Row],[Fuel Consumption (mmBtu)]]*Table1[[#This Row],[Emission Factor (kg CO2/ mmBtu)]]*10^3 -> 202141631412 | U46: =Table1[[#This Row],[Emissions (g CO2)]]/(Table1[[#This Row],[Generation (TWh)]]*10^9) -> 584.1906
A47: société algérienne de production de l'electricité spa | B47: fossil gas: natural gas | C47: =SUBSTITUTE(Table1[[#This Row],[Fuel]],", ",",") -> fossil gas: natural gas | D47: fossil gas: natural gas | H47: gas turbine | I47: 100 | J47: operating | K47: 1988 | L47: N/A | M47: N/A | N47: 31.787607 | O47: 6.051812 | P47: algeria | Q47: =Table1[[#This Row],[Capacity (MW)]]*0.395*8760*10^-6 -> 0.34602 | R47: {=AVERAGE(VLOOKUP(_xlfn.TEXTSPLIT(Table1[[#This Row],[Fuel (no space after comma)]], ","), FuelList_Final_EF!$A$2:$B$65, 2, FALSE))} -> 53.06 | S47: =Table1[[#This Row],[Generation (TWh)]]*10^9*VLOOKUP(Table1[[#This Row],[Turbine/Engine Technology]],Technology_HR!$A$2:$B$11,2,FALSE)*10^-6 -> 3809680.2 | T47: =Table1[[#This Row],[Fuel Consumption (mmBtu)]]*Table1[[#This Row],[Emission Factor (kg CO2/ mmBtu)]]*10^3 -> 202141631412 | U47: =Table1[[#This Row],[Emissions (g CO2)]]/(Table1[[#This Row],[Generation (TWh)]]*10^9) -> 584.1906
A48: société algérienne de production de l'electricité spa | B48: fossil gas: natural gas | C48: =SUBSTITUTE(Table1[[#This Row],[Fuel]],", ",",") -> fossil gas: natural gas | D48: fossil gas: natural gas | H48: gas turbine | I48: 220 | J48: operating | K48: 2015 | L48: N/A | M48: N/A | N48: 31.805889 | O48: 5.996306 | P48: algeria | Q48: =Table1[[#This Row],[Capacity (MW)]]*0.395*8760*10^-6 -> 0.761244 | R48: {=AVERAGE(VLOOKUP(_xlfn.TEXTSPLIT(Table1[[#This Row],[Fuel (no space after comma)]], ","), FuelList_Final_EF!$A$2:$B$65, 2, FALSE))} -> 53.06 | S48: =Table1[[#This Row],[Generation (TWh)]]*10^9*VLOOKUP(Table1[[#This Row],[Turbine/Engine Technology]],Technology_HR!$A$2:$B$11,2,FALSE)*10^-6 -> 8381296.4 | T48: =Table1[[#This Row],[Fuel Consumption (mmBtu)]]*Table1[[#This Row],[Emission Factor (kg CO2/ mmBtu)]]*10^3 -> 4.4471159e+11 | U48: =Table1[[#This Row],[Emissions (g CO2)]]/(Table1[[#This Row],[Generation (TWh)]]*10^9) -> 584.1906
A49: société algérienne de production de l'electricité spa | B49: fossil gas: natural gas | C49: =SUBSTITUTE(Table1[[#This Row],[Fuel]],", ",",") -> fossil gas: natural gas | D49: fossil gas: natural gas | H49: gas turbine | I49: 220 | J49: operating | K49: 2015 | L49: N/A | M49: N/A | N49: 31.805889 | O49: 5.996306 | P49: algeria | Q49: =Table1[[#This Row],[Capacity (MW)]]*0.395*8760*10^-6 -> 0.761244 | R49: {=AVERAGE(VLOOKUP(_xlfn.TEXTSPLIT(Table1[[#This Row],[Fuel (no space after comma)]], ","), FuelList_Final_EF!$A$2:$B$65, 2, FALSE))} -> 53.06 | S49: =Table1[[#This Row],[Generation (TWh)]]*10^9*VLOOKUP(Table1[[#This Row],[Turbine/Engine Technology]],Technology_HR!$A$2:$B$11,2,FALSE)*10^-6 -> 8381296.4 | T49: =Table1[[#This Row],[Fuel Consumption (mmBtu)]]*Table1[[#This Row],[Emission Factor (kg CO2/ mmBtu)]]*10^3 -> 4.4471159e+11 | U49: =Table1[[#This Row],[Emissions (g CO2)]]/(Table1[[#This Row],[Generation (TWh)]]*10^9) -> 584.1906
A50: société algérienne de production de l'electricité spa | B50: fossil gas: natural gas | C50: =SUBSTITUTE(Table1[[#This Row],[Fuel]],", ",",") -> fossil gas: natural gas | D50: fossil gas: natural gas | H50: gas turbine | I50: 220 | J50: operating | K50: 2015 | L50: N/A | M50: N/A | N50: 31.805889 | O50: 5.996306 | P50: algeria | Q50: =Table1[[#This Row],[Capacity (MW)]]*0.395*8760*10^-6 -> 0.761244 | R50: {=AVERAGE(VLOOKUP(_xlfn.TEXTSPLIT(Table1[[#This Row],[Fuel (no space after comma)]], ","), FuelList_Final_EF!$A$2:$B$65, 2, FALSE))} -> 53.06 | S50: =Table1[[#This Row],[Generation (TWh)]]*10^9*VLOOKUP(Table1[[#This Row],[Turbine/Engine Technology]],Technology_HR!$A$2:$B$11,2,FALSE)*10^-6 -> 8381296.4 | T50: =Table1[[#This Row],[Fuel Consumption (mmBtu)]]*Table1[[#This Row],[Emission Factor (kg CO2/ mmBtu)]]*10^3 -> 4.4471159e+11 | U50: =Table1[[#This Row],[Emissions (g CO2)]]/(Table1[[#This Row],[Generation (TWh)]]*10^9) -> 584.1906
A51: société algérienne de production de l'electricité spa | B51: fossil gas: natural gas | C51: =SUBSTITUTE(Table1[[#This Row],[Fuel]],", ",",") -> fossil gas: natural gas | D51: fossil gas: natural gas | H51: gas turbine | I51: 123 | J51: operating | K51: 1999 | L51: N/A | M51: N/A | N51: 31.7609 | O51: 6.023 | P51: algeria | Q51: =Table1[[#This Row],[Capacity (MW)]]*0.395*8760*10^-6 -> 0.4256046 | R51: {=AVERAGE(VLOOKUP(_xlfn.TEXTSPLIT(Table1[[#This Row],[Fuel (no space after comma)]], ","), FuelList_Final_EF!$A$2:$B$65, 2, FALSE))} -> 53.06 | S51: =Table1[[#This Row],[Generation (TWh)]]*10^9*VLOOKUP(Table1[[#This Row],[Turbine/Engine Technology]],Technology_HR!$A$2:$B$11,2,FALSE)*10^-6 -> 4685906.6 | T51: =Table1[[#This Row],[Fuel Consumption (mmBtu)]]*Table1[[#This Row],[Emission Factor (kg CO2/ mmBtu)]]*10^3 -> 2.4863421e+11 | U51: =Table1[[#This Row],[Emissions (g CO2)]]/(Table1[[#This Row],[Generation (TWh)]]*10^9) -> 584.1906
A52: société algérienne de production de l'electricité spa | B52: fossil gas: natural gas | C52: =SUBSTITUTE(Table1[[#This Row],[Fuel]],", ",",") -> fossil gas: natural gas | D52: fossil gas: natural gas | H52: gas turbine | I52: 123 | J52: operating | K52: 1999 | L52: N/A | M52: N/A | N52: 31.7609 | O52: 6.023 | P52: algeria | Q52: =Table1[[#This Row],[Capacity (MW)]]*0.395*8760*10^-6 -> 0.4256046 | R52: {=AVERAGE(VLOOKUP(_xlfn.TEXTSPLIT(Table1[[#This Row],[Fuel (no space after comma)]], ","), FuelList_Final_EF!$A$2:$B$65, 2, FALSE))} -> 53.06 | S52: =Table1[[#This Row],[Generation (TWh)]]*10^9*VLOOKUP(Table1[[#This Row],[Turbine/Engine Technology]],Technology_HR!$A$2:$B$11,2,FALSE)*10^-6 -> 4685906.6 | T52: =Table1[[#This Row],[Fuel Consumption (mmBtu)]]*Table1[[#This Row],[Emission Factor (kg CO2/ mmBtu)]]*10^3 -> 2.4863421e+11 | U52: =Table1[[#This Row],[Emissions (g CO2)]]/(Table1[[#This Row],[Generation (TWh)]]*10^9) -> 584.1906
A53: société algérienne de production de l'electricité spa | B53: fossil gas: natural gas | C53: =SUBSTITUTE(Table1[[#This Row],[Fuel]],", ",",") -> fossil gas: natural gas | D53: fossil gas: natural gas | H53: gas turbine | I53: 123 | J53: operating | K53: 2000 | L53: N/A | M53: N/A | N53: 31.7609 | O53: 6.023 | P53: algeria | Q53: =Table1[[#This Row],[Capacity (MW)]]*0.395*8760*10^-6 -> 0.4256046 | R53: {=AVERAGE(VLOOKUP(_xlfn.TEXTSPLIT(Table1[[#This Row],[Fuel (no space after comma)]], ","), FuelList_Final_EF!$A$2:$B$65, 2, FALSE))} -> 53.06 | S53: =Table1[[#This Row],[Generation (TWh)]]*10^9*VLOOKUP(Table1[[#This Row],[Turbine/Engine Technology]],Technology_HR!$A$2:$B$11,2,FALSE)*10^-6 -> 4685906.6 | T53: =Table1[[#This Row],[Fuel Consumption (mmBtu)]]*Table1[[#This Row],[Emission Factor (kg CO2/ mmBtu)]]*10^3 -> 2.4863421e+11 | U53: =Table1[[#This Row],[Emissions (g CO2)]]/(Table1[[#This Row],[Generation (TWh)]]*10^9) -> 584.1906
A54: société algérienne de production de l'electricité spa | B54: fossil gas: natural gas | C54: =SUBSTITUTE(Table1[[#This Row],[Fuel]],", ",",") -> fossil gas: natural gas | D54: fossil gas: natural gas | H54: gas turbine | I54: 123 | J54: operating | K54: 2003 | L54: N/A | M54: N/A | N54: 31.7609 | O54: 6.023 | P54: algeria | Q54: =Table1[[#This Row],[Capacity (MW)]]*0.395*8760*10^-6 -> 0.4256046 | R54: {=AVERAGE(VLOOKUP(_xlfn.TEXTSPLIT(Table1[[#This Row],[Fuel (no space after comma)]], ","), FuelList_Final_EF!$A$2:$B$65, 2, FALSE))} -> 53.06 | S54: =Table1[[#This Row],[Generation (TWh)]]*10^9*VLOOKUP(Table1[[#This Row],[Turbine/Engine Technology]],Technology_HR!$A$2:$B$11,2,FALSE)*10^-6 -> 4685906.6 | T54: =Table1[[#This Row],[Fuel Consumption (mmBtu)]]*Table1[[#This Row],[Emission Factor (kg CO2/ mmBtu)]]*10^3 -> 2.4863421e+11 | U54: =Table1[[#This Row],[Emissions (g CO2)]]/(Table1[[#This Row],[Generation (TWh)]]*10^9) -> 584.1906
A55: sonatrach spa | B55: fossil gas: natural gas, other: other | C55: =SUBSTITUTE(Table1[[#This Row],[Fuel]],", ",",") -> fossil gas: natural gas,other: other | D55: fossil gas: natural gas | E55: other: other | H55: ISCC | I55: 150 | J55: operating | K55: 2011 | L55: N/A | M55: N/A | N55: 33.125166 | O55: 3.356092 | P55: algeria | Q55: =Table1[[#This Row],[Capacity (MW)]]*0.395*8760*10^-6 -> 0.51903 | R55: {=AVERAGE(VLOOKUP(_xlfn.TEXTSPLIT(Table1[[#This Row],[Fuel (no space after comma)]], ","), FuelList_Final_EF!$A$2:$B$65, 2, FALSE))} -> 26.53 | S55: =Table1[[#This Row],[Generation (TWh)]]*10^9*VLOOKUP(Table1[[#This Row],[Turbine/Engine Technology]],Technology_HR!$A$2:$B$11,2,FALSE)*10^-6 -> 3918157.5 | T55: =Table1[[#This Row],[Fuel Consumption (mmBtu)]]*Table1[[#This Row],[Emission Factor (kg CO2/ mmBtu)]]*10^3 -> 1.0394872e+11 | U55: =Table1[[#This Row],[Emissions (g CO2)]]/(Table1[[#This Row],[Generation (TWh)]]*10^9) -> 200.27497
A56: société algérienne de production de l'electricité spa | B56: fossil gas: natural gas, fossil liquids: fuel oil | C56: =SUBSTITUTE(Table1[[#This Row],[Fuel]],", ",",") -> fossil gas: natural gas,fossil liquids: fuel oil | D56: fossil gas: natural gas | E56: fossil liquids: fuel oil | H56: steam turbine | I56: 196 | J56: operating | K56: 1992 | L56: N/A | M56: N/A | N56: 36.8139 | O56: 5.876 | P56: algeria | Q56: =Table1[[#This Row],[Capacity (MW)]]*0.395*8760*10^-6 -> 0.6781992 | R56: {=AVERAGE(VLOOKUP(_xlfn.TEXTSPLIT(Table1[[#This Row],[Fuel (no space after comma)]], ","), FuelList_Final_EF!$A$2:$B$65, 2, FALSE))} -> 65.583341 | S56: =Table1[[#This Row],[Generation (TWh)]]*10^9*VLOOKUP(Table1[[#This Row],[Turbine/Engine Technology]],Technology_HR!$A$2:$B$11,2,FALSE)*10^-6 -> 6975278.8 | T56: =Table1[[#This Row],[Fuel Consumption (mmBtu)]]*Table1[[#This Row],[Emission Factor (kg CO2/ mmBtu)]]*10^3 -> 4.5746209e+11 | U56: =Table1[[#This Row],[Emissions (g CO2)]]/(Table1[[#This Row],[Generation (TWh)]]*10^9) -> 674.52466
A57: société algérienne de production de l'electricité spa | B57: fossil gas: natural gas, fossil liquids: fuel oil | C57: =SUBSTITUTE(Table1[[#This Row],[Fuel]],", ",",") -> fossil gas: natural gas,fossil liquids: fuel oil | D57: fossil gas: natural gas | E57: fossil liquids: fuel oil | H57: steam turbine | I57: 196 | J57: operating | K57: 1993 | L57: N/A | M57: N/A | N57: 36.8139 | O57: 5.876 | P57: algeria | Q57: =Table1[[#This Row],[Capacity (MW)]]*0.395*8760*10^-6 -> 0.6781992 | R57: {=AVERAGE(VLOOKUP(_xlfn.TEXTSPLIT(Table1[[#This Row],[Fuel (no space after comma)]], ","), FuelList_Final_EF!$A$2:$B$65, 2, FALSE))} -> 65.583341 | S57: =Table1[[#This Row],[Generation (TWh)]]*10^9*VLOOKUP(Table1[[#This Row],[Turbine/Engine Technology]],Technology_HR!$A$2:$B$11,2,FALSE)*10^-6 -> 6975278.8 | T57: =Table1[[#This Row],[Fuel Consumption (mmBtu)]]*Table1[[#This Row],[Emission Factor (kg CO2/ mmBtu)]]*10^3 -> 4.5746209e+11 | U57: =Table1[[#This Row],[Emissions (g CO2)]]/(Table1[[#This Row],[Generation (TWh)]]*10^9) -> 674.52466
A58: société algérienne de production de l'electricité spa | B58: fossil gas: natural gas, fossil liquids: fuel oil | C58: =SUBSTITUTE(Table1[[#This Row],[Fuel]],", ",",") -> fossil gas: natural gas,fossil liquids: fuel oil | D58: fossil gas: natural gas | E58: fossil liquids: fuel oil | H58: steam turbine | I58: 196 | J58: operating | K58: 1994 | L58: N/A | M58: N/A | N58: 36.8139 | O58: 5.876 | P58: algeria | Q58: =Table1[[#This Row],[Capacity (MW)]]*0.395*8760*10^-6 -> 0.6781992 | R58: {=AVERAGE(VLOOKUP(_xlfn.TEXTSPLIT(Table1[[#This Row],[Fuel (no space after comma)]], ","), FuelList_Final_EF!$A$2:$B$65, 2, FALSE))} -> 65.583341 | S58: =Table1[[#This Row],[Generation (TWh)]]*10^9*VLOOKUP(Table1[[#This Row],[Turbine/Engine Technology]],Technology_HR!$A$2:$B$11,2,FALSE)*10^-6 -> 6975278.8 | T58: =Table1[[#This Row],[Fuel Consumption (mmBtu)]]*Table1[[#This Row],[Emission Factor (kg CO2/ mmBtu)]]*10^3 -> 4.5746209e+11 | U58: =Table1[[#This Row],[Emissions (g CO2)]]/(Table1[[#This Row],[Generation (TWh)]]*10^9) -> 674.52466
A59: kahrama spa | B59: fossil gas: natural gas | C59: =SUBSTITUTE(Table1[[#This Row],[Fuel]],", ",",") -> fossil gas: natural gas | D59: fossil gas: natural gas | H59: gas turbine | I59: 115 | J59: operating | K59: 2005 | L59: N/A | M59: N/A | N59: 35.806393 | O59: -0.247637 | P59: algeria | Q59: =Table1[[#This Row],[Capacity (MW)]]*0.395*8760*10^-6 -> 0.397923 | R59: {=AVERAGE(VLOOKUP(_xlfn.TEXTSPLIT(Table1[[#This Row],[Fuel (no space after comma)]], ","), FuelList_Final_EF!$A$2:$B$65, 2, FALSE))} -> 53.06 | S59: =Table1[[#This Row],[Generation (TWh)]]*10^9*VLOOKUP(Table1[[#This Row],[Turbine/Engine Technology]],Technology_HR!$A$2:$B$11,2,FALSE)*10^-6 -> 4381132.2 | T59: =Table1[[#This Row],[Fuel Consumption (mmBtu)]]*Table1[[#This Row],[Emission Factor (kg CO2/ mmBtu)]]*10^3 -> 2.3246288e+11 | U59: =Table1[[#This Row],[Emissions (g CO2)]]/(Table1[[#This Row],[Generation (TWh)]]*10^9) -> 584.1906
A60: kahrama spa | B60: fossil gas: natural gas | C60: =SUBSTITUTE(Table1[[#This Row],[Fuel]],", ",",") -> fossil gas: natural gas | D60: fossil gas: natural gas | H60: gas turbine | I60: 115 | J60: operating | K60: 2005 | L60: N/A | M60: N/A | N60: 35.806393 | O60: -0.247637 | P60: algeria | Q60: =Table1[[#This Row],[Capacity (MW)]]*0.395*8760*10^-6 -> 0.397923 | R60: {=AVERAGE(VLOOKUP(_xlfn.TEXTSPLIT(Table1[[#This Row],[Fuel (no space after comma)]], ","), FuelList_Final_EF!$A$2:$B$65, 2, FALSE))} -> 53.06 | S60: =Table1[[#This Row],[Generation (TWh)]]*10^9*VLOOKUP(Table1[[#This Row],[Turbine/Engine Technology]],Technology_HR!$A$2:$B$11,2,FALSE)*10^-6 -> 4381132.2 | T60: =Table1[[#This Row],[Fuel Consumption (mmBtu)]]*Table1[[#This Row],[Emission Factor (kg CO2/ mmBtu)]]*10^3 -> 2.3246288e+11 | U60: =Table1[[#This Row],[Emissions (g CO2)]]/(Table1[[#This Row],[Generation (TWh)]]*10^9) -> 584.1906
A61: kahrama spa | B61: fossil gas: natural gas | C61: =SUBSTITUTE(Table1[[#This Row],[Fuel]],", ",",") -> fossil gas: natural gas | D61: fossil gas: natural gas | H61: gas turbine | I61: 115 | J61: operating | K61: 2005 | L61: N/A | M61: N/A | N61: 35.806393 | O61: -0.247637 | P61: algeria | Q61: =Table1[[#This Row],[Capacity (MW)]]*0.395*8760*10^-6 -> 0.397923 | R61: {=AVERAGE(VLOOKUP(_xlfn.TEXTSPLIT(Table1[[#This Row],[Fuel (no space after comma)]], ","), FuelList_Final_EF!$A$2:$B$65, 2, FALSE))} -> 53.06 | S61: =Table1[[#This Row],[Generation (TWh)]]*10^9*VLOOKUP(Table1[[#This Row],[Turbine/Engine Technology]],Technology_HR!$A$2:$B$11,2,FALSE)*10^-6 -> 4381132.2 | T61: =Table1[[#This Row],[Fuel Consumption (mmBtu)]]*Table1[[#This Row],[Emission Factor (kg CO2/ mmBtu)]]*10^3 -> 2.3246288e+11 | U61: =Table1[[#This Row],[Emissions (g CO2)]]/(Table1[[#This Row],[Generation (TWh)]]*10^9) -> 584.1906
A62: société algérienne de production de l'electricité spa | B62: fossil gas: natural gas, fossil liquids: fuel oil | C62: =SUBSTITUTE(Table1[[#This Row],[Fuel]],", ",",") -> fossil gas: natural gas,fossil liquids: fuel oil | D62: fossil gas: natural gas | E62: fossil liquids: fuel oil | H62: gas turbine | I62: 211 | J62: operating | K62: 2019 | L62: N/A | M62: N/A | N62: 35.550316 | O62: 6.869692 | P62: algeria | Q62: =Table1[[#This Row],[Capacity (MW)]]*0.395*8760*10^-6 -> 0.7301022 | R62: {=AVERAGE(VLOOKUP(_xlfn.TEXTSPLIT(Table1[[#This Row],[Fuel (no space after comma)]], ","), FuelList_Final_EF!$A$2:$B$65, 2, FALSE))} -> 65.583341 | S62: =Table1[[#This Row],[Generation (TWh)]]*10^9*VLOOKUP(Table1[[#This Row],[Turbine/Engine Technology]],Technology_HR!$A$2:$B$11,2,FALSE)*10^-6 -> 8038425.2 | T62: =Table1[[#This Row],[Fuel Consumption (mmBtu)]]*Table1[[#This Row],[Emission Factor (kg CO2/ mmBtu)]]*10^3 -> 5.2718678e+11 | U62: =Table1[[#This Row],[Emissions (g CO2)]]/(Table1[[#This Row],[Generation (TWh)]]*10^9) -> 722.07259
A63: société algérienne de production de l'electricité spa | B63: fossil gas: natural gas, fossil liquids: fuel oil | C63: =SUBSTITUTE(Table1[[#This Row],[Fuel]],", ",",") -> fossil gas: natural gas,fossil liquids: fuel oil | D63: fossil gas: natural gas | E63: fossil liquids: fuel oil | H63: gas turbine | I63: 211 | J63: operating | K63: 2019 | L63: N/A | M63: N/A | N63: 35.550316 | O63: 6.869692 | P63: algeria | Q63: =Table1[[#This Row],[Capacity (MW)]]*0.395*8760*10^-6 -> 0.7301022 | R63: {=AVERAGE(VLOOKUP(_xlfn.TEXTSPLIT(Table1[[#This Row],[Fuel (no space after comma)]], ","), FuelList_Final_EF!$A$2:$B$65, 2, FALSE))} -> 65.583341 | S63: =Table1[[#This Row],[Generation (TWh)]]*10^9*VLOOKUP(Table1[[#This Row],[Turbine/Engine Technology]],Technology_HR!$A$2:$B$11,2,FALSE)*10^-6 -> 8038425.2 | T63: =Table1[[#This Row],[Fuel Consumption (mmBtu)]]*Table1[[#This Row],[Emission Factor (kg CO2/ mmBtu)]]*10^3 -> 5.2718678e+11 | U63: =Table1[[#This Row],[Emissions (g CO2)]]/(Table1[[#This Row],[Generation (TWh)]]*10^9) -> 722.07259
A64: société algérienne de production de l'electricité spa | B64: fossil gas: natural gas, fossil liquids: fuel oil | C64: =SUBSTITUTE(Table1[[#This Row],[Fuel]],", ",",") -> fossil gas: natural gas,fossil liquids: fuel oil | D64: fossil gas: natural gas | E64: fossil liquids: fuel oil | H64: steam turbine | I64: 211 | J64: construction | K64: 2024 | L64: N/A | M64: N/A | N64: 35.550316 | O64: 6.869692 | P64: algeria | Q64: =Table1[[#This Row],[Capacity (MW)]]*0.395*8760*10^-6 -> 0.7301022 | R64: {=AVERAGE(VLOOKUP(_xlfn.TEXTSPLIT(Table1[[#This Row],[Fuel (no space after comma)]], ","), FuelList_Final_EF!$A$2:$B$65, 2, FALSE))} -> 65.583341 | S64: =Table1[[#This Row],[Generation (TWh)]]*10^9*VLOOKUP(Table1[[#This Row],[Turbine/Engine Technology]],Technology_HR!$A$2:$B$11,2,FALSE)*10^-6 -> 7509101.1 | T64: =Table1[[#This Row],[Fuel Consumption (mmBtu)]]*Table1[[#This Row],[Emission Factor (kg CO2/ mmBtu)]]*10^3 -> 4.9247194e+11 | U64: =Table1[[#This Row],[Emissions (g CO2)]]/(Table1[[#This Row],[Generation (TWh)]]*10^9) -> 674.52466
A65: société algérienne de production de l'electricité spa | B65: fossil gas: natural gas, fossil liquids: fuel oil | C65: =SUBSTITUTE(Table1[[#This Row],[Fuel]],", ",",") -> fossil gas: natural gas,fossil liquids: fuel oil | D65: fossil gas: natural gas | E65: fossil liquids: fuel oil | H65: gas turbine | I65: 211 | J65: operating | K65: 2019 | L65: N/A | M65: N/A | N65: 35.550316 | O65: 6.869692 | P65: algeria | Q65: =Table1[[#This Row],[Capacity (MW)]]*0.395*8760*10^-6 -> 0.7301022 | R65: {=AVERAGE(VLOOKUP(_xlfn.TEXTSPLIT(Table1[[#This Row],[Fuel (no space after comma)]], ","), FuelList_Final_EF!$A$2:$B$65, 2, FALSE))} -> 65.583341 | S65: =Table1[[#This Row],[Generation (TWh)]]*10^9*VLOOKUP(Table1[[#This Row],[Turbine/Engine Technology]],Technology_HR!$A$2:$B$11,2,FALSE)*10^-6 -> 8038425.2 | T65: =Table1[[#This Row],[Fuel Consumption (mmBtu)]]*Table1[[#This Row],[Emission Factor (kg CO2/ mmBtu)]]*10^3 -> 5.2718678e+11 | U65: =Table1[[#This Row],[Emissions (g CO2)]]/(Table1[[#This Row],[Generation (TWh)]]*10^9) -> 722.07259
A66: société algérienne de production de l'electricité spa | B66: fossil gas: natural gas, fossil liquids: fuel oil | C66: =SUBSTITUTE(Table1[[#This Row],[Fuel]],", ",",") -> fossil gas: natural gas,fossil liquids: fuel oil | D66: fossil gas: natural gas | E66: fossil liquids: fuel oil | H66: gas turbine | I66: 211 | J66: operating | K66: N/A | L66: N/A | M66: N/A | N66: 35.550316 | O66: 6.869692 | P66: algeria | Q66: =Table1[[#This Row],[Capacity (MW)]]*0.395*8760*10^-6 -> 0.7301022 | R66: {=AVERAGE(VLOOKUP(_xlfn.TEXTSPLIT(Table1[[#This Row],[Fuel (no space after comma)]], ","), FuelList_Final_EF!$A$2:$B$65, 2, FALSE))} -> 65.583341 | S66: =Table1[[#This Row],[Generation (TWh)]]*10^9*VLOOKUP(Table1[[#This Row],[Turbine/Engine Technology]],Technology_HR!$A$2:$B$11,2,FALSE)*10^-6 -> 8038425.2 | T66: =Table1[[#This Row],[Fuel Consumption (mmBtu)]]*Table1[[#This Row],[Emission Factor (kg CO2/ mmBtu)]]*10^3 -> 5.2718678e+11 | U66: =Table1[[#This Row],[Emissions (g CO2)]]/(Table1[[#This Row],[Generation (TWh)]]*10^9) -> 722.07259
A67: société algérienne de production de l'electricité spa | B67: fossil gas: natural gas, fossil liquids: fuel oil | C67: =SUBSTITUTE(Table1[[#This Row],[Fuel]],", ",",") -> fossil gas: natural gas,fossil liquids: fuel oil | D67: fossil gas: natural gas | E67: fossil liquids: fuel oil | H67: steam turbine | I67: 211 | J67: construction | K67: 2024 | L67: N/A | M67: N/A | N67: 35.550316 | O67: 6.869692 | P67: algeria | Q67: =Table1[[#This Row],[Capacity (MW)]]*0.395*8760*10^-6 -> 0.7301022 | R67: {=AVERAGE(VLOOKUP(_xlfn.TEXTSPLIT(Table1[[#This Row],[Fuel (no space after comma)]], ","), FuelList_Final_EF!$A$2:$B$65, 2, FALSE))} -> 65.583341 | S67: =Table1[[#This Row],[Generation (TWh)]]*10^9*VLOOKUP(Table1[[#This Row],[Turbine/Engine Technology]],Technology_HR!$A$2:$B$11,2,FALSE)*10^-6 -> 7509101.1 | T67: =Table1[[#This Row],[Fuel Consumption (mmBtu)]]*Table1[[#This Row],[Emission Factor (kg CO2/ mmBtu)]]*10^3 -> 4.9247194e+11 | U67: =Table1[[#This Row],[Emissions (g CO2)]]/(Table1[[#This Row],[Generation (TWh)]]*10^9) -> 674.52466
A68: shariket karhaba koudiet eddraouch spa | B68: fossil gas: natural gas, fossil liquids: fuel oil | C68: =SUBSTITUTE(Table1[[#This Row],[Fuel]],", ",",") -> fossil gas: natural gas,fossil liquids: fuel oil | D68: fossil gas: natural gas | E68: fossil liquids: fuel oil | H68: combined cycle | I68: 400 | J68: operating | K68: 2013 | L68: N/A | M68: N/A | N68: 36.885 | O68: 8.0778 | P68: algeria | Q68: =Table1[[#This Row],[Capacity (MW)]]*0.395*8760*10^-6 -> 1.38408 | R68: {=AVERAGE(VLOOKUP(_xlfn.TEXTSPLIT(Table1[[#This Row],[Fuel (no space after comma)]], ","), FuelList_Final_EF!$A$2:$B$65, 2, FALSE))} -> 65.583341 | S68: =Table1[[#This Row],[Generation (TWh)]]*10^9*VLOOKUP(Table1[[#This Row],[Turbine/Engine Technology]],Technology_HR!$A$2:$B$11,2,FALSE)*10^-6 -> 10448420 | T68: =Table1[[#This Row],[Fuel Consumption (mmBtu)]]*Table1[[#This Row],[Emission Factor (kg CO2/ mmBtu)]]*10^3 -> 6.8524229e+11 | U68: =Table1[[#This Row],[Emissions (g CO2)]]/(Table1[[#This Row],[Generation (TWh)]]*10^9) -> 495.08864
A69: shariket karhaba koudiet eddraouch spa | B69: fossil gas: natural gas, fossil liquids: fuel oil | C69: =SUBSTITUTE(Table1[[#This Row],[Fuel]],", ",",") -> fossil gas: natural gas,fossil liquids: fuel oil | D69: fossil gas: natural gas | E69: fossil liquids: fuel oil | H69: combined cycle | I69: 400 | J69: operating | K69: 2013 | L69: N/A | M69: N/A | N69: 36.885 | O69: 8.0778 | P69: algeria | Q69: =Table1[[#This Row],[Capacity (MW)]]*0.395*8760*10^-6 -> 1.38408 | R69: {=AVERAGE(VLOOKUP(_xlfn.TEXTSPLIT(Table1[[#This Row],[Fuel (no space after comma)]], ","), FuelList_Final_EF!$A$2:$B$65, 2, FALSE))} -> 65.583341 | S69: =Table1[[#This Row],[Generation (TWh)]]*10^9*VLOOKUP(Table1[[#This Row],[Turbine/Engine Technology]],Technology_HR!$A$2:$B$11,2,FALSE)*10^-6 -> 10448420 | T69: =Table1[[#This Row],[Fuel Consumption (mmBtu)]]*Table1[[#This Row],[Emission Factor (kg CO2/ mmBtu)]]*10^3 -> 6.8524229e+11 | U69: =Table1[[#This Row],[Emissions (g CO2)]]/(Table1[[#This Row],[Generation (TWh)]]*10^9) -> 495.08864
A70: shariket karhaba koudiet eddraouch spa | B70: fossil gas: natural gas, fossil liquids: fuel oil | C70: =SUBSTITUTE(Table1[[#This Row],[Fuel]],", ",",") -> fossil gas: natural gas,fossil liquids: fuel oil | D70: fossil gas: natural gas | E70: fossil liquids: fuel oil | H70: combined cycle | I70: 400 | J70: operating | K70: 2013 | L70: N/A | M70: N/A | N70: 36.885 | O70: 8.0778 | P70: algeria | Q70: =Table1[[#This Row],[Capacity (MW)]]*0.395*8760*10^-6 -> 1.38408 | R70: {=AVERAGE(VLOOKUP(_xlfn.TEXTSPLIT(Table1[[#This Row],[Fuel (no space after comma)]], ","), FuelList_Final_EF!$A$2:$B$65, 2, FALSE))} -> 65.583341 | S70: =Table1[[#This Row],[Generation (TWh)]]*10^9*VLOOKUP(Table1[[#This Row],[Turbine/Engine Technology]],Technology_HR!$A$2:$B$11,2,FALSE)*10^-6 -> 10448420 | T70: =Table1[[#This Row],[Fuel Consumption (mmBtu)]]*Table1[[#This Row],[Emission Factor (kg CO2/ mmBtu)]]*10^3 -> 6.8524229e+11 | U70: =Table1[[#This Row],[Emissions (g CO2)]]/(Table1[[#This Row],[Generation (TWh)]]*10^9) -> 495.08864
A71: société algérienne de production de l'electricité spa | B71: fossil gas: natural gas, fossil liquids: fuel oil | C71: =SUBSTITUTE(Table1[[#This Row],[Fuel]],", ",",") -> fossil gas: natural gas,fossil liquids: fuel oil | D71: fossil gas: natural gas | E71: fossil liquids: fuel oil | H71: gas turbine | I71: 140 | J71: operating | K71: 2015 | L71: N/A | M71: N/A | N71: 34.503822 | O71: 6.982111 | P71: algeria | Q71: =Table1[[#This Row],[Capacity (MW)]]*0.395*8760*10^-6 -> 0.484428 | R71: {=AVERAGE(VLOOKUP(_xlfn.TEXTSPLIT(Table1[[#This Row],[Fuel (no space after comma)]], ","), FuelList_Final_EF!$A$2:$B$65, 2, FALSE))} -> 65.583341 | S71: =Table1[[#This Row],[Generation (TWh)]]*10^9*VLOOKUP(Table1[[#This Row],[Turbine/Engine Technology]],Technology_HR!$A$2:$B$11,2,FALSE)*10^-6 -> 5333552.3 | T71: =Table1[[#This Row],[Fuel Consumption (mmBtu)]]*Table1[[#This Row],[Emission Factor (kg CO2/ mmBtu)]]*10^3 -> 3.4979218e+11 | U71: =Table1[[#This Row],[Emissions (g CO2)]]/(Table1[[#This Row],[Generation (TWh)]]*10^9) -> 722.07259
A72: société algérienne de production de l'electricité spa | B72: fossil gas: natural gas, fossil liquids: fuel oil | C72: =SUBSTITUTE(Table1[[#This Row],[Fuel]],", ",",") -> fossil gas: natural gas,fossil liquids: fuel oil | D72: fossil gas: natural gas | E72: fossil liquids: fuel oil | H72: gas turbine | I72: 140 | J72: operating | K72: 2015 | L72: N/A | M72: N/A | N72: 34.503822 | O72: 6.982111 | P72: algeria | Q72: =Table1[[#This Row],[Capacity (MW)]]*0.395*8760*10^-6 -> 0.484428 | R72: {=AVERAGE(VLOOKUP(_xlfn.TEXTSPLIT(Table1[[#This Row],[Fuel (no space after comma)]], ","), FuelList_Final_EF!$A$2:$B$65, 2, FALSE))} -> 65.583341 | S72: =Table1[[#This Row],[Generation (TWh)]]*10^9*VLOOKUP(Table1[[#This Row],[Turbine/Engine Technology]],Technology_HR!$A$2:$B$11,2,FALSE)*10^-6 -> 5333552.3 | T72: =Table1[[#This Row],[Fuel Consumption (mmBtu)]]*Table1[[#This Row],[Emission Factor (kg CO2/ mmBtu)]]*10^3 -> 3.4979218e+11 | U72: =Table1[[#This Row],[Emissions (g CO2)]]/(Table1[[#This Row],[Generation (TWh)]]*10^9) -> 722.07259
A73: société algérienne de production de l'electricité spa | B73: fossil gas: natural gas, fossil liquids: fuel oil | C73: =SUBSTITUTE(Table1[[#This Row],[Fuel]],", ",",") -> fossil gas: natural gas,fossil liquids: fuel oil | D73: fossil gas: natural gas | E73: fossil liquids: fuel oil | H73: gas turbine | I73: 140 | J73: operating | K73: 2015 | L73: N/A | M73: N/A | N73: 34.503822 | O73: 6.982111 | P73: algeria | Q73: =Table1[[#This Row],[Capacity (MW)]]*0.395*8760*10^-6 -> 0.484428 | R73: {=AVERAGE(VLOOKUP(_xlfn.TEXTSPLIT(Table1[[#This Row],[Fuel (no space after comma)]], ","), FuelList_Final_EF!$A$2:$B$65, 2, FALSE))} -> 65.583341 | S73: =Table1[[#This Row],[Generation (TWh)]]*10^9*VLOOKUP(Table1[[#This Row],[Turbine/Engine Technology]],Technology_HR!$A$2:$B$11,2,FALSE)*10^-6 -> 5333552.3 | T73: =Table1[[#This Row],[Fuel Consumption (mmBtu)]]*Table1[[#This Row],[Emission Factor (kg CO2/ mmBtu)]]*10^3 -> 3.4979218e+11 | U73: =Table1[[#This Row],[Emissions (g CO2)]]/(Table1[[#This Row],[Generation (TWh)]]*10^9) -> 722.07259
A74: société algérienne de production de l'electricité spa | B74: fossil gas: natural gas | C74: =SUBSTITUTE(Table1[[#This Row],[Fuel]],", ",",") -> fossil gas: natural gas | D74: fossil gas: natural gas | H74: gas turbine | I74: 140 | J74: operating | K74: 2010 | L74: N/A | M74: N/A | N74: 36.598949 | O74: 3.137429 | P74: algeria | Q74: =Table1[[#This Row],[Capacity (MW)]]*0.395*8760*10^-6 -> 0.484428 | R74: {=AVERAGE(VLOOKUP(_xlfn.TEXTSPLIT(Table1[[#This Row],[Fuel (no space after comma)]], ","), FuelList_Final_EF!$A$2:$B$65, 2, FALSE))} -> 53.06 | S74: =Table1[[#This Row],[Generation (TWh)]]*10^9*VLOOKUP(Table1[[#This Row],[Turbine/Engine Technology]],Technology_HR!$A$2:$B$11,2,FALSE)*10^-6 -> 5333552.3 | T74: =Table1[[#This Row],[Fuel Consumption (mmBtu)]]*Table1[[#This Row],[Emission Factor (kg CO2/ mmBtu)]]*10^3 -> 2.8299828e+11 | U74: =Table1[[#This Row],[Emissions (g CO2)]]/(Table1[[#This Row],[Generation (TWh)]]*10^9) -> 584.1906
A75: société algérienne de production de l'electricité spa | B75: fossil gas: natural gas | C75: =SUBSTITUTE(Table1[[#This Row],[Fuel]],", ",",") -> fossil gas: natural gas | D75: fossil gas: natural gas | H75: gas turbine | I75: 140 | J75: operating | K75: 2010 | L75: N/A | M75: N/A | N75: 36.598949 | O75: 3.137429 | P75: algeria | Q75: =Table1[[#This Row],[Capacity (MW)]]*0.395*8760*10^-6 -> 0.484428 | R75: {=AVERAGE(VLOOKUP(_xlfn.TEXTSPLIT(Table1[[#This Row],[Fuel (no space after comma)]], ","), FuelList_Final_EF!$A$2:$B$65, 2, FALSE))} -> 53.06 | S75: =Table1[[#This Row],[Generation (TWh)]]*10^9*VLOOKUP(Table1[[#This Row],[Turbine/Engine Technology]],Technology_HR!$A$2:$B$11,2,FALSE)*10^-6 -> 5333552.3 | T75: =Table1[[#This Row],[Fuel Consumption (mmBtu)]]*Table1[[#This Row],[Emission Factor (kg CO2/ mmBtu)]]*10^3 -> 2.8299828e+11 | U75: =Table1[[#This Row],[Emissions (g CO2)]]/(Table1[[#This Row],[Generation (TWh)]]*10^9) -> 584.1906
A76: société algérienne de production de l'electricité spa | B76: fossil gas: natural gas | C76: =SUBSTITUTE(Table1[[#This Row],[Fuel]],", ",",") -> fossil gas: natural gas | D76: fossil gas: natural gas | H76: gas turbine | I76: 140 | J76: operating | K76: 2010 | L76: N/A | M76: N/A | N76: 36.598949 | O76: 3.137429 | P76: algeria | Q76: =Table1[[#This Row],[Capacity (MW)]]*0.395*8760*10^-6 -> 0.484428 | R76: {=AVERAGE(VLOOKUP(_xlfn.TEXTSPLIT(Table1[[#This Row],[Fuel (no space after comma)]], ","), FuelList_Final_EF!$A$2:$B$65, 2, FALSE))} -> 53.06 | S76: =Table1[[#This Row],[Generation (TWh)]]*10^9*VLOOKUP(Table1[[#This Row],[Turbine/Engine Technology]],Technology_HR!$A$2:$B$11,2,FALSE)*10^-6 -> 5333552.3 | T76: =Table1[[#This Row],[Fuel Consumption (mmBtu)]]*Table1[[#This Row],[Emission Factor (kg CO2/ mmBtu)]]*10^3 -> 2.8299828e+11 | U76: =Table1[[#This Row],[Emissions (g CO2)]]/(Table1[[#This Row],[Generation (TWh)]]*10^9) -> 584.1906
A77: société algérienne de production de l'electricité spa | B77: fossil gas: natural gas | C77: =SUBSTITUTE(Table1[[#This Row],[Fuel]],", ",",") -> fossil gas: natural gas | D77: fossil gas: natural gas | H77: gas turbine | I77: 140 | J77: operating | K77: 2010 | L77: N/A | M77: N/A | N77: 36.598949 | O77: 3.137429 | P77: algeria | Q77: =Table1[[#This Row],[Capacity (MW)]]*0.395*8760*10^-6 -> 0.484428 | R77: {=AVERAGE(VLOOKUP(_xlfn.TEXTSPLIT(Table1[[#This Row],[Fuel (no space after comma)]], ","), FuelList_Final_EF!$A$2:$B$65, 2, FALSE))} -> 53.06 | S77: =Table1[[#This Row],[Generation (TWh)]]*10^9*VLOOKUP(Table1[[#This Row],[Turbine/Engine Technology]],Technology_HR!$A$2:$B$11,2,FALSE)*10^-6 -> 5333552.3 | T77: =Table1[[#This Row],[Fuel Consumption (mmBtu)]]*Table1[[#This Row],[Emission Factor (kg CO2/ mmBtu)]]*10^3 -> 2.8299828e+11 | U77: =Table1[[#This Row],[Emissions (g CO2)]]/(Table1[[#This Row],[Generation (TWh)]]*10^9) -> 584.1906
A78: société algérienne de production de l'electricité spa | B78: fossil gas: natural gas | C78: =SUBSTITUTE(Table1[[#This Row],[Fuel]],", ",",") -> fossil gas: natural gas | D78: fossil gas: natural gas | H78: gas turbine | I78: 100 | J78: operating | K78: 1998 | L78: N/A | M78: N/A | N78: 35.708885 | O78: 4.476781 | P78: algeria | Q78: =Table1[[#This Row],[Capacity (MW)]]*0.395*8760*10^-6 -> 0.34602 | R78: {=AVERAGE(VLOOKUP(_xlfn.TEXTSPLIT(Table1[[#This Row],[Fuel (no space after comma)]], ","), FuelList_Final_EF!$A$2:$B$65, 2, FALSE))} -> 53.06 | S78: =Table1[[#This Row],[Generation (TWh)]]*10^9*VLOOKUP(Table1[[#This Row],[Turbine/Engine Technology]],Technology_HR!$A$2:$B$11,2,FALSE)*10^-6 -> 3809680.2 | T78: =Table1[[#This Row],[Fuel Consumption (mmBtu)]]*Table1[[#This Row],[Emission Factor (kg CO2/ mmBtu)]]*10^3 -> 202141631412 | U78: =Table1[[#This Row],[Emissions (g CO2)]]/(Table1[[#This Row],[Generation (TWh)]]*10^9) -> 584.1906
A79: société algérienne de production de l'electricité spa | B79: fossil gas: natural gas | C79: =SUBSTITUTE(Table1[[#This Row],[Fuel]],", ",",") -> fossil gas: natural gas | D79: fossil gas: natural gas | H79: gas turbine | I79: 100 | J79: operating | K79: 1989 | L79: N/A | M79: N/A | N79: 35.708885 | O79: 4.476781 | P79: algeria | Q79: =Table1[[#This Row],[Capacity (MW)]]*0.395*8760*10^-6 -> 0.34602 | R79: {=AVERAGE(VLOOKUP(_xlfn.TEXTSPLIT(Table1[[#This Row],[Fuel (no space after comma)]], ","), FuelList_Final_EF!$A$2:$B$65, 2, FALSE))} -> 53.06 | S79: =Table1[[#This Row],[Generation (TWh)]]*10^9*VLOOKUP(Table1[[#This Row],[Turbine/Engine Technology]],Technology_HR!$A$2:$B$11,2,FALSE)*10^-6 -> 3809680.2 | T79: =Table1[[#This Row],[Fuel Consumption (mmBtu)]]*Table1[[#This Row],[Emission Factor (kg CO2/ mmBtu)]]*10^3 -> 202141631412 | U79: =Table1[[#This Row],[Emissions (g CO2)]]/(Table1[[#This Row],[Generation (TWh)]]*10^9) -> 584.1906
A80: société algérienne de production de l'electricité spa | B80: fossil gas: natural gas | C80: =SUBSTITUTE(Table1[[#This Row],[Fuel]],", ",",") -> fossil gas: natural gas | D80: fossil gas: natural gas | H80: gas turbine | I80: 100 | J80: operating | K80: 1990 | L80: N/A | M80: N/A | N80: 35.708885 | O80: 4.476781 | P80: algeria | Q80: =Table1[[#This Row],[Capacity (MW)]]*0.395*8760*10^-6 -> 0.34602 | R80: {=AVERAGE(VLOOKUP(_xlfn.TEXTSPLIT(Table1[[#This Row],[Fuel (no space after comma)]], ","), FuelList_Final_EF!$A$2:$B$65, 2, FALSE))} -> 53.06 | S80: =Table1[[#This Row],[Generation (TWh)]]*10^9*VLOOKUP(Table1[[#This Row],[Turbine/Engine Technology]],Technology_HR!$A$2:$B$11,2,FALSE)*10^-6 -> 3809680.2 | T80: =Table1[[#This Row],[Fuel Consumption (mmBtu)]]*Table1[[#This Row],[Emission Factor (kg CO2/ mmBtu)]]*10^3 -> 202141631412 | U80: =Table1[[#This Row],[Emissions (g CO2)]]/(Table1[[#This Row],[Generation (TWh)]]*10^9) -> 584.1906
A81: société algérienne de production de l'electricité spa | B81: fossil gas: natural gas, fossil liquids: fuel oil | C81: =SUBSTITUTE(Table1[[#This Row],[Fuel]],", ",",") -> fossil gas: natural gas,fossil liquids: fuel oil | D81: fossil gas: natural gas | E81: fossil liquids: fuel oil | H81: gas turbine | I81: 215 | J81: operating | K81: 2010 | L81: N/A | M81: N/A | N81: 35.708885 | O81: 4.476781 | P81: algeria | Q81: =Table1[[#This Row],[Capacity (MW)]]*0.395*8760*10^-6 -> 0.743943 | R81: {=AVERAGE(VLOOKUP(_xlfn.TEXTSPLIT(Table1[[#This Row],[Fuel (no space after comma)]], ","), FuelList_Final_EF!$A$2:$B$65, 2, FALSE))} -> 65.583341 | S81: =Table1[[#This Row],[Generation (TWh)]]*10^9*VLOOKUP(Table1[[#This Row],[Turbine/Engine Technology]],Technology_HR!$A$2:$B$11,2,FALSE)*10^-6 -> 8190812.4 | T81: =Table1[[#This Row],[Fuel Consumption (mmBtu)]]*Table1[[#This Row],[Emission Factor (kg CO2/ mmBtu)]]*10^3 -> 5.3718085e+11 | U81: =Table1[[#This Row],[Emissions (g CO2)]]/(Table1[[#This Row],[Generation (TWh)]]*10^9) -> 722.07259
A82: société algérienne de production de l'electricité spa | B82: fossil gas: natural gas, fossil liquids: fuel oil | C82: =SUBSTITUTE(Table1[[#This Row],[Fuel]],", ",",") -> fossil gas: natural gas,fossil liquids: fuel oil | D82: fossil gas: natural gas | E82: fossil liquids: fuel oil | H82: gas turbine | I82: 215 | J82: operating | K82: 2010 | L82: N/A | M82: N/A | N82: 35.708885 | O82: 4.476781 | P82: algeria | Q82: =Table1[[#This Row],[Capacity (MW)]]*0.395*8760*10^-6 -> 0.743943 | R82: {=AVERAGE(VLOOKUP(_xlfn.TEXTSPLIT(Table1[[#This Row],[Fuel (no space after comma)]], ","), FuelList_Final_EF!$A$2:$B$65, 2, FALSE))} -> 65.583341 | S82: =Table1[[#This Row],[Generation (TWh)]]*10^9*VLOOKUP(Table1[[#This Row],[Turbine/Engine Technology]],Technology_HR!$A$2:$B$11,2,FALSE)*10^-6 -> 8190812.4 | T82: =Table1[[#This Row],[Fuel Consumption (mmBtu)]]*Table1[[#This Row],[Emission Factor (kg CO2/ mmBtu)]]*10^3 -> 5.3718085e+11 | U82: =Table1[[#This Row],[Emissions (g CO2)]]/(Table1[[#This Row],[Generation (TWh)]]*10^9) -> 722.07259
A83: société algérienne de production de l'electricité spa | B83: fossil gas: natural gas, fossil liquids: fuel oil | C83: =SUBSTITUTE(Table1[[#This Row],[Fuel]],", ",",") -> fossil gas: natural gas,fossil liquids: fuel oil | D83: fossil gas: natural gas | E83: fossil liquids: fuel oil | H83: steam turbine | I83: 168 | J83: operating | K83: 1982 | L83: N/A | M83: N/A | N83: 35.8 | O83: -0.1924 | P83: algeria | Q83: =Table1[[#This Row],[Capacity (MW)]]*0.395*8760*10^-6 -> 0.5813136 | R83: {=AVERAGE(VLOOKUP(_xlfn.TEXTSPLIT(Table1[[#This Row],[Fuel (no space after comma)]], ","), FuelList_Final_EF!$A$2:$B$65, 2, FALSE))} -> 65.583341 | S83: =Table1[[#This Row],[Generation (TWh)]]*10^9*VLOOKUP(Table1[[#This Row],[Turbine/Engine Technology]],Technology_HR!$A$2:$B$11,2,FALSE)*10^-6 -> 5978810.4 | T83: =Table1[[#This Row],[Fuel Consumption (mmBtu)]]*Table1[[#This Row],[Emission Factor (kg CO2/ mmBtu)]]*10^3 -> 3.9211036e+11 | U83: =Table1[[#This Row],[Emissions (g CO2)]]/(Table1[[#This Row],[Generation (TWh)]]*10^9) -> 674.52466
A84: société algérienne de production de l'electricité spa | B84: fossil gas: natural gas, fossil liquids: fuel oil | C84: =SUBSTITUTE(Table1[[#This Row],[Fuel]],", ",",") -> fossil gas: natural gas,fossil liquids: fuel oil | D84: fossil gas: natural gas | E84: fossil liquids: fuel oil | H84: steam turbine | I84: 168 | J84: operating | K84: 1983 | L84: N/A | M84: N/A | N84: 35.8 | O84: -0.1924 | P84: algeria | Q84: =Table1[[#This Row],[Capacity (MW)]]*0.395*8760*10^-6 -> 0.5813136 | R84: {=AVERAGE(VLOOKUP(_xlfn.TEXTSPLIT(Table1[[#This Row],[Fuel (no space after comma)]], ","), FuelList_Final_EF!$A$2:$B$65, 2, FALSE))} -> 65.583341 | S84: =Table1[[#This Row],[Generation (TWh)]]*10^9*VLOOKUP(Table1[[#This Row],[Turbine/Engine Technology]],Technology_HR!$A$2:$B$11,2,FALSE)*10^-6 -> 5978810.4 | T84: =Table1[[#This Row],[Fuel Consumption (mmBtu)]]*Table1[[#This Row],[Emission Factor (kg CO2/ mmBtu)]]*10^3 -> 3.9211036e+11 | U84: =Table1[[#This Row],[Emissions (g CO2)]]/(Table1[[#This Row],[Generation (TWh)]]*10^9) -> 674.52466
A85: société algérienne de production de l'electricité spa | B85: fossil gas: natural gas, fossil liquids: fuel oil | C85: =SUBSTITUTE(Table1[[#This Row],[Fuel]],", ",",") -> fossil gas: natural gas,fossil liquids: fuel oil | D85: fossil gas: natural gas | E85: fossil liquids: fuel oil | H85: steam turbine | I85: 168 | J85: operating | K85: 1984 | L85: N/A | M85: N/A | N85: 35.8 | O85: -0.1924 | P85: algeria | Q85: =Table1[[#This Row],[Capacity (MW)]]*0.395*8760*10^-6 -> 0.5813136 | R85: {=AVERAGE(VLOOKUP(_xlfn.TEXTSPLIT(Table1[[#This Row],[Fuel (no space after comma)]], ","), FuelList_Final_EF!$A$2:$B$65, 2, FALSE))} -> 65.583341 | S85: =Table1[[#This Row],[Generation (TWh)]]*10^9*VLOOKUP(Table1[[#This Row],[Turbine/Engine Technology]],Technology_HR!$A$2:$B$11,2,FALSE)*10^-6 -> 5978810.4 | T85: =Table1[[#This Row],[Fuel Consumption (mmBtu)]]*Table1[[#This Row],[Emission Factor (kg CO2/ mmBtu)]]*10^3 -> 3.9211036e+11 | U85: =Table1[[#This Row],[Emissions (g CO2)]]/(Table1[[#This Row],[Generation (TWh)]]*10^9) -> 674.52466
A86: société algérienne de production de l'electricité spa | B86: fossil gas: natural gas, fossil liquids: fuel oil | C86: =SUBSTITUTE(Table1[[#This Row],[Fuel]],", ",",") -> fossil gas: natural gas,fossil liquids: fuel oil | D86: fossil gas: natural gas | E86: fossil liquids: fuel oil | H86: steam turbine | I86: 168 | J86: operating | K86: 1990 | L86: N/A | M86: N/A | N86: 35.8 | O86: -0.1924 | P86: algeria | Q86: =Table1[[#This Row],[Capacity (MW)]]*0.395*8760*10^-6 -> 0.5813136 | R86: {=AVERAGE(VLOOKUP(_xlfn.TEXTSPLIT(Table1[[#This Row],[Fuel (no space after comma)]], ","), FuelList_Final_EF!$A$2:$B$65, 2, FALSE))} -> 65.583341 | S86: =Table1[[#This Row],[Generation (TWh)]]*10^9*VLOOKUP(Table1[[#This Row],[Turbine/Engine Technology]],Technology_HR!$A$2:$B$11,2,FALSE)*10^-6 -> 5978810.4 | T86: =Table1[[#This Row],[Fuel Consumption (mmBtu)]]*Table1[[#This Row],[Emission Factor (kg CO2/ mmBtu)]]*10^3 -> 3.9211036e+11 | U86: =Table1[[#This Row],[Emissions (g CO2)]]/(Table1[[#This Row],[Generation (TWh)]]*10^9) -> 674.52466
A87: société algérienne de production de l'electricité spa | B87: fossil gas: natural gas, fossil liquids: fuel oil | C87: =SUBSTITUTE(Table1[[#This Row],[Fuel]],", ",",") -> fossil gas: natural gas,fossil liquids: fuel oil | D87: fossil gas: natural gas | E87: fossil liquids: fuel oil | H87: steam turbine | I87: 168 | J87: operating | K87: 1991 | L87: N/A | M87: N/A | N87: 35.8 | O87: -0.1924 | P87: algeria | Q87: =Table1[[#This Row],[Capacity (MW)]]*0.395*8760*10^-6 -> 0.5813136 | R87: {=AVERAGE(VLOOKUP(_xlfn.TEXTSPLIT(Table1[[#This Row],[Fuel (no space after comma)]], ","), FuelList_Final_EF!$A$2:$B$65, 2, FALSE))} -> 65.583341 | S87: =Table1[[#This Row],[Generation (TWh)]]*10^9*VLOOKUP(Table1[[#This Row],[Turbine/Engine Technology]],Technology_HR!$A$2:$B$11,2,FALSE)*10^-6 -> 5978810.4 | T87: =Table1[[#This Row],[Fuel Consumption (mmBtu)]]*Table1[[#This Row],[Emission Factor (kg CO2/ mmBtu)]]*10^3 -> 3.9211036e+11 | U87: =Table1[[#This Row],[Emissions (g CO2)]]/(Table1[[#This Row],[Generation (TWh)]]*10^9) -> 674.52466
A88: société algérienne de production de l'electricité spa | B88: fossil gas: natural gas | C88: =SUBSTITUTE(Table1[[#This Row],[Fuel]],", ",",") -> fossil gas: natural gas | D88: fossil gas: natural gas | H88: combined cycle | I88: 450 | J88: operating | K88: 2024 | L88: N/A | M88: N/A | N88: 36.017915 | O88: 0.127492 | P88: algeria | Q88: =Table1[[#This Row],[Capacity (MW)]]*0.395*8760*10^-6 -> 1.55709 | R88: {=AVERAGE(VLOOKUP(_xlfn.TEXTSPLIT(Table1[[#This Row],[Fuel (no space after comma)]], ","), FuelList_Final_EF!$A$2:$B$65, 2, FALSE))} -> 53.06 | S88: =Table1[[#This Row],[Generation (TWh)]]*10^9*VLOOKUP(Table1[[#This Row],[Turbine/Engine Technology]],Technology_HR!$A$2:$B$11,2,FALSE)*10^-6 -> 11754472 | T88: =Table1[[#This Row],[Fuel Consumption (mmBtu)]]*Table1[[#This Row],[Emission Factor (kg CO2/ mmBtu)]]*10^3 -> 6.2369231e+11 | U88: =Table1[[#This Row],[Emissions (g CO2)]]/(Table1[[#This Row],[Generation (TWh)]]*10^9) -> 400.54994
A89: société algérienne de production de l'electricité spa | B89: fossil gas: natural gas | C89: =SUBSTITUTE(Table1[[#This Row],[Fuel]],", ",",") -> fossil gas: natural gas | D89: fossil gas: natural gas | H89: combined cycle | I89: 500 | J89: construction | K89: 2024 | L89: N/A | M89: N/A | N89: 36.017915 | O89: 0.127492 | P89: algeria | Q89: =Table1[[#This Row],[Capacity (MW)]]*0.395*8760*10^-6 -> 1.7301 | R89: {=AVERAGE(VLOOKUP(_xlfn.TEXTSPLIT(Table1[[#This Row],[Fuel (no space after comma)]], ","), FuelList_Final_EF!$A$2:$B$65, 2, FALSE))} -> 53.06 | S89: =Table1[[#This Row],[Generation (TWh)]]*10^9*VLOOKUP(Table1[[#This Row],[Turbine/Engine Technology]],Technology_HR!$A$2:$B$11,2,FALSE)*10^-6 -> 13060525 | T89: =Table1[[#This Row],[Fuel Consumption (mmBtu)]]*Table1[[#This Row],[Emission Factor (kg CO2/ mmBtu)]]*10^3 -> 692991451194 | U89: =Table1[[#This Row],[Emissions (g CO2)]]/(Table1[[#This Row],[Generation (TWh)]]*10^9) -> 400.54994
A90: société algérienne de production de l'electricité spa | B90: fossil gas: natural gas | C90: =SUBSTITUTE(Table1[[#This Row],[Fuel]],", ",",") -> fossil gas: natural gas | D90: fossil gas: natural gas | H90: combined cycle | I90: 500 | J90: construction | K90: 2024 | L90: N/A | M90: N/A | N90: 36.017915 | O90: 0.127492 | P90: algeria | Q90: =Table1[[#This Row],[Capacity (MW)]]*0.395*8760*10^-6 -> 1.7301 | R90: {=AVERAGE(VLOOKUP(_xlfn.TEXTSPLIT(Table1[[#This Row],[Fuel (no space after comma)]], ","), FuelList_Final_EF!$A$2:$B$65, 2, FALSE))} -> 53.06 | S90: =Table1[[#This Row],[Generation (TWh)]]*10^9*VLOOKUP(Table1[[#This Row],[Turbine/Engine Technology]],Technology_HR!$A$2:$B$11,2,FALSE)*10^-6 -> 13060525 | T90: =Table1[[#This Row],[Fuel Consumption (mmBtu)]]*Table1[[#This Row],[Emission Factor (kg CO2/ mmBtu)]]*10^3 -> 692991451194 | U90: =Table1[[#This Row],[Emissions (g CO2)]]/(Table1[[#This Row],[Generation (TWh)]]*10^9) -> 400.54994
A91: société algérienne de production de l'electricité spa | B91: fossil gas: natural gas, fossil liquids: fuel oil | C91: =SUBSTITUTE(Table1[[#This Row],[Fuel]],", ",",") -> fossil gas: natural gas,fossil liquids: fuel oil | D91: fossil gas: natural gas | E91: fossil liquids: fuel oil | H91: combined cycle | I91: 582 | J91: operating | K91: 2021 | L91: N/A | M91: N/A | N91: 33.475212 | O91: -0.343239 | P91: algeria | Q91: =Table1[[#This Row],[Capacity (MW)]]*0.395*8760*10^-6 -> 2.0138364 | R91: {=AVERAGE(VLOOKUP(_xlfn.TEXTSPLIT(Table1[[#This Row],[Fuel (no space after comma)]], ","), FuelList_Final_EF!$A$2:$B$65, 2, FALSE))} -> 65.583341 | S91: =Table1[[#This Row],[Generation (TWh)]]*10^9*VLOOKUP(Table1[[#This Row],[Turbine/Engine Technology]],Technology_HR!$A$2:$B$11,2,FALSE)*10^-6 -> 15202451 | T91: =Table1[[#This Row],[Fuel Consumption (mmBtu)]]*Table1[[#This Row],[Emission Factor (kg CO2/ mmBtu)]]*10^3 -> 9.9702753e+11 | U91: =Table1[[#This Row],[Emissions (g CO2)]]/(Table1[[#This Row],[Generation (TWh)]]*10^9) -> 495.08864
A92: société algérienne de production de l'electricité spa | B92: fossil gas: natural gas, fossil liquids: fuel oil | C92: =SUBSTITUTE(Table1[[#This Row],[Fuel]],", ",",") -> fossil gas: natural gas,fossil liquids: fuel oil | D92: fossil gas: natural gas | E92: fossil liquids: fuel oil | H92: combined cycle | I92: 582 | J92: operating | K92: 2021 | L92: N/A | M92: N/A | N92: 33.475212 | O92: -0.343239 | P92: algeria | Q92: =Table1[[#This Row],[Capacity (MW)]]*0.395*8760*10^-6 -> 2.0138364 | R92: {=AVERAGE(VLOOKUP(_xlfn.TEXTSPLIT(Table1[[#This Row],[Fuel (no space after comma)]], ","), FuelList_Final_EF!$A$2:$B$65, 2, FALSE))} -> 65.583341 | S92: =Table1[[#This Row],[Generation (TWh)]]*10^9*VLOOKUP(Table1[[#This Row],[Turbine/Engine Technology]],Technology_HR!$A$2:$B$11,2,FALSE)*10^-6 -> 15202451 | T92: =Table1[[#This Row],[Fuel Consumption (mmBtu)]]*Table1[[#This Row],[Emission Factor (kg CO2/ mmBtu)]]*10^3 -> 9.9702753e+11 | U92: =Table1[[#This Row],[Emissions (g CO2)]]/(Table1[[#This Row],[Generation (TWh)]]*10^9) -> 495.08864
A93: société algérienne de production de l'electricité spa | B93: fossil gas: unknown | C93: =SUBSTITUTE(Table1[[#This Row],[Fuel]],", ",",") -> fossil gas: unknown | D93: fossil gas: unknown | H93: unknown | I93: 700 | J93: construction | K93: 2026 | L93: N/A | M93: N/A | N93: 34.98942 | O93: 7.95184 | P93: algeria | Q93: =Table1[[#This Row],[Capacity (MW)]]*0.395*8760*10^-6 -> 2.42214 | R93: {=AVERAGE(VLOOKUP(_xlfn.TEXTSPLIT(Table1[[#This Row],[Fuel (no space after comma)]], ","), FuelList_Final_EF!$A$2:$B$65, 2, FALSE))} -> 60.319164 | S93: =Table1[[#This Row],[Generation (TWh)]]*10^9*VLOOKUP(Table1[[#This Row],[Turbine/Engine Technology]],Technology_HR!$A$2:$B$11,2,FALSE)*10^-6 -> 20092862 | T93: =Table1[[#This Row],[Fuel Consumption (mmBtu)]]*Table1[[#This Row],[Emission Factor (kg CO2/ mmBtu)]]*10^3 -> 1.2119847e+12 | U93: =Table1[[#This Row],[Emissions (g CO2)]]/(Table1[[#This Row],[Generation (TWh)]]*10^9) -> 500.37762
A94: société algérienne de production de l'electricité spa | B94: fossil gas: natural gas, fossil liquids: fuel oil | C94: =SUBSTITUTE(Table1[[#This Row],[Fuel]],", ",",") -> fossil gas: natural gas,fossil liquids: fuel oil | D94: fossil gas: natural gas | E94: fossil liquids: fuel oil | H94: combined cycle | I94: 500 | J94: operating | K94: 2021 | L94: N/A | M94: N/A | N94: 34.441042 | O94: 5.889285 | P94: algeria | Q94: =Table1[[#This Row],[Capacity (MW)]]*0.395*8760*10^-6 -> 1.7301 | R94: {=AVERAGE(VLOOKUP(_xlfn.TEXTSPLIT(Table1[[#This Row],[Fuel (no space after comma)]], ","), FuelList_Final_EF!$A$2:$B$65, 2, FALSE))} -> 65.583341 | S94: =Table1[[#This Row],[Generation (TWh)]]*10^9*VLOOKUP(Table1[[#This Row],[Turbine/Engine Technology]],Technology_HR!$A$2:$B$11,2,FALSE)*10^-6 -> 13060525 | T94: =Table1[[#This Row],[Fuel Consumption (mmBtu)]]*Table1[[#This Row],[Emission Factor (kg CO2/ mmBtu)]]*10^3 -> 8.5655286e+11 | U94: =Table1[[#This Row],[Emissions (g CO2)]]/(Table1[[#This Row],[Generation (TWh)]]*10^9) -> 495.08864
A95: société algérienne de production de l'electricité spa | B95: fossil gas: natural gas, fossil liquids: fuel oil | C95: =SUBSTITUTE(Table1[[#This Row],[Fuel]],", ",",") -> fossil gas: natural gas,fossil liquids: fuel oil | D95: fossil gas: natural gas | E95: fossil liquids: fuel oil | H95: combined cycle | I95: 500 | J95: operating | K95: 2022 | L95: N/A | M95: N/A | N95: 34.441042 | O95: 5.889285 | P95: algeria | Q95: =Table1[[#This Row],[Capacity (MW)]]*0.395*8760*10^-6 -> 1.7301 | R95: {=AVERAGE(VLOOKUP(_xlfn.TEXTSPLIT(Table1[[#This Row],[Fuel (no space after comma)]], ","), FuelList_Final_EF!$A$2:$B$65, 2, FALSE))} -> 65.583341 | S95: =Table1[[#This Row],[Generation (TWh)]]*10^9*VLOOKUP(Table1[[#This Row],[Turbine/Engine Technology]],Technology_HR!$A$2:$B$11,2,FALSE)*10^-6 -> 13060525 | T95: =Table1[[#This Row],[Fuel Consumption (mmBtu)]]*Table1[[#This Row],[Emission Factor (kg CO2/ mmBtu)]]*10^3 -> 8.5655286e+11 | U95: =Table1[[#This Row],[Emissions (g CO2)]]/(Table1[[#This Row],[Generation (TWh)]]*10^9) -> 495.08864
A96: société algérienne de production de l'electricité spa | B96: fossil gas: natural gas, fossil liquids: fuel oil | C96: =SUBSTITUTE(Table1[[#This Row],[Fuel]],", ",",") -> fossil gas: natural gas,fossil liquids: fuel oil | D96: fossil gas: natural gas | E96: fossil liquids: fuel oil | H96: gas turbine | I96: 228 | J96: operating | K96: 2016 | L96: N/A | M96: N/A | N96: 34.441042 | O96: 5.889285 | P96: algeria | Q96: =Table1[[#This Row],[Capacity (MW)]]*0.395*8760*10^-6 -> 0.7889256 | R96: {=AVERAGE(VLOOKUP(_xlfn.TEXTSPLIT(Table1[[#This Row],[Fuel (no space after comma)]], ","), FuelList_Final_EF!$A$2:$B$65, 2, FALSE))} -> 65.583341 | S96: =Table1[[#This Row],[Generation (TWh)]]*10^9*VLOOKUP(Table1[[#This Row],[Turbine/Engine Technology]],Technology_HR!$A$2:$B$11,2,FALSE)*10^-6 -> 8686070.9 | T96: =Table1[[#This Row],[Fuel Consumption (mmBtu)]]*Table1[[#This Row],[Emission Factor (kg CO2/ mmBtu)]]*10^3 -> 5.6966155e+11 | U96: =Table1[[#This Row],[Emissions (g CO2)]]/(Table1[[#This Row],[Generation (TWh)]]*10^9) -> 722.07259
A97: société algérienne de production de l'electricité spa | B97: fossil gas: natural gas, fossil liquids: fuel oil | C97: =SUBSTITUTE(Table1[[#This Row],[Fuel]],", ",",") -> fossil gas: natural gas,fossil liquids: fuel oil | D97: fossil gas: natural gas | E97: fossil liquids: fuel oil | H97: gas turbine | I97: 228 | J97: operating | K97: 2017 | L97: N/A | M97: N/A | N97: 34.441042 | O97: 5.889285 | P97: algeria | Q97: =Table1[[#This Row],[Capacity (MW)]]*0.395*8760*10^-6 -> 0.7889256 | R97: {=AVERAGE(VLOOKUP(_xlfn.TEXTSPLIT(Table1[[#This Row],[Fuel (no space after comma)]], ","), FuelList_Final_EF!$A$2:$B$65, 2, FALSE))} -> 65.583341 | S97: =Table1[[#This Row],[Generation (TWh)]]*10^9*VLOOKUP(Table1[[#This Row],[Turbine/Engine Technology]],Technology_HR!$A$2:$B$11,2,FALSE)*10^-6 -> 8686070.9 | T97: =Table1[[#This Row],[Fuel Consumption (mmBtu)]]*Table1[[#This Row],[Emission Factor (kg CO2/ mmBtu)]]*10^3 -> 5.6966155e+11 | U97: =Table1[[#This Row],[Emissions (g CO2)]]/(Table1[[#This Row],[Generation (TWh)]]*10^9) -> 722.07259
A98: hyunson engineering and construction spa | B98: fossil gas: natural gas | C98: =SUBSTITUTE(Table1[[#This Row],[Fuel]],", ",",") -> fossil gas: natural gas | D98: fossil gas: natural gas | H98: combined cycle | I98: 1294 | J98: construction | K98: 2024 | L98: N/A | M98: N/A | N98: 34.441042 | O98: 5.889285 | P98: algeria | Q98: =Table1[[#This Row],[Capacity (MW)]]*0.395*8760*10^-6 -> 4.4774988 | R98: {=AVERAGE(VLOOKUP(_xlfn.TEXTSPLIT(Table1[[#This Row],[Fuel (no space after comma)]], ","), FuelList_Final_EF!$A$2:$B$65, 2, FALSE))} -> 53.06 | S98: =Table1[[#This Row],[Generation (TWh)]]*10^9*VLOOKUP(Table1[[#This Row],[Turbine/Engine Technology]],Technology_HR!$A$2:$B$11,2,FALSE)*10^-6 -> 33800638 | T98: =Table1[[#This Row],[Fuel Consumption (mmBtu)]]*Table1[[#This Row],[Emission Factor (kg CO2/ mmBtu)]]*10^3 -> 1.7934619e+12 | U98: =Table1[[#This Row],[Emissions (g CO2)]]/(Table1[[#This Row],[Generation (TWh)]]*10^9) -> 400.54994
A99: société algérienne de production de l'electricité spa | B99: fossil gas: natural gas, fossil liquids: light fuel oil | C99: =SUBSTITUTE(Table1[[#This Row],[Fuel]],", ",",") -> fossil gas: natural gas,fossil liquids: light fuel oil | D99: fossil gas: natural gas | E99: fossil liquids: light fuel oil | H99: steam turbine | I99: 168 | J99: operating | K99: 1986 | L99: N/A | M99: N/A | N99: 36.849894 | O99: 3.699716 | P99: algeria | Q99: =Table1[[#This Row],[Capacity (MW)]]*0.395*8760*10^-6 -> 0.5813136 | R99: {=AVERAGE(VLOOKUP(_xlfn.TEXTSPLIT(Table1[[#This Row],[Fuel (no space after comma)]], ","), FuelList_Final_EF!$A$2:$B$65, 2, FALSE))} -> 65.591676 | S99: =Table1[[#This Row],[Generation (TWh)]]*10^9*VLOOKUP(Table1[[#This Row],[Turbine/Engine Technology]],Technology_HR!$A$2:$B$11,2,FALSE)*10^-6 -> 5978810.4 | T99: =Table1[[#This Row],[Fuel Consumption (mmBtu)]]*Table1[[#This Row],[Emission Factor (kg CO2/ mmBtu)]]*10^3 -> 3.921602e+11 | U99: =Table1[[#This Row],[Emissions (g CO2)]]/(Table1[[#This Row],[Generation (TWh)]]*10^9) -> 674.61039
A100: société algérienne de production de l'electricité spa | B100: fossil gas: natural gas, fossil liquids: light fuel oil | C100: =SUBSTITUTE(Table1[[#This Row],[Fuel]],", ",",") -> fossil gas: natural gas,fossil liquids: light fuel oil | D100: fossil gas: natural gas | E100: fossil liquids: light fuel oil | H100: steam turbine | I100: 168 | J100: operating | K100: 1986 | L100: N/A | M100: N/A | N100: 36.849894 | O100: 3.699716 | P100: algeria | Q100: =Table1[[#This Row],[Capacity (MW)]]*0.395*8760*10^-6 -> 0.5813136 | R100: {=AVERAGE(VLOOKUP(_xlfn.TEXTSPLIT(Table1[[#This Row],[Fuel (no space after comma)]], ","), FuelList_Final_EF!$A$2:$B$65, 2, FALSE))} -> 65.591676 | S100: =Table1[[#This Row],[Generation (TWh)]]*10^9*VLOOKUP(Table1[[#This Row],[Turbine/Engine Technology]],Technology_HR!$A$2:$B$11,2,FALSE)*10^-6 -> 5978810.4 | T100: =Table1[[#This Row],[Fuel Consumption (mmBtu)]]*Table1[[#This Row],[Emission Factor (kg CO2/ mmBtu)]]*10^3 -> 3.921602e+11 | U100: =Table1[[#This Row],[Emissions (g CO2)]]/(Table1[[#This Row],[Generation (TWh)]]*10^9) -> 674.61039
...

Sheet Technology_HR
A1: Technology | B1: Heat Rate (Btu/ kWh) | C1: Source | D1: Comment
A2: {=_xlfn.UNIQUE(Gas_Oil_Data!H2:H14163)} -> gas turbine | B2: 11010 | C2: https://www.eia.gov/electricity/annual/html/epa_08_02.html
A3: internal combustion | B3: 8900 | C3: https://www.eia.gov/electricity/annual/html/epa_08_02.html
A4: combined cycle | B4: 7549 | C4: https://www.eia.gov/electricity/annual/html/epa_08_02.html
A5: unknown | B5: =AVERAGE(B2:B4,B6:B9,B11) -> 8295.5 | C5: Average of all
A6: ISCC | B6: 7549 | C6: https://www.eia.gov/electricity/annual/html/epa_08_02.html | D6: Combined cycle
A7: steam turbine | B7: 10285 | C7: https://www.eia.gov/electricity/annual/html/epa_08_02.html
A8: ICCC | B8: 7549 | C8: https://www.eia.gov/electricity/annual/html/epa_08_02.html | D8: Combined cycle
A9: AFC | B9: 5973 | C9: https://www.researchgate.net/publication/337168526_Progress_Update_on_the_Allam_Cycle_Commercialization_of_NET_Power_and_the_NET_Power_Demonstration_Facility
A10: N/A | B10: =B5 -> 8295.5 | C10: Average of all
A11: IGCC | B11: 7549 | C11: https://www.eia.gov/electricity/annual/html/epa_08_02.html | D11: Combined cycle

Sheet FuelList_Final_EF
A1: Fuel | B1: Emission Factor (kg CO2/ mmBtu) | C1: Source | D1: Comment
A2: {=_xlfn.UNIQUE(FuelList_IntermediateStep!A2:A111)} -> fossil gas: natural gas | B2: 53.06 | C2: https://www.epa.gov/system/files/documents/2025-01/ghg-emission-factors-hub-2025.pdf
A3: fossil liquids: heavy fuel oil | B3: =77400/948.5 -> 81.60253 | C3: https://www.sciencedirect.com/topics/engineering/specific-emission-factor
A4: fossil gas: lng | B4: =64200/948.5 -> 67.68582 | C4: https://www.ipcc-nggip.iges.or.jp/public/2006gl/pdf/2_Volume2/V2_2_Ch2_Stationary_Combustion.pdf
A5: fossil gas: unknown | B5: =AVERAGE(B2,B4,B7,B10,B47) -> 60.319164 | C5: Average "fossil gas:"
A6: fossil liquids: crude oil | B6: 74.54 | C6: https://www.epa.gov/system/files/documents/2025-01/ghg-emission-factors-hub-2025.pdf
A7: fossil gas: waste heat from natural gas | B7: 66.33 | C7: https://www.epa.gov/system/files/documents/2025-01/ghg-emission-factors-hub-2025.pdf | D7: Steam and Heat
A8: fossil liquids: fuel oil | B8: =266.5/3.412 -> 78.106682 | C8: https://www.volker-quaschning.de/datserv/CO2-spez/index_e.php
A9: fossil liquids: diesel | B9: =266.5/3.412 -> 78.106682 | C9: https://www.volker-quaschning.de/datserv/CO2-spez/index_e.php
A10: fossil gas: coalbed methane | B10: 53.06 | C10: https://www.epa.gov/system/files/documents/2025-01/ghg-emission-factors-hub-2025.pdf | D10: It is a type of natural gas
A11: fossil gas: lng [50%] | B11: =64200/948.5 -> 67.68582 | C11: Lng*(0,5/0,5)
A12: fossil gas: natural gas [95%] | B12: =B2*(0.95/0.5) -> 100.814 | C12: Natural gas*(0,95/05)
A13: other: hydrogen (green) | B13: 0 | C13: https://www.mckinsey.com/industries/automotive-and-assembly/our-insights/how-hydrogen-combustion-engines-can-contribute-to-zero-emissions
A14: fossil gas: natural gas [90%] | B14: =B2*(0.9/0.5) -> 95.508 | C14: Natural gas*(0,9/0,5)
A15: industrial by-product: blast furnace gas | B15: 274.32 | C15: https://www.epa.gov/system/files/documents/2025-01/ghg-emission-factors-hub-2025.pdf
A16: industrial by-product: coke oven gas | B16: 46.85 | C16: https://www.epa.gov/system/files/documents/2025-01/ghg-emission-factors-hub-2025.pdf
A17: fossil liquids: light fuel oil | B17: =74100/948.5 -> 78.123353 | C17: https://www.sciencedirect.com/topics/engineering/specific-emission-factor
A18: industrial by-product: blast furnace gas [90%] | B18: =B15*(0.9/0.5) -> 493.776 | C18: Blast furnace gas*(0,9/0,5)
A19: fossil gas: lng [80%] | B19: =B4*(0.8/0.5) -> 108.29731 | C19: Lng*(0,8/0,5)
A20: fossil liquids: liquefied petroleum gas | B20: 61.71 | C20: https://www.epa.gov/system/files/documents/2025-01/ghg-emission-factors-hub-2025.pdf
A21: fossil gas: natural gas [80%] | B21: =B2*(0.8/0.5) -> 84.896 | C21: Natural gas*(0,8/05)
A22: fossil liquids: naphtha | B22: =73300/948.5 -> 77.279916 | C22: https://www.ipcc-nggip.iges.or.jp/public/2006gl/pdf/2_Volume2/V2_2_Ch2_Stationary_Combustion.pdf
A23: fossil liquids: unknown | B23: =AVERAGE(B3,B6,B8,B9,B17,B20,B22,B26,B27,B31,B50,B62) -> 76.954923 | C23: Average "fossil liquids:"
A24: fossil gas: natural gas [50%] | B24: =B2 -> 53.06 | C24: Natural gas*(0,5/0,5)
A25: other: hydrogen (unknown) | B25: 0 | C25: Average of "other:hydrogen"
A26: fossil liquids: kerosene | B26: 75.2 | C26: https://www.epa.gov/system/files/documents/2025-01/ghg-emission-factors-hub-2025.pdf
A27: fossil liquids: petroleum coke | B27: 102.41 | C27: https://www.epa.gov/system/files/documents/2025-01/ghg-emission-factors-hub-2025.pdf
A28: industrial by-product: blast furnace gas [75%] | B28: =B15*(0.75/0.5) -> 411.48 | C28: Blast furnace gas*(0,75/0,5)
A29: fossil gas: natural gas [70%] | B29: =B2*(0.7/0.5) -> 74.284 | C29: Natural gas*(0,7/0,5)
A30: fossil gas: natural gas [98%] | B30: =B2*(0.98/0.5) -> 103.9976 | C30: Natural gas*(0,98/0,5)
A31: fossil liquids: jet fuel | B31: 72.22 | C31: https://www.epa.gov/system/files/documents/2025-01/ghg-emission-factors-hub-2025.pdf
A32: fossil gas: natural gas [97%] | B32: =B2*(0.97/0.5) -> 102.9364 | C32: Natural gas*(0,97/0,5)
A33: other: other | B33: 0 | C33: Average of "other:"
A34: fossil gas: natural gas [65%] | B34: =B2*(0.65/0.5) -> 68.978 | C34: Natural gas*(0,65/0,5)
A35: 0
A36: coal: unknown | B36: =AVERAGE(B51,B53,B57) -> 100.26357 | C36: Average of "coal:"
A37: other: hydrogen (unknown) [50%] | B37: 0
A38: other: hydrogen (green) [5%] | B38: 0
A39: other: hydrogen (unknown) [10%] | B39: 0
A40: bioenergy: unknown | B40: =AVERAGE(B49,B60,B61,B65) -> 74.0375 | C40: Average of "bioenergy:"
A41: other: hydrogen (green) [10%] | B41: 0
A42: industrial by-product: coke oven gas [10%] | B42: =B16*(0.1/0.5) -> 9.37 | C42: Coke oven gas (0,1/0,5)
A43: other: hydrogen (unknown) [20%] | B43: 0
A44: other: hydrogen (unknown) [30%] | B44: 0
A45: other: hydrogen (blue) | B45: 0 | C45: https://www.mckinsey.com/industries/automotive-and-assembly/our-insights/how-hydrogen-combustion-engines-can-contribute-to-zero-emissions
A46: industrial by-product: | B46: =AVERAGE(B15,B16) -> 160.585 | C46: Average of "industrial by-product:"
A47: fossil gas: gaseous propane | B47: 61.46 | C47: https://www.epa.gov/system/files/documents/2025-01/ghg-emission-factors-hub-2025.pdf
A48: other: hydrogen (green) [50%] | B48: 0
A49: bioenergy: agricultural waste (solids) | B49: 118.17 | C49: https://www.epa.gov/system/files/documents/2025-01/ghg-emission-factors-hub-2025.pdf
A50: fossil liquids: gasoline | B50: 66.88 | C50: https://www.epa.gov/system/files/documents/2025-01/ghg-emission-factors-hub-2025.pdf
A51: coal: waste coal | B51: =94600/948.5 -> 99.736426 | C51: Coal Dataset (from IPCC 2006)
A52: fossil liquids: fuel oil [20%] | B52: =B8*(0.2/0.5) -> 31.242673 | C52: Fuel oil*(0,2/0,5)
A53: coal: subbituminous | B53: =96100/948.5 -> 101.31787 | C53: Coal Dataset (from IPCC 2006)
A54: other: hydrogen (green) [0%] | B54: 0
A55: fossil gas: natural gas [25%] | B55: =B2*(0.25/0.5) -> 26.53 | C55: Natura gas*(0,25/0,5)
A56: other: hydrogen (green) [2%] | B56: 0
A57: coal: bituminous | B57: =94600/948.5 -> 99.736426 | C57: Coal Dataset (from IPCC 2006)
A58: other: hydrogen (unknown) [15%] | B58: 0
A59: other: hydrogen (unknown) [3%] | B59: 0
A60: bioenergy: refuse (landfill gas) | B60: 52.07 | C60: https://www.epa.gov/system/files/documents/2025-01/ghg-emission-factors-hub-2025.pdf
A61: bioenergy: agricultural waste (biogas) | B61: 52.07 | C61: https://www.epa.gov/system/files/documents/2025-01/ghg-emission-factors-hub-2025.pdf
A62: fossil liquids: waste/other oil | B62: =73300/948.5 -> 77.279916 | C62: https://www.ipcc-nggip.iges.or.jp/public/2006gl/pdf/2_Volume2/V2_2_Ch2_Stationary_Combustion.pdf
A63: fossil liquids: diesel [20%] | B63: =B9*(0.2/0.5) -> 31.242673 | C63: Diesel*(0,2/0,5)
A64: other: hydrogen (green) [35%] | B64: 0
A65: bioenergy: biodiesel | B65: 73.84 | C65: https://www.epa.gov/system/files/documents/2025-01/ghg-emission-factors-hub-2025.pdf

Sheet FuelList_IntermediateStep
A1: Fuel: Intermediate Step
A2: {=_xlfn.UNIQUE(Gas_Oil_Data!D2:D14163)} -> fossil gas: natural gas
A3: fossil liquids: heavy fuel oil
A4: fossil gas: lng
A5: fossil gas: unknown
A6: fossil liquids: crude oil
A7: fossil gas: waste heat from natural gas
A8: fossil liquids: fuel oil
A9: fossil liquids: diesel
A10: fossil gas: coalbed methane
A11: fossil gas: lng [50%]
A12: fossil gas: natural gas [95%]
A13: other: hydrogen (green)
A14: fossil gas: natural gas [90%]
... A34: fossil gas: natural gas [65%]
A35: {=_xlfn.UNIQUE(Gas_Oil_Data!E2:E14163)} -> 0
A36: fossil liquids: diesel
A37: fossil liquids: fuel oil
A38: other: other
A39: fossil liquids: light fuel oil
A40: fossil gas: natural gas
A41: coal: unknown
A42: fossil gas: lng
A43: other: hydrogen (unknown) [50%]
A44: other: hydrogen (green) [5%]
A45: fossil liquids: heavy fuel oil
A46: other: hydrogen (unknown) [10%]
A47: industrial by-product: coke oven gas
... A83: other: hydrogen (green) [35%]
A84: {=_xlfn.UNIQUE(Gas_Oil_Data!F2:F14163)} -> 0
A85: fossil liquids: fuel oil
A86: fossil liquids: heavy fuel oil
A87: fossil gas: natural gas
A88: bioenergy: unknown
A89: fossil liquids: diesel
A90: fossil liquids: light fuel oil
A91: fossil gas: lng
A92: other: hydrogen (unknown)
A93: fossil liquids: jet fuel
A94: fossil gas: unknown
A95: fossil liquids: crude oil
A96: fossil liquids: petroleum coke
... A105: bioenergy: biodiesel
A106: {=_xlfn.UNIQUE(Gas_Oil_Data!G2:G14163)} -> 0
A107: other: hydrogen (unknown)
A108: fossil liquids: light fuel oil
A109: fossil liquids: heavy fuel oil
A110: industrial by-product: coke oven gas
A111: fossil liquids: waste/other oil
A112: fossil liquids: fuel oil
